Workbook

Sheet README
A1: Biopunk Housing — composite ranked tracker
A2: Built Aug 22, 2026 from: Incubator Housing Report (Jul 16, 5 research rounds), cost dashboard, master contact sheet, Giulia/Alex Notion tracker, and the May 2026 house-hunt sheet.
A4: TABS
A5: Weights — the scoring inputs (yellow cells). Change a weight and every score on Pipeline and Inventory recalculates.
A6: Pipeline — whole buildings / master-lease targets for the 40–50 person program (Elliot + Ria work this tab). Ranked by Score.
A7: Inventory — bookable beds already operating in SF (from the Notion tracker). This is what incoming founders can use today and the seed for the live portal.
A8: Contacts — every phone/email from the contact sheet, with section. ⚠ = verify by phone before relying on it.
A9: Outreach log — one row per touch. Fill it in; the portal will read outreach status from here.
A10: Templates — email + call scripts, scaled up from the team's existing Gener/Sironi template.
A12: SCORING (0–100, criteria in the order the team stated them)
A13: Transit to Frontier (995 Market): full points ≤10 min walk, 0 at ≥45 min; East Bay / Peninsula / North Bay / Remote = 0.
A14: Price per bed: full points ≤ target ($1,000), linear to 0 at $2,200. Blank price = 5 pts (unknown).
... A23: Priority neighborhoods: SoMa, Nob Hill, Civic Center, FiDi, Union Square, NoPa/Panhandle. East Bay ruled out (too far from Frontier) — rows kept, scored 0 on transit.

Sheet Weights
A1: Input | B1: Value
A2: Transit weight (pts) | B2: 35
A3: Price weight (pts) | B3: 30
A4: Kitchen weight (pts) | B4: 15
A5: Bed-fit weight (pts) | B5: 20
A6: Target $/bed (full price points at or below) | B6: 1000
A7: Max $/bed (0 price points at or above) | B7: 2200
A8: Walk min for full transit points | B8: 10
A9: Walk min for 0 transit points | B9: 45
A10: Sept-15-ready bonus (pts) | B10: 5
A11: Tourist-hotel no-kitchen cap | B11: 40
A12: Cohort size for monthly estimate | B12: 45
A13: Ideal beds low | B13: 40
A14: Ideal beds high | B14: 60
A16: Yellow cells are the only inputs. Weights should sum to 100. Source: team criteria from the Aug 2026 planning call (transit, price, kitchen, bed count) and the Jul 2026 report's budget math.

Sheet Pipeline
A1: Rank | B1: Name | C1: Address | D1: Neighborhood | E1: Region | F1: Walk min to Frontier (est) | G1: Walk source | H1: Type | I1: Rooms / units | J1: Occ. per room | K1: Beds est | L1: $/room low | M1: $/room high | N1: $/bed est | O1: Monthly for cohort ($) | P1: Kitchen | Q1: Status | R1: Source tier | S1: Timeline tags | T1: Sept-15 ready? | U1: AAU? | V1: Baseline? | W1: Price / ask (as sourced) | X1: The play | Y1: Contact | Z1: Phone | AA1: Email / path | AB1: Contact section | AC1: Source links | AD1: Notes | AE1: Transit pts | AF1: Price pts | AG1: Kitchen pts | AH1: Beds pts | AI1: SCORE | AJ1: Outreach status | AK1: Last checked
A2: =RANK(AI2,$AI$2:$AI$70) -> 38 | B2: Moxy Oakland — receiver-held, built 2021 | C2: 2225 Telegraph Ave, Uptown Oakland | D2: Uptown Oakland | E2: East Bay | F2: 45 | G2: est. by neighborhood (geocode in portal) | H2: tourist-hotel | I2: 172 | J2: 1 | K2: =IF(I2="","",I2*J2) -> 172 | L2: 1000 | M2: 1400 | N2: =IF(L2="","",ROUND((L2+M2)/2/J2,0)) -> 1200 | O2: =IF(N2="","",N2*Weights!$B$12) -> 54000 | P2: none | Q2: receivership | R2: Jewel | S2: expansion | T2: no | W2: Receiver collecting $0 — pitch $1,000–1,400/room | X2: Approach receiver Michelle Russo (HotelAVE) | Y2: Michelle Russo, receiver — HotelAVE; also Acore Capital West Coast asset mgmt | Z2: via hotelave.com | AA2: — | AB2: ⭐ Jewels — call these first | AC2: SF Standard: https://sfstandard.com/2026/01/20/oakland-moxy-hotel-closed/ TRD: https://therealdeal.com/san-francisco/2026/01/21/moxy-hotel-shutters-in-oakland-after-loan-default/ Oaklandside: https://oaklandside.org/2026/01/20/moxy-uptown-oakland-stops-taking-hotel-reservations-and-is-expected-to-close/ | AD2: Re-verified July 16: zero movement since January — no sale motion, no auction. Receiver Michelle Russo (HotelAVE) has a dark, brand-new 172-room building earning $0; a master lease is a receiver's dream. Second door: developer Tidewater Capital still carries a live '2225 Telegraph' page in its listings portfolio (tidewatercap.com/listings/2225-telegraph) — call them too, plus Acore's West Coast asset management. | AE2: =IF(LEFT(E2,2)="SF",IF(F2="",0,Weights!$B$2*MAX(0,MIN(1,(Weights!$B$9-F2)/(Weights!$B$9-Weights!$B$8)))),0) -> 0 | AF2: =IF(N2="",5,Weights!$B$3*MAX(0,MIN(1,(Weights!$B$7-N2)/(Weights!$B$7-Weights!$B$6)))) -> 25 | AG2: =IF(P2="none",0,IF(P2="unknown",5,Weights!$B$4)) -> 0 | AH2: =IF(K2="",4,IF(AND(K2>=Weights!$B$13,K2<=Weights!$B$14),Weights!$B$5,IF(K2>100,15,IF(K2>=20,12,4)))) -> 15 | AI2: =IF(OR(Q2="taken",Q2="sold",Q2="ruled-out"),0,MIN(IF(AND(H2="tourist-hotel",P2="none"),Weights!$B$11,100),AE2+AF2+AG2+AH2)+IF(T2="yes",Weights!$B$10,0)) -> 40 | AJ2: not-contacted | AK2: Jul 16 2026 (report)
A3: =RANK(AI3,$AI$2:$AI$70) -> 11 | B3: Crystal Hotel — 'Residential Master Lease available' | C3: 2766–2770 Mission St (at ~24th), Mission, SF | D3: Mission | E3: SF-other | F3: 32 | G3: est. by neighborhood (geocode in portal) | H3: sro-hotel | I3: 45 | J3: 1 | K3: =IF(I3="","",I3*J3) -> 45 | L3: 500 | M3: 500 | N3: =IF(L3="","",ROUND((L3+M3)/2/J3,0)) -> 500 | O3: =IF(N3="","",N3*Weights!$B$12) -> 22500 | P3: communal | Q3: on-market | R3: Jewel | S3: q1-2027 | T3: unknown | W3: $5.5M ask ($122k/room) · listed 2.5 YEARS = highly negotiable | X3: Call broker Richard Ehmer, (415) 225-5176 · rehmer@ehmergroup.com | Y3: Richard Ehmer — The Ehmer Group | Z3: (415) 225-5176 | AA3: rehmer@ehmergroup.com | AB3: ⭐ Jewels — call these first | AC3: LoopNet listing: https://www.loopnet.com/Listing/2766-2770-Mission-St-San-Francisco-CA/30746850/ Showcase: https://www.showcase.com/2766-2770-mission-st-san-francisco-ca-94110/30746850/ | AD3: Published master-lease terms $500/room = $22,500/mo for all 45 rooms. Only 31/45 rooms permitted — pull Chapter 41 split from DBI. | CONFIRMED master-lease terms on the Realmo mirror: $500/room/month = $22,500/mo for the WHOLE 45-room building — less than half the low end of budget, and rooms at this exact building retail at $1,575/mo all-in (a 3x spread). $450k of recent cap-ex incl. soft-story seismic. Diligence flags: only 31 of 45 rooms are permitted; pull the Chapter 41 residential/tourist split from DBI; 24th & Mission street conditions are improving under 2026 police surge but still rough. Someone already branded it 'Crystal Startup Hotel' once — the concept fits. | AE3: =IF(LEFT(E3,2)="SF",IF(F3="",0,Weights!$B$2*MAX(0,MIN(1,(Weights!$B$9-F3)/(Weights!$B$9-Weights!$B$8)))),0) -> 13 | AF3: =IF(N3="",5,Weights!$B$3*MAX(0,MIN(1,(Weights!$B$7-N3)/(Weights!$B$7-Weights!$B$6)))) -> 30 | AG3: =IF(P3="none",0,IF(P3="unknown",5,Weights!$B$4)) -> 15 | AH3: =IF(K3="",4,IF(AND(K3>=Weights!$B$13,K3<=Weights!$B$14),Weights!$B$5,IF(K3>100,15,IF(K3>=20,12,4)))) -> 20 | AI3: =IF(OR(Q3="taken",Q3="sold",Q3="ruled-out"),0,MIN(IF(AND(H3="tourist-hotel",P3="none"),Weights!$B$11,100),AE3+AF3+AG3+AH3)+IF(T3="yes",Weights!$B$10,0)) -> 78 | AJ3: not-contacted | AK3: Jul 16 2026 (report)
A4: =RANK(AI4,$AI$2:$AI$70) -> 19 | B4: Hill Castle Apartments — 160 units at $43k/unit basis | C4: 1431 Jackson St, Lakeside, Downtown Oakland | D4: Downtown Oakland | E4: East Bay | F4: 40 | G4: est. by neighborhood (geocode in portal) | H4: apartment-block | I4: 160 | J4: 1 | K4: =IF(I4="","",I4*J4) -> 160 | L4: 700 | M4: 1000 | N4: =IF(L4="","",ROUND((L4+M4)/2/J4,0)) -> 850 | O4: =IF(N4="","",N4*Weights!$B$12) -> 38250 | P4: private | Q4: active | R4: Jewel | S4: expansion | T4: yes | W4: Sold Mar 30, 2026 for $6.95M ALL-CASH ('downtown fire sale') | X4: Now run by MAG Management — property office (510) 444-6004 | Y4: MAG Management (property office); buyer via 3/30/26 deed pull, Alameda Co. recorder | Z4: (510) 444-6004 | AA4: hillcastle.gaehwiler.com | AB4: ⭐ Jewels — call these first | AC4: Hoodline, Apr 2026: https://hoodline.com/2026/04/oakland-s-hill-castle-dumps-for-6-95-million-in-downtown-fire-sale/ Building leasing page: https://hillcastle.gaehwiler.com/contactus.aspx | AD4: Deep-dive done: buyer is almost certainly the Gaehwiler family (SF owner-operator; their MAG Management runs the building and it's already on their web platform). Studios $1,250–1,575, 1BRs $1,650–1,875, actively leasing with flex terms = classic lease-up pressure. Blocks from Lake Merritt + 12th St BART, Walk Score 98. Direct-deal family operator: MAG main (415) 550-0300; Lana August, tenancy manager, (415) 720-0820, lana.august@magmanagement.com; property office (510) 444-6004. | AE4: =IF(LEFT(E4,2)="SF",IF(F4="",0,Weights!$B$2*MAX(0,MIN(1,(Weights!$B$9-F4)/(Weights!$B$9-Weights!$B$8)))),0) -> 0 | AF4: =IF(N4="",5,Weights!$B$3*MAX(0,MIN(1,(Weights!$B$7-N4)/(Weights!$B$7-Weights!$B$6)))) -> 30 | AG4: =IF(P4="none",0,IF(P4="unknown",5,Weights!$B$4)) -> 15 | AH4: =IF(K4="",4,IF(AND(K4>=Weights!$B$13,K4<=Weights!$B$14),Weights!$B$5,IF(K4>100,15,IF(K4>=20,12,4)))) -> 15 | AI4: =IF(OR(Q4="taken",Q4="sold",Q4="ruled-out"),0,MIN(IF(AND(H4="tourist-hotel",P4="none"),Weights!$B$11,100),AE4+AF4+AG4+AH4)+IF(T4="yes",Weights!$B$10,0)) -> 65 | AJ4: not-contacted | AK4: Jul 16 2026 (report)
A5: =RANK(AI5,$AI$2:$AI$70) -> 38 | B5: Embassy Hotel — 84 rooms, on-market, unencumbered | C5: 610 Polk St (at Turk), Van Ness corridor, SF | D5: Civic Center | E5: SF-priority | F5: 14 | G5: est. by neighborhood (geocode in portal) | H5: tourist-hotel | I5: 84 | J5: 1 | K5: =IF(I5="","",I5*J5) -> 84 | L5: 1100 | M5: 1300 | N5: =IF(L5="","",ROUND((L5+M5)/2/J5,0)) -> 1200 | O5: =IF(N5="","",N5*Weights!$B$12) -> 54000 | P5: none | Q5: on-market | R5: Jewel | S5: q1-2027;expansion | T5: no | W5: For sale via CBRE Hotels; rack rate $55–64/night = struggling | X5: CBRE Hotels listing team; lowball buy or master lease to owner | Y5: CBRE Hotels — SF listing team (ask for 610 Polk St) | Z5: CBRE SF (415) 772-0123 — verify | AA5: cbre.com/properties | AB5: Report §6e | AC5: Hotel News Resource — CBRE listing: https://www.hotelnewsresource.com/article131697.html Hotel site: https://www.theembassyhotelsf.com/ | AD5: The best size/location/price fit found in round 5: fee simple, no brand, no management contract, non-union — nothing standing between the owner and a master lease. At $55/night rack the hotel grosses ~$1,400/room/month at FULL occupancy; a guaranteed $1,100–1,300/room master lease beats their reality. | AE5: =IF(LEFT(E5,2)="SF",IF(F5="",0,Weights!$B$2*MAX(0,MIN(1,(Weights!$B$9-F5)/(Weights!$B$9-Weights!$B$8)))),0) -> 31 | AF5: =IF(N5="",5,Weights!$B$3*MAX(0,MIN(1,(Weights!$B$7-N5)/(Weights!$B$7-Weights!$B$6)))) -> 25 | AG5: =IF(P5="none",0,IF(P5="unknown",5,Weights!$B$4)) -> 0 | AH5: =IF(K5="",4,IF(AND(K5>=Weights!$B$13,K5<=Weights!$B$14),Weights!$B$5,IF(K5>100,15,IF(K5>=20,12,4)))) -> 12 | AI5: =IF(OR(Q5="taken",Q5="sold",Q5="ruled-out"),0,MIN(IF(AND(H5="tourist-hotel",P5="none"),Weights!$B$11,100),AE5+AF5+AG5+AH5)+IF(T5="yes",Weights!$B$10,0)) -> 40 | AJ5: not-contacted | AK5: Jul 16 2026 (report)
A6: =RANK(AI6,$AI$2:$AI$70) -> 38 | B6: Hotel Union Square — 131 rooms, dark since 2021 | C6: 114–120 Powell St, Union Square, SF | D6: Union Square | E6: SF-priority | F6: 8 | G6: est. by neighborhood (geocode in portal) | H6: tourist-hotel | I6: 131 | J6: 1 | K6: =IF(I6="","",I6*J6) -> 131 | L6: 1500 | M6: 2000 | N6: =IF(L6="","",ROUND((L6+M6)/2/J6,0)) -> 1750 | O6: =IF(N6="","",N6*Weights!$B$12) -> 78750 | P6: none | Q6: dark | R6: Jewel | S6: q1-2027;expansion | T6: no | W6: New owner paid ~$30M vs $102M debt wiped | X6: Catch owner before he commits to hotel use | Y6: Owner Mahmood Alam (Faizan Corp, Ukiah) | Z6: (510) 862-3333 (per 2023 CEQA filing) | AA6: alam786@aol.com ⚠ · CA SoS lookup: "Hotel Union Square LLC" | AB6: ⭐ Jewels — call these first | AC6: SF Standard: https://sfstandard.com/2025/09/26/shuttered-union-square-hotel-finds-new-buyer/ | AD6: Shuttered ~5 years; sold Sept 2025 to investor Mahmood Alam at ~$229k/key with no announced plan. A low-basis owner holding a dark building = ideal master-lease counterparty. 131 genuinely nice rooms covers 60 people twice over; target $1,500–2,000/room. | AE6: =IF(LEFT(E6,2)="SF",IF(F6="",0,Weights!$B$2*MAX(0,MIN(1,(Weights!$B$9-F6)/(Weights!$B$9-Weights!$B$8)))),0) -> 35 | AF6: =IF(N6="",5,Weights!$B$3*MAX(0,MIN(1,(Weights!$B$7-N6)/(Weights!$B$7-Weights!$B$6)))) -> 11.25 | AG6: =IF(P6="none",0,IF(P6="unknown",5,Weights!$B$4)) -> 0 | AH6: =IF(K6="",4,IF(AND(K6>=Weights!$B$13,K6<=Weights!$B$14),Weights!$B$5,IF(K6>100,15,IF(K6>=20,12,4)))) -> 15 | AI6: =IF(OR(Q6="taken",Q6="sold",Q6="ruled-out"),0,MIN(IF(AND(H6="tourist-hotel",P6="none"),Weights!$B$11,100),AE6+AF6+AG6+AH6)+IF(T6="yes",Weights!$B$10,0)) -> 40 | AJ6: not-contacted | AK6: Jul 16 2026 (report)
A7: =RANK(AI7,$AI$2:$AI$70) -> 10 | B7: AAU dorm — 736 Jones St | C7: 736 Jones St, Nob Hill, SF | D7: Nob Hill | E7: SF-priority | F7: 18 | G7: est. by neighborhood (geocode in portal) | H7: dorm | I7: 36 | J7: 2 | K7: =IF(I7="","",I7*J7) -> 72 | L7: 1100 | M7: 1500 | N7: =IF(L7="","",ROUND((L7+M7)/2/J7,0)) -> 650 | O7: =IF(N7="","",N7*Weights!$B$12) -> 29250 | P7: communal | Q7: dark | R7: Jewel | S7: bridge-sept;q1-2027;femme-house | T7: unknown | U7: yes | W7: 1055 Pine asks $20M; leases negotiable | X7: One motivated seller — M&M brokers | Y7: AAU Housing Office — existing landlord, warm intro | Z7: via 79 New Montgomery switchboard | AA7: academyart.edu/campus-athletics/housing | AB7: ⭐ Jewels — call these first | AC7: TRD — $130M portfolio: https://therealdeal.com/san-francisco/2025/10/22/san-francisco-art-academy-to-sell-130-million-portfolio/ 1055 Pine LoopNet: https://www.loopnet.com/Listing/1055-Pine-St-San-Francisco-CA/38157856/ AAU housing page: https://www.academyart.edu/campus-athletics/housing/ 736 Jones: https://www.apartments.com/academy-of-art-university-san-francisco-ca/s6esxj6/ | AD7: Round-4 check: none of the dorms is formally listed — the $130M portfolio never included them (its residential pieces, 1055 Pine and 1946 Van Ness, are under contract). AAU's facilities page still shows all four as student housing, though 736 Jones and 860 Sutter were dropped from the current-housing page — mixed signals that only a direct ask resolves. Two routes: the existing landlord relationship, and Marcus & Millichap (handling ALL AAU dispositions) for an off-market approach. Comp: the Commodore dorm-hotel traded at ~$13M (~$115k/key). | AE7: =IF(LEFT(E7,2)="SF",IF(F7="",0,Weights!$B$2*MAX(0,MIN(1,(Weights!$B$9-F7)/(Weights!$B$9-Weights!$B$8)))),0) -> 27 | AF7: =IF(N7="",5,Weights!$B$3*MAX(0,MIN(1,(Weights!$B$7-N7)/(Weights!$B$7-Weights!$B$6)))) -> 30 | AG7: =IF(P7="none",0,IF(P7="unknown",5,Weights!$B$4)) -> 15 | AH7: =IF(K7="",4,IF(AND(K7>=Weights!$B$13,K7<=Weights!$B$14),Weights!$B$5,IF(K7>100,15,IF(K7>=20,12,4)))) -> 12 | AI7: =IF(OR(Q7="taken",Q7="sold",Q7="ruled-out"),0,MIN(IF(AND(H7="tourist-hotel",P7="none"),Weights!$B$11,100),AE7+AF7+AG7+AH7)+IF(T7="yes",Weights!$B$10,0)) -> 84 | AJ7: not-contacted | AK7: Jul 16 2026 (report)
A8: =RANK(AI8,$AI$2:$AI$70) -> 5 | B8: AAU dorm — 860 Sutter St | C8: 860 Sutter St, Nob Hill, SF | D8: Nob Hill | E8: SF-priority | F8: 16 | G8: est. by neighborhood (geocode in portal) | H8: dorm | I8: 60 | J8: 2 | K8: =IF(I8="","",I8*J8) -> 120 | L8: 1100 | M8: 1500 | N8: =IF(L8="","",ROUND((L8+M8)/2/J8,0)) -> 650 | O8: =IF(N8="","",N8*Weights!$B$12) -> 29250 | P8: communal | Q8: dark | R8: Jewel | S8: bridge-sept;q1-2027;expansion | T8: unknown | U8: yes | W8: 1055 Pine asks $20M; leases negotiable | X8: One motivated seller — M&M brokers | Y8: AAU Housing Office — existing landlord, warm intro | Z8: via 79 New Montgomery switchboard | AA8: academyart.edu/campus-athletics/housing | AB8: ⭐ Jewels — call these first | AC8: TRD — $130M portfolio: https://therealdeal.com/san-francisco/2025/10/22/san-francisco-art-academy-to-sell-130-million-portfolio/ 1055 Pine LoopNet: https://www.loopnet.com/Listing/1055-Pine-St-San-Francisco-CA/38157856/ AAU housing page: https://www.academyart.edu/campus-athletics/housing/ 736 Jones: https://www.apartments.com/academy-of-art-university-san-francisco-ca/s6esxj6/ | AD8: Round-4 check: none of the dorms is formally listed — the $130M portfolio never included them (its residential pieces, 1055 Pine and 1946 Van Ness, are under contract). AAU's facilities page still shows all four as student housing, though 736 Jones and 860 Sutter were dropped from the current-housing page — mixed signals that only a direct ask resolves. Two routes: the existing landlord relationship, and Marcus & Millichap (handling ALL AAU dispositions) for an off-market approach. Comp: the Commodore dorm-hotel traded at ~$13M (~$115k/key). | AE8: =IF(LEFT(E8,2)="SF",IF(F8="",0,Weights!$B$2*MAX(0,MIN(1,(Weights!$B$9-F8)/(Weights!$B$9-Weights!$B$8)))),0) -> 29 | AF8: =IF(N8="",5,Weights!$B$3*MAX(0,MIN(1,(Weights!$B$7-N8)/(Weights!$B$7-Weights!$B$6)))) -> 30 | AG8: =IF(P8="none",0,IF(P8="unknown",5,Weights!$B$4)) -> 15 | AH8: =IF(K8="",4,IF(AND(K8>=Weights!$B$13,K8<=Weights!$B$14),Weights!$B$5,IF(K8>100,15,IF(K8>=20,12,4)))) -> 15 | AI8: =IF(OR(Q8="taken",Q8="sold",Q8="ruled-out"),0,MIN(IF(AND(H8="tourist-hotel",P8="none"),Weights!$B$11,100),AE8+AF8+AG8+AH8)+IF(T8="yes",Weights!$B$10,0)) -> 89 | AJ8: not-contacted | AK8: Jul 16 2026 (report)
A9: =RANK(AI9,$AI$2:$AI$70) -> 7 | B9: AAU dorm — 1080 Bush St | C9: 1080 Bush St, Nob Hill, SF | D9: Nob Hill | E9: SF-priority | F9: 17 | G9: est. by neighborhood (geocode in portal) | H9: dorm | I9: 57 | J9: 2 | K9: =IF(I9="","",I9*J9) -> 114 | L9: 1100 | M9: 1500 | N9: =IF(L9="","",ROUND((L9+M9)/2/J9,0)) -> 650 | O9: =IF(N9="","",N9*Weights!$B$12) -> 29250 | P9: communal | Q9: active | R9: Jewel | S9: q1-2027;expansion | T9: unknown | U9: yes | W9: 1055 Pine asks $20M; leases negotiable | X9: One motivated seller — M&M brokers | Y9: AAU Housing Office — existing landlord, warm intro | Z9: via 79 New Montgomery switchboard | AA9: academyart.edu/campus-athletics/housing | AB9: ⭐ Jewels — call these first | AC9: TRD — $130M portfolio: https://therealdeal.com/san-francisco/2025/10/22/san-francisco-art-academy-to-sell-130-million-portfolio/ 1055 Pine LoopNet: https://www.loopnet.com/Listing/1055-Pine-St-San-Francisco-CA/38157856/ AAU housing page: https://www.academyart.edu/campus-athletics/housing/ 736 Jones: https://www.apartments.com/academy-of-art-university-san-francisco-ca/s6esxj6/ | AD9: Round-4 check: none of the dorms is formally listed — the $130M portfolio never included them (its residential pieces, 1055 Pine and 1946 Van Ness, are under contract). AAU's facilities page still shows all four as student housing, though 736 Jones and 860 Sutter were dropped from the current-housing page — mixed signals that only a direct ask resolves. Two routes: the existing landlord relationship, and Marcus & Millichap (handling ALL AAU dispositions) for an off-market approach. Comp: the Commodore dorm-hotel traded at ~$13M (~$115k/key). | AE9: =IF(LEFT(E9,2)="SF",IF(F9="",0,Weights!$B$2*MAX(0,MIN(1,(Weights!$B$9-F9)/(Weights!$B$9-Weights!$B$8)))),0) -> 28 | AF9: =IF(N9="",5,Weights!$B$3*MAX(0,MIN(1,(Weights!$B$7-N9)/(Weights!$B$7-Weights!$B$6)))) -> 30 | AG9: =IF(P9="none",0,IF(P9="unknown",5,Weights!$B$4)) -> 15 | AH9: =IF(K9="",4,IF(AND(K9>=Weights!$B$13,K9<=Weights!$B$14),Weights!$B$5,IF(K9>100,15,IF(K9>=20,12,4)))) -> 15 | AI9: =IF(OR(Q9="taken",Q9="sold",Q9="ruled-out"),0,MIN(IF(AND(H9="tourist-hotel",P9="none"),Weights!$B$11,100),AE9+AF9+AG9+AH9)+IF(T9="yes",Weights!$B$10,0)) -> 88 | AJ9: not-contacted | AK9: Jul 16 2026 (report)
A10: =RANK(AI10,$AI$2:$AI$70) -> 7 | B10: AAU dorm — 680 Sutter St | C10: 680 Sutter St, Nob Hill, SF | D10: Nob Hill | E10: SF-priority | F10: 14 | G10: est. by neighborhood (geocode in portal) | H10: dorm | I10: 50 | J10: 2 | K10: =IF(I10="","",I10*J10) -> 100 | L10: 1100 | M10: 1500 | N10: =IF(L10="","",ROUND((L10+M10)/2/J10,0)) -> 650 | O10: =IF(N10="","",N10*Weights!$B$12) -> 29250 | P10: communal | Q10: active | R10: Jewel | S10: q1-2027 | T10: unknown | U10: yes | W10: 1055 Pine asks $20M; leases negotiable | X10: One motivated seller — M&M brokers | Y10: AAU Housing Office — existing landlord, warm intro | Z10: via 79 New Montgomery switchboard | AA10: academyart.edu/campus-athletics/housing | AB10: ⭐ Jewels — call these first | AC10: TRD — $130M portfolio: https://therealdeal.com/san-francisco/2025/10/22/san-francisco-art-academy-to-sell-130-million-portfolio/ 1055 Pine LoopNet: https://www.loopnet.com/Listing/1055-Pine-St-San-Francisco-CA/38157856/ AAU housing page: https://www.academyart.edu/campus-athletics/housing/ 736 Jones: https://www.apartments.com/academy-of-art-university-san-francisco-ca/s6esxj6/ | AD10: Round-4 check: none of the dorms is formally listed — the $130M portfolio never included them (its residential pieces, 1055 Pine and 1946 Van Ness, are under contract). AAU's facilities page still shows all four as student housing, though 736 Jones and 860 Sutter were dropped from the current-housing page — mixed signals that only a direct ask resolves. Two routes: the existing landlord relationship, and Marcus & Millichap (handling ALL AAU dispositions) for an off-market approach. Comp: the Commodore dorm-hotel traded at ~$13M (~$115k/key). | AE10: =IF(LEFT(E10,2)="SF",IF(F10="",0,Weights!$B$2*MAX(0,MIN(1,(Weights!$B$9-F10)/(Weights!$B$9-Weights!$B$8)))),0) -> 31 | AF10: =IF(N10="",5,Weights!$B$3*MAX(0,MIN(1,(Weights!$B$7-N10)/(Weights!$B$7-Weights!$B$6)))) -> 30 | AG10: =IF(P10="none",0,IF(P10="unknown",5,Weights!$B$4)) -> 15 | AH10: =IF(K10="",4,IF(AND(K10>=Weights!$B$13,K10<=Weights!$B$14),Weights!$B$5,IF(K10>100,15,IF(K10>=20,12,4)))) -> 12 | AI10: =IF(OR(Q10="taken",Q10="sold",Q10="ruled-out"),0,MIN(IF(AND(H10="tourist-hotel",P10="none"),Weights!$B$11,100),AE10+AF10+AG10+AH10)+IF(T10="yes",Weights!$B$10,0)) -> 88 | AJ10: not-contacted | AK10: Jul 16 2026 (report)
A11: =RANK(AI11,$AI$2:$AI$70) -> 55 | B11: Waterfront Hotel — closed, actively brokered | C11: 10 Washington St, Jack London Square, Oakland | D11: Jack London Sq, Oakland | E11: East Bay | F11: 55 | G11: est. by neighborhood (geocode in portal) | H11: tourist-hotel | I11: 145 | J11: 1 | K11: =IF(I11="","",I11*J11) -> 145 | L11: 1200 | M11: 1800 | N11: =IF(L11="","",ROUND((L11+M11)/2/J11,0)) -> 1500 | O11: =IF(N11="","",N11*Weights!$B$12) -> 67500 | P11: none | Q11: dark | R11: Jewel | S11: expansion | T11: no | W11: Leasehold, 'fully unencumbered' — unsold a year+ | X11: Call Berkadia (Kelso / Michels) | Y11: Jared Kelso / Steve Michels — Berkadia | Z11: 646-432-7480 / 646-432-7475 | AA11: Port of Oakland + CIM consent needed | AB11: ⭐ Jewels — call these first | AC11: Berkadia listing: https://properties.berkadia.com/waterfront-hotel-414425/ CBS — closure: https://www.cbsnews.com/sanfrancisco/news/oakland-landmark-waterfront-hotel-jack-london-square-closes/ | AD11: Verified July 2026: still unsold after 18 months, no price guidance — a stuck listing. Contacts: Jared Kelso 646-432-7480 / Steve Michels 646-432-7475 (Berkadia). Caveat: leasehold — land is Port of Oakland, ground lease runs through CIM Group, so Port consent likely needed. Comp: Homewood Suites Oakland just sold at $42k/key. | AE11: =IF(LEFT(E11,2)="SF",IF(F11="",0,Weights!$B$2*MAX(0,MIN(1,(Weights!$B$9-F11)/(Weights!$B$9-Weights!$B$8)))),0) -> 0 | AF11: =IF(N11="",5,Weights!$B$3*MAX(0,MIN(1,(Weights!$B$7-N11)/(Weights!$B$7-Weights!$B$6)))) -> 17.5 | AG11: =IF(P11="none",0,IF(P11="unknown",5,Weights!$B$4)) -> 0 | AH11: =IF(K11="",4,IF(AND(K11>=Weights!$B$13,K11<=Weights!$B$14),Weights!$B$5,IF(K11>100,15,IF(K11>=20,12,4)))) -> 15 | AI11: =IF(OR(Q11="taken",Q11="sold",Q11="ruled-out"),0,MIN(IF(AND(H11="tourist-hotel",P11="none"),Weights!$B$11,100),AE11+AF11+AG11+AH11)+IF(T11="yes",Weights!$B$10,0)) -> 32.5 | AJ11: not-contacted | AK11: Jul 16 2026 (report)
A12: =RANK(AI12,$AI$2:$AI$70) -> 26 | B12: 1900 Broadway co-living block (verified pricing) | C12: Uptown Oakland, on top of 19th St BART | D12: Uptown Oakland | E12: East Bay | F12: 40 | G12: est. by neighborhood (geocode in portal) | H12: co-living | I12: 60 | J12: 1 | K12: =IF(I12="","",I12*J12) -> 60 | L12: 1400 | M12: 1660 | N12: =IF(L12="","",ROUND((L12+M12)/2/J12,0)) -> 1530 | O12: =IF(N12="","",N12*Weights!$B$12) -> 68850 | P12: private | Q12: active | R12: Jewel | S12: bridge-sept;expansion | T12: yes | W12: $1,803/bed listed · 4 wks free → ~$1,660 effective · block deal ≈ $1,400–1,550 | X12: Negotiate 40–60 bed block | Y12: Leasing (Bozzuto) · STAK · owner: Behring Companies (Colin Behring) | Z12: 844-932-4196 · (510) 925-4860 | AA12: live1900.com · stakspace.com | AB12: ⭐ Jewels — call these first | AC12: Apartments.com: https://www.apartments.com/1900-broadway-oakland-ca/bht2eec/ live1900.com: https://www.live1900.com/ Zillow — 23 units: https://www.zillow.com/apartments/oakland-ca/1900-broadway/Ch7XFs/ | AD12: Verified live: co-living beds from $1,803 with 4 weeks free; ~23 units on Zillow = leverage. STAK sells Bronze/Silver/Gold apartment+coworking packages ('up to $60k/yr savings') — the group-block product exists in all but name. For 40–60 beds, go over the leasing office (844-932-4196) to owner Behring Companies (Colin Behring). | AE12: =IF(LEFT(E12,2)="SF",IF(F12="",0,Weights!$B$2*MAX(0,MIN(1,(Weights!$B$9-F12)/(Weights!$B$9-Weights!$B$8)))),0) -> 0 | AF12: =IF(N12="",5,Weights!$B$3*MAX(0,MIN(1,(Weights!$B$7-N12)/(Weights!$B$7-Weights!$B$6)))) -> 16.75 | AG12: =IF(P12="none",0,IF(P12="unknown",5,Weights!$B$4)) -> 15 | AH12: =IF(K12="",4,IF(AND(K12>=Weights!$B$13,K12<=Weights!$B$14),Weights!$B$5,IF(K12>100,15,IF(K12>=20,12,4)))) -> 20 | AI12: =IF(OR(Q12="taken",Q12="sold",Q12="ruled-out"),0,MIN(IF(AND(H12="tourist-hotel",P12="none"),Weights!$B$11,100),AE12+AF12+AG12+AH12)+IF(T12="yes",Weights!$B$10,0)) -> 56.75 | AJ12: not-contacted | AK12: Jul 16 2026 (report)
A13: =RANK(AI13,$AI$2:$AI$70) -> 29 | B13: Ora Apartments — REO, on market now | C13: 1815 Alice St, Downtown Oakland | D13: Downtown Oakland | E13: East Bay | F13: 45 | G13: est. by neighborhood (geocode in portal) | H13: apartment-block | I13: 74 | J13: 2 | K13: =IF(I13="","",I13*J13) -> 148 | L13: 2200 | M13: 2800 | N13: =IF(L13="","",ROUND((L13+M13)/2/J13,0)) -> 1250 | O13: =IF(N13="","",N13*Weights!$B$12) -> 56250 | P13: private | Q13: on-market | R13: Bargain / distressed | S13: expansion | T13: no | W13: Lender foreclosed at $25M vs $41M (2021); JLL listing | X13: Master lease or bulk-unit deal with lender-seller | Y13: JLL: Ryan Wagner · Matt Kroger · Brandon Geraldo · Fatai Alashe | Z13: (415) 706-7215 · (415) 395-7219 · (415) 395-7273 · (415) 395-7284 | AA13: firstname.lastname@jll.com | AB13: Bargains / distressed | AC13: TRD, May 2026: https://therealdeal.com/sanfrancisco/2026/05/08/ora-apartments-in-oakland-hit-market-after-foreclosure/ | AD13: Nearly-new building marketed 'below replacement cost.' A credit master tenant filling 74 units is exactly what a lender-seller wants while waiting for a sale. | AE13: =IF(LEFT(E13,2)="SF",IF(F13="",0,Weights!$B$2*MAX(0,MIN(1,(Weights!$B$9-F13)/(Weights!$B$9-Weights!$B$8)))),0) -> 0 | AF13: =IF(N13="",5,Weights!$B$3*MAX(0,MIN(1,(Weights!$B$7-N13)/(Weights!$B$7-Weights!$B$6)))) -> 23.75 | AG13: =IF(P13="none",0,IF(P13="unknown",5,Weights!$B$4)) -> 15 | AH13: =IF(K13="",4,IF(AND(K13>=Weights!$B$13,K13<=Weights!$B$14),Weights!$B$5,IF(K13>100,15,IF(K13>=20,12,4)))) -> 15 | AI13: =IF(OR(Q13="taken",Q13="sold",Q13="ruled-out"),0,MIN(IF(AND(H13="tourist-hotel",P13="none"),Weights!$B$11,100),AE13+AF13+AG13+AH13)+IF(T13="yes",Weights!$B$10,0)) -> 53.75 | AJ13: not-contacted | AK13: Jul 16 2026 (report)
A14: =RANK(AI14,$AI$2:$AI$70) -> 31 | B14: Moran + Telegraph Arts — one lender, 175 units | C14: 570 21st St + 471 26th St, Uptown Oakland (0.4 mi apart) | D14: Uptown Oakland | E14: East Bay | F14: 45 | G14: est. by neighborhood (geocode in portal) | H14: apartment-block | I14: 175 | J14: 2 | K14: =IF(I14="","",I14*J14) -> 350 | L14: 2200 | M14: 3000 | N14: =IF(L14="","",ROUND((L14+M14)/2/J14,0)) -> 1300 | O14: =IF(N14="","",N14*Weights!$B$12) -> 58500 | P14: private | Q14: receivership | R14: Bargain / distressed | S14: expansion | T14: no | W14: CWCapital took both ~50% below assessed (2026) | X14: One special-servicer negotiation covers everything | Y14: CWCapital Asset Management | Z14: (202) 715-9500 | AA14: sells via RealINSIGHT Marketplace (800) 915-7015 | AB14: Bargains / distressed | AC14: Multifamily Dive: https://www.multifamilydive.com/news/oakland-multifamily-distress-auction-loan-default/814338/ TRD: https://therealdeal.com/sanfrancisco/2026/04/09/lender-forecloses-on-two-oakland-apartment-complexes/ Hoodline: https://hoodline.com/2026/03/foreclosure-shock-rocks-uptown-oakland-as-two-apartment-hubs-teeter/ | AD14: Both foreclosed spring 2026. A single counterparty controlling two nearby modern buildings = the whole program (and its expansion) in one deal, at distressed pricing. Also the strongest 'pair' on the board. | AE14: =IF(LEFT(E14,2)="SF",IF(F14="",0,Weights!$B$2*MAX(0,MIN(1,(Weights!$B$9-F14)/(Weights!$B$9-Weights!$B$8)))),0) -> 0 | AF14: =IF(N14="",5,Weights!$B$3*MAX(0,MIN(1,(Weights!$B$7-N14)/(Weights!$B$7-Weights!$B$6)))) -> 22.5 | AG14: =IF(P14="none",0,IF(P14="unknown",5,Weights!$B$4)) -> 15 | AH14: =IF(K14="",4,IF(AND(K14>=Weights!$B$13,K14<=Weights!$B$14),Weights!$B$5,IF(K14>100,15,IF(K14>=20,12,4)))) -> 15 | AI14: =IF(OR(Q14="taken",Q14="sold",Q14="ruled-out"),0,MIN(IF(AND(H14="tourist-hotel",P14="none"),Weights!$B$11,100),AE14+AF14+AG14+AH14)+IF(T14="yes",Weights!$B$10,0)) -> 52.5 | AJ14: not-contacted | AK14: Jul 16 2026 (report)
A15: =RANK(AI15,$AI$2:$AI$70) -> 68 | B15: 1919 Market St — foreclosed new-build co-living | C15: West Oakland (former Greyhound terminal site) | D15: West Oakland | E15: East Bay | F15: 40 | G15: est. by neighborhood (geocode in portal) | H15: co-living | I15: 102 | J15: 1 | K15: =IF(I15="","",I15*J15) -> 102 | L15: 1300 | M15: 1800 | N15: =IF(L15="","",ROUND((L15+M15)/2/J15,0)) -> 1550 | O15: =IF(N15="","",N15*Weights!$B$12) -> 69750 | P15: communal | Q15: sold | R15: Bargain / distressed | T15: no | W15: Parkview bought at foreclosure for $37.5M (Jan 2026) vs $58.5M debt | X15: Pitch new low-basis owner | AC15: TRD: https://therealdeal.com/sanfrancisco/2026/01/16/west-oakland-apartments-sell-at-foreclosure/ Multifamily Dive: https://www.multifamilydive.com/news/oakland-apartment-foreclosure-multifamily-distress/810263/ | AD15: Newly built by oWow with co-living-style layouts — unusually well suited to 40–60 beds. Owner at a 36% haircut basis needs income. | AE15: =IF(LEFT(E15,2)="SF",IF(F15="",0,Weights!$B$2*MAX(0,MIN(1,(Weights!$B$9-F15)/(Weights!$B$9-Weights!$B$8)))),0) -> 0 | AF15: =IF(N15="",5,Weights!$B$3*MAX(0,MIN(1,(Weights!$B$7-N15)/(Weights!$B$7-Weights!$B$6)))) -> 16.25 | AG15: =IF(P15="none",0,IF(P15="unknown",5,Weights!$B$4)) -> 15 | AH15: =IF(K15="",4,IF(AND(K15>=Weights!$B$13,K15<=Weights!$B$14),Weights!$B$5,IF(K15>100,15,IF(K15>=20,12,4)))) -> 15 | AI15: =IF(OR(Q15="taken",Q15="sold",Q15="ruled-out"),0,MIN(IF(AND(H15="tourist-hotel",P15="none"),Weights!$B$11,100),AE15+AF15+AG15+AH15)+IF(T15="yes",Weights!$B$10,0)) -> 0 | AJ15: not-contacted | AK15: Jul 16 2026 (report)
A16: =RANK(AI16,$AI$2:$AI$70) -> 49 | B16: AC Hotel / Residence Inn Oakland — lender-seized, 1 yr old | C16: 1431 Jefferson St, Downtown Oakland | D16: Downtown Oakland | E16: East Bay | F16: 45 | G16: est. by neighborhood (geocode in portal) | H16: tourist-hotel | I16: 276 | J16: 1 | K16: =IF(I16="","",I16*J16) -> 276 | L16: 1500 | M16: 2200 | N16: =IF(L16="","",ROUND((L16+M16)/2/J16,0)) -> 1850 | O16: =IF(N16="","",N16*Weights!$B$12) -> 83250 | P16: private | Q16: receivership | R16: Bargain / distressed | S16: expansion | T16: no | W16: Defaulted on $101M one year after opening; seized Apr 2025 | X16: Approach the lender | AC16: SF Standard: https://sfstandard.com/2026/01/20/oakland-moxy-hotel-closed/ TRD: https://therealdeal.com/sanfrancisco/2025/07/10/oakland-marriott-city-center-finds-buyer-at-foreclosure/ | AD16: Brand-new extended-stay product (kitchens!) under lender control — arguably the best hotel-side target in Oakland for quality per dollar. | AE16: =IF(LEFT(E16,2)="SF",IF(F16="",0,Weights!$B$2*MAX(0,MIN(1,(Weights!$B$9-F16)/(Weights!$B$9-Weights!$B$8)))),0) -> 0 | AF16: =IF(N16="",5,Weights!$B$3*MAX(0,MIN(1,(Weights!$B$7-N16)/(Weights!$B$7-Weights!$B$6)))) -> 8.75 | AG16: =IF(P16="none",0,IF(P16="unknown",5,Weights!$B$4)) -> 15 | AH16: =IF(K16="",4,IF(AND(K16>=Weights!$B$13,K16<=Weights!$B$14),Weights!$B$5,IF(K16>100,15,IF(K16>=20,12,4)))) -> 15 | AI16: =IF(OR(Q16="taken",Q16="sold",Q16="ruled-out"),0,MIN(IF(AND(H16="tourist-hotel",P16="none"),Weights!$B$11,100),AE16+AF16+AG16+AH16)+IF(T16="yes",Weights!$B$10,0)) -> 38.75 | AJ16: not-contacted | AK16: Jul 16 2026 (report)
A17: =RANK(AI17,$AI$2:$AI$70) -> 55 | B17: Courtyard Oakland Downtown — owner will take any exit | C17: 988 Broadway, Oakland (Chinatown edge) | D17: Downtown Oakland | E17: East Bay | F17: 45 | G17: est. by neighborhood (geocode in portal) | H17: tourist-hotel | I17: 160 | J17: 1 | K17: =IF(I17="","",I17*J17) -> 160 | L17: 1200 | M17: 1800 | N17: =IF(L17="","",ROUND((L17+M17)/2/J17,0)) -> 1500 | O17: =IF(N17="","",N17*Weights!$B$12) -> 67500 | P17: none | Q17: dark | R17: Bargain / distressed | S17: expansion | T17: no | W17: Owner shopped it as a 150-bed shelter, then as 64 apartments | X17: 3–5 yr master lease during entitlement | Y17: Gaw Capital USA, SF office | Z17: (415) 645-7000 | AA17: gawcapitalusa.com contact form | AB17: Bargains / distressed | AC17: TRD, Apr 2026: https://therealdeal.com/san-francisco/2026/04/16/hoteliers-look-to-convert-oakland-marriott-into-apartments/ SF YIMBY: https://sfyimby.com/2026/04/preliminary-application-for-hotel-to-housing-conversion-at-988-broadway-downtown-oakland.html | AD17: Gaw Capital has tried everything with this building (and already lost the Marriott City Center next door to foreclosure). A residential master lease during their apartment-conversion entitlement fits their playbook exactly. | AE17: =IF(LEFT(E17,2)="SF",IF(F17="",0,Weights!$B$2*MAX(0,MIN(1,(Weights!$B$9-F17)/(Weights!$B$9-Weights!$B$8)))),0) -> 0 | AF17: =IF(N17="",5,Weights!$B$3*MAX(0,MIN(1,(Weights!$B$7-N17)/(Weights!$B$7-Weights!$B$6)))) -> 17.5 | AG17: =IF(P17="none",0,IF(P17="unknown",5,Weights!$B$4)) -> 0 | AH17: =IF(K17="",4,IF(AND(K17>=Weights!$B$13,K17<=Weights!$B$14),Weights!$B$5,IF(K17>100,15,IF(K17>=20,12,4)))) -> 15 | AI17: =IF(OR(Q17="taken",Q17="sold",Q17="ruled-out"),0,MIN(IF(AND(H17="tourist-hotel",P17="none"),Weights!$B$11,100),AE17+AF17+AG17+AH17)+IF(T17="yes",Weights!$B$10,0)) -> 32.5 | AJ17: not-contacted | AK17: Jul 16 2026 (report)
A18: =RANK(AI18,$AI$2:$AI$70) -> 38 | B18: Stanford Court — 4-star Nob Hill, receiver in place | C18: 905 California St, Nob Hill, SF | D18: Nob Hill | E18: SF-priority | F18: 20 | G18: est. by neighborhood (geocode in portal) | H18: tourist-hotel | I18: 60 | J18: 1 | K18: =IF(I18="","",I18*J18) -> 60 | L18: 1800 | M18: 2200 | N18: =IF(L18="","",ROUND((L18+M18)/2/J18,0)) -> 2000 | O18: =IF(N18="","",N18*Weights!$B$12) -> 90000 | P18: none | Q18: receivership | R18: Bargain / distressed | S18: q1-2027 | T18: no | W18: $105M default; foreclosure trial July 13, 2026; Eastdil marketing leasehold | X18: Pitch receiver a guaranteed 50–60 room block | Y18: Eastdil Secured SF — ask for the Stanford Court deal team | Z18: (415) 228-2900 | AA18: 101 California St #2950 | AB18: Bargains / distressed | AC18: TRD, Mar 2026: https://therealdeal.com/san-francisco/2026/03/03/nob-hill-hotel-hits-market-again-as-foreclosure-looms/ SFist — case background: https://sfist.com/2025/01/17/nob-hills-posh-stanford-court-hotel-hit-with-foreclosure-lawsuit-over-claims-of-missed-mortgage-payments/ | AD18: Foreclosure trial was held July 13 — no published outcome yet (press lags bench rulings; check the SF Superior Court docket: Deutsche Bank AG v. Pine & Powell Partners). Either way the live counterparties are unchanged: receiver Chad Crandell (CHMWarnick) + Eastdil. A guaranteed 50–60 room block at $1,800–2,200 is 4-star quality — the 'much nicer rooms' winner. | AE18: =IF(LEFT(E18,2)="SF",IF(F18="",0,Weights!$B$2*MAX(0,MIN(1,(Weights!$B$9-F18)/(Weights!$B$9-Weights!$B$8)))),0) -> 25 | AF18: =IF(N18="",5,Weights!$B$3*MAX(0,MIN(1,(Weights!$B$7-N18)/(Weights!$B$7-Weights!$B$6)))) -> 5 | AG18: =IF(P18="none",0,IF(P18="unknown",5,Weights!$B$4)) -> 0 | AH18: =IF(K18="",4,IF(AND(K18>=Weights!$B$13,K18<=Weights!$B$14),Weights!$B$5,IF(K18>100,15,IF(K18>=20,12,4)))) -> 20 | AI18: =IF(OR(Q18="taken",Q18="sold",Q18="ruled-out"),0,MIN(IF(AND(H18="tourist-hotel",P18="none"),Weights!$B$11,100),AE18+AF18+AG18+AH18)+IF(T18="yes",Weights!$B$10,0)) -> 40 | AJ18: not-contacted | AK18: Jul 16 2026 (report)
A19: =RANK(AI19,$AI$2:$AI$70) -> 33 | B19: Parkmerced — bulk units from a receiver | C19: 3711 19th Ave, SF (SW corner, near SFSU) | D19: Parkmerced | E19: SF-other | F19: 50 | G19: est. by neighborhood (geocode in portal) | H19: apartment-block | I19: 60 | J19: 2 | K19: =IF(I19="","",I19*J19) -> 120 | L19: 3000 | M19: 3000 | N19: =IF(L19="","",ROUND((L19+M19)/2/J19,0)) -> 1500 | O19: =IF(N19="","",N19*Weights!$B$12) -> 67500 | P19: private | Q19: receivership | R19: Bargain / distressed | S19: expansion | T19: unknown | W19: In receivership since Mar 2025 ($1.8B default) | X19: 60–120 bed corporate block at a steep discount | Y19: Leasing; receiver = Douglas Wilson Companies | Z19: (415) 689-6252 | AA19: lease@rentbt.com | AB19: Bargains / distressed | AC19: TRD: https://therealdeal.com/san-francisco/2025/03/20/sfs-largest-apartment-complex-ordered-into-receivership/ SF Standard: https://sfstandard.com/2025/04/18/parkmerced-billion-dollar-housing-project-timeline/ | AD19: The fastest 60+ beds in SF at scale: 2–3BR townhomes at 2/room lands near $1,500/bed. Not charming, but September-ready and endlessly scalable. Rent-control structuring needs counsel. | AE19: =IF(LEFT(E19,2)="SF",IF(F19="",0,Weights!$B$2*MAX(0,MIN(1,(Weights!$B$9-F19)/(Weights!$B$9-Weights!$B$8)))),0) -> 0 | AF19: =IF(N19="",5,Weights!$B$3*MAX(0,MIN(1,(Weights!$B$7-N19)/(Weights!$B$7-Weights!$B$6)))) -> 17.5 | AG19: =IF(P19="none",0,IF(P19="unknown",5,Weights!$B$4)) -> 15 | AH19: =IF(K19="",4,IF(AND(K19>=Weights!$B$13,K19<=Weights!$B$14),Weights!$B$5,IF(K19>100,15,IF(K19>=20,12,4)))) -> 15 | AI19: =IF(OR(Q19="taken",Q19="sold",Q19="ruled-out"),0,MIN(IF(AND(H19="tourist-hotel",P19="none"),Weights!$B$11,100),AE19+AF19+AG19+AH19)+IF(T19="yes",Weights!$B$10,0)) -> 47.5 | AJ19: not-contacted | AK19: Jul 16 2026 (report)
A20: =RANK(AI20,$AI$2:$AI$70) -> 6 | B20: Mosser SRO — 1000 Market St (owner stuck) | C20: 1000 Market / Turk St, Mid-Market SF | D20: Civic Center | E20: SF-priority | F20: 3 | G20: est. by neighborhood (geocode in portal) | H20: sro-hotel | I20: 361 | J20: 1 | K20: =IF(I20="","",I20*J20) -> 361 | L20: 1100 | M20: 1400 | N20: =IF(L20="","",ROUND((L20+M20)/2/J20,0)) -> 1250 | O20: =IF(N20="","",N20*Weights!$B$12) -> 56250 | P20: communal | Q20: active | R20: Bargain / distressed | S20: bridge-sept;q1-2027;expansion | T20: unknown | W20: Owner tried converting rooms to tourist use — rejected by Planning (Mar 2025) | X20: Master-lease the rooms he can't fill | Y20: Mosser Companies | Z20: (415) 673-1608 | AA20: mosserliving.com/contact | AB20: Bargains / distressed | AC20: 48 Hills: https://48hills.org/2025/03/planning-commission-rejects-landlord-plan-to-convert-sro-rooms-to-tourist-hotels/ SFADC: https://sfadc.org/2025/03/21/community-victory-planning-commission-rejects-mosser-sro-attempt-to-convert-sro-rooms-to-tourist-hotel/ | AD20: An owner who publicly argued residential SRO doesn't pencil, now stuck with rooms he can't convert. A block lease at $1,100–1,400/room solves his problem and yours. | AE20: =IF(LEFT(E20,2)="SF",IF(F20="",0,Weights!$B$2*MAX(0,MIN(1,(Weights!$B$9-F20)/(Weights!$B$9-Weights!$B$8)))),0) -> 35 | AF20: =IF(N20="",5,Weights!$B$3*MAX(0,MIN(1,(Weights!$B$7-N20)/(Weights!$B$7-Weights!$B$6)))) -> 23.75 | AG20: =IF(P20="none",0,IF(P20="unknown",5,Weights!$B$4)) -> 15 | AH20: =IF(K20="",4,IF(AND(K20>=Weights!$B$13,K20<=Weights!$B$14),Weights!$B$5,IF(K20>100,15,IF(K20>=20,12,4)))) -> 15 | AI20: =IF(OR(Q20="taken",Q20="sold",Q20="ruled-out"),0,MIN(IF(AND(H20="tourist-hotel",P20="none"),Weights!$B$11,100),AE20+AF20+AG20+AH20)+IF(T20="yes",Weights!$B$10,0)) -> 88.75 | AJ20: not-contacted | AK20: Jul 16 2026 (report)
A21: =RANK(AI21,$AI$2:$AI$70) -> 25 | B21: Veritas & Ballast portfolios — bank-controlled SF buildings | C21: Tenderloin / Civic Center / citywide SF | D21: Civic Center | E21: SF-priority | F21: 10 | G21: est. by neighborhood (geocode in portal) | H21: apartment-block | J21: 2 | K21: =IF(I21="","",I21*J21) | N21: =IF(L21="","",ROUND((L21+M21)/2/J21,0)) | O21: =IF(N21="","",N21*Weights!$B$12) | P21: private | Q21: receivership | R21: Bargain / distressed | S21: q1-2027 | T21: unknown | W21: Receiver/lender controlled | X21: Building-level master-lease conversations | Y21: Receiver / lender — identify via SF Assessor-Recorder deed pull | Z21: — | AA21: Prospect Hill Capital (Veritas) / RBC (Ballast) | AB21: Report §6b | AC21: Mission Local: https://missionlocal.org/2025/09/sf-veritas-foreclosure-652-million-debt/ Multifamily Dive — Ballast: https://www.multifamilydive.com/news/goldman-sachs-ballast-investments-distressed-loans-san-francisco/722955/ | AD21: Portfolio play — no single building identified yet; find the receiver/lender contact first. | SF's two mega-distress portfolios. Whoever holds these post-auction inherits scattered vacancy in exactly the neighborhoods with SRO/studio stock. Worth a call to receiver Wald Realty Advisors / Hamilton Zanze. | AE21: =IF(LEFT(E21,2)="SF",IF(F21="",0,Weights!$B$2*MAX(0,MIN(1,(Weights!$B$9-F21)/(Weights!$B$9-Weights!$B$8)))),0) -> 35 | AF21: =IF(N21="",5,Weights!$B$3*MAX(0,MIN(1,(Weights!$B$7-N21)/(Weights!$B$7-Weights!$B$6)))) -> 5 | AG21: =IF(P21="none",0,IF(P21="unknown",5,Weights!$B$4)) -> 15 | AH21: =IF(K21="",4,IF(AND(K21>=Weights!$B$13,K21<=Weights!$B$14),Weights!$B$5,IF(K21>100,15,IF(K21>=20,12,4)))) -> 4 | AI21: =IF(OR(Q21="taken",Q21="sold",Q21="ruled-out"),0,MIN(IF(AND(H21="tourist-hotel",P21="none"),Weights!$B$11,100),AE21+AF21+AG21+AH21)+IF(T21="yes",Weights!$B$10,0)) -> 59 | AJ21: not-contacted | AK21: Jul 16 2026 (report)
A22: =RANK(AI22,$AI$2:$AI$70) -> 58 | B22: St. Anne's Home — closed 6-acre care campus | C22: 300 Lake St, Inner Richmond, SF | D22: Inner Richmond | E22: SF-other | F22: 55 | G22: est. by neighborhood (geocode in portal) | H22: campus | I22: 100 | J22: 1 | K22: =IF(I22="","",I22*J22) -> 100 | N22: =IF(L22="","",ROUND((L22+M22)/2/J22,0)) | O22: =IF(N22="","",N22*Weights!$B$12) | P22: communal | Q22: on-market | R22: Bargain / distressed | S22: q1-2027;expansion | T22: no | W22: Listed $58.5M (May 2025); no closed sale announced | X22: Interim master lease from whoever wins it | Y22: Greg Zielinski — Zielinski Companies (runs the sale for the order) | Z22: (800) 489-2150 / (314) 644-2150 | AA22: mail@zielinskico.com | AB22: Bargains / distressed | AC22: TRD: https://therealdeal.com/san-francisco/2025/05/12/catholic-order-lists-sf-nursing-home-site-for-59-million/ SF Standard: https://sfstandard.com/2025/01/09/st-annes-home-little-sisters-poor-to-close-sf/ | AD22: Closed 2025 after 124 years (Little Sisters of the Poor). Any developer buyer faces a 3–6 year rezoning window — a ~100-bed interim lease of a fully built residential building is very plausible. Chase the winning bidder. | AE22: =IF(LEFT(E22,2)="SF",IF(F22="",0,Weights!$B$2*MAX(0,MIN(1,(Weights!$B$9-F22)/(Weights!$B$9-Weights!$B$8)))),0) -> 0 | AF22: =IF(N22="",5,Weights!$B$3*MAX(0,MIN(1,(Weights!$B$7-N22)/(Weights!$B$7-Weights!$B$6)))) -> 5 | AG22: =IF(P22="none",0,IF(P22="unknown",5,Weights!$B$4)) -> 15 | AH22: =IF(K22="",4,IF(AND(K22>=Weights!$B$13,K22<=Weights!$B$14),Weights!$B$5,IF(K22>100,15,IF(K22>=20,12,4)))) -> 12 | AI22: =IF(OR(Q22="taken",Q22="sold",Q22="ruled-out"),0,MIN(IF(AND(H22="tourist-hotel",P22="none"),Weights!$B$11,100),AE22+AF22+AG22+AH22)+IF(T22="yes",Weights!$B$10,0)) -> 32 | AJ22: not-contacted | AK22: Jul 16 2026 (report)
A23: =RANK(AI23,$AI$2:$AI$70) -> 58 | B23: Santa Sabina Center — closed convent retreat | C23: 25 Magnolia Ave, San Rafael (25–30 min to SF) | D23: San Rafael | E23: North Bay | F23: 90 | G23: est. by neighborhood (geocode in portal) | H23: campus | I23: 38 | J23: 2 | K23: =IF(I23="","",I23*J23) -> 76 | N23: =IF(L23="","",ROUND((L23+M23)/2/J23,0)) | O23: =IF(N23="","",N23*Weights!$B$12) | P23: communal | Q23: on-market | R23: Bargain / distressed | S23: expansion | T23: no | W23: For sale via faith-property specialist; price undisclosed | X23: Mission-aligned lease-to-own pitch | Y23: Dominic Dutra — 3D Strategies | Z23: (510) 366-9931 | AA23: ddutra@3Dstrategies.com | AB23: Bargains / distressed | AC23: Listing background: https://phillipacriswell.com/blog/historic-bay-area-retreat-will-go-for-sale Yelp — closed: https://www.yelp.com/biz/santa-sabina-center-san-rafael | AD23: Dominican Sisters closed it Feb 2026. The buyer pool for convents is tiny — a residential-education story plus lease-to-own could win at a low number. Turnkey: dining hall, library, conference space. | AE23: =IF(LEFT(E23,2)="SF",IF(F23="",0,Weights!$B$2*MAX(0,MIN(1,(Weights!$B$9-F23)/(Weights!$B$9-Weights!$B$8)))),0) -> 0 | AF23: =IF(N23="",5,Weights!$B$3*MAX(0,MIN(1,(Weights!$B$7-N23)/(Weights!$B$7-Weights!$B$6)))) -> 5 | AG23: =IF(P23="none",0,IF(P23="unknown",5,Weights!$B$4)) -> 15 | AH23: =IF(K23="",4,IF(AND(K23>=Weights!$B$13,K23<=Weights!$B$14),Weights!$B$5,IF(K23>100,15,IF(K23>=20,12,4)))) -> 12 | AI23: =IF(OR(Q23="taken",Q23="sold",Q23="ruled-out"),0,MIN(IF(AND(H23="tourist-hotel",P23="none"),Weights!$B$11,100),AE23+AF23+AG23+AH23)+IF(T23="yes",Weights!$B$10,0)) -> 32 | AJ23: not-contacted | AK23: Jul 16 2026 (report)
A24: =RANK(AI24,$AI$2:$AI$70) -> 27 | B24: Ferns Hotel — price-cut, income-hungry | C24: 415–417 15th St, Downtown Oakland | D24: Downtown Oakland | E24: East Bay | F24: 45 | G24: est. by neighborhood (geocode in portal) | H24: sro-hotel | I24: 33 | J24: 1 | K24: =IF(I24="","",I24*J24) -> 33 | L24: 950 | M24: 1200 | N24: =IF(L24="","",ROUND((L24+M24)/2/J24,0)) -> 1075 | O24: =IF(N24="","",N24*Weights!$B$12) -> 48375 | P24: communal | Q24: on-market | R24: Bargain / distressed | T24: unknown | W24: $4.32M, cut from $4.98M; gross income only $377k/yr | X24: Lowball master lease ≈ $800–900/room matches current gross | Y24: Fred Lewis | Z24: (209) 522-9999 | AA24: info@hotdealsoakland.com | AB24: Bargains / distressed | AC24: Offering brochure (PDF): https://images3.loopnet.com/d2/fcQavuW6QnYRr5iaTP1pTcdxUIxr5FCekoZrGvUWJoQ/document.pdf | AD24: Recently rehabbed (20 units redone, new boiler, solar), 1 block to 19th St BART. Broker Fred Lewis, (209) 522-9999. A master lease at $800–900/room roughly equals what the whole building earns today. | AE24: =IF(LEFT(E24,2)="SF",IF(F24="",0,Weights!$B$2*MAX(0,MIN(1,(Weights!$B$9-F24)/(Weights!$B$9-Weights!$B$8)))),0) -> 0 | AF24: =IF(N24="",5,Weights!$B$3*MAX(0,MIN(1,(Weights!$B$7-N24)/(Weights!$B$7-Weights!$B$6)))) -> 28.125 | AG24: =IF(P24="none",0,IF(P24="unknown",5,Weights!$B$4)) -> 15 | AH24: =IF(K24="",4,IF(AND(K24>=Weights!$B$13,K24<=Weights!$B$14),Weights!$B$5,IF(K24>100,15,IF(K24>=20,12,4)))) -> 12 | AI24: =IF(OR(Q24="taken",Q24="sold",Q24="ruled-out"),0,MIN(IF(AND(H24="tourist-hotel",P24="none"),Weights!$B$11,100),AE24+AF24+AG24+AH24)+IF(T24="yes",Weights!$B$10,0)) -> 55.125 | AJ24: not-contacted | AK24: Jul 16 2026 (report)
A25: =RANK(AI25,$AI$2:$AI$70) -> 63 | B25: Alameda Point BEQ — city signs as-is 5-yr leases | C25: Alameda Point (former Naval Air Station), Alameda | D25: Alameda | E25: East Bay | F25: 70 | G25: est. by neighborhood (geocode in portal) | H25: dorm | I25: 80 | J25: 2 | K25: =IF(I25="","",I25*J25) -> 160 | N25: =IF(L25="","",ROUND((L25+M25)/2/J25,0)) | O25: =IF(N25="","",N25*Weights!$B$12) | P25: unknown | Q25: dark | R25: Bargain / distressed | S25: expansion | T25: no | W25: City-owned, parked in 'Phase 2 future transactions' = unprogrammed | X25: Call JLL: Francisco Torres (510) 213-3580 / Kristi Childers (510) 812-2878 | Y25: JLL: Francisco Torres / Kristi Childers · property mgmt | Z25: (510) 213-3580 / (510) 812-2878 · (510) 749-0304 | AA25: alamedapoint@lpc.com | AB25: Bargains / distressed | AC25: Alameda Point leasing: https://www.alamedapoint.co/leasing Council preview, Jan 2026: https://alamedapost.com/news/january-20-city-council-preview/ | AD25: The city already signs market-rate as-is 5-year leases at the Point (e.g. Kai Concepts, Bldg 168). A barracks building is the exact format needed; expect condition/entitlement work. Also trace the never-used former Navy BOQ at Todd St & Pan Am Way (sold by the school district in 2021, owner unknown). | AE25: =IF(LEFT(E25,2)="SF",IF(F25="",0,Weights!$B$2*MAX(0,MIN(1,(Weights!$B$9-F25)/(Weights!$B$9-Weights!$B$8)))),0) -> 0 | AF25: =IF(N25="",5,Weights!$B$3*MAX(0,MIN(1,(Weights!$B$7-N25)/(Weights!$B$7-Weights!$B$6)))) -> 5 | AG25: =IF(P25="none",0,IF(P25="unknown",5,Weights!$B$4)) -> 5 | AH25: =IF(K25="",4,IF(AND(K25>=Weights!$B$13,K25<=Weights!$B$14),Weights!$B$5,IF(K25>100,15,IF(K25>=20,12,4)))) -> 15 | AI25: =IF(OR(Q25="taken",Q25="sold",Q25="ruled-out"),0,MIN(IF(AND(H25="tourist-hotel",P25="none"),Weights!$B$11,100),AE25+AF25+AG25+AH25)+IF(T25="yes",Weights!$B$10,0)) -> 25 | AJ25: not-contacted | AK25: Jul 16 2026 (report)
A26: =RANK(AI26,$AI$2:$AI$70) -> 65 | B26: 3700 California St — vacant hospital campus, years of runway | C26: Presidio Heights, SF (former CPMC campus) | D26: Presidio Heights | E26: SF-other | F26: 55 | G26: est. by neighborhood (geocode in portal) | H26: campus | J26: 1 | K26: =IF(I26="","",I26*J26) | N26: =IF(L26="","",ROUND((L26+M26)/2/J26,0)) | O26: =IF(N26="","",N26*Weights!$B$12) | P26: unknown | Q26: dark | R26: Bargain / distressed | S26: q1-2027 | T26: no | W26: Owner Prado Group still in environmental review — no construction start | X26: Pitch Prado Group an interim activation lease | Y26: Prado Group | Z26: — | AA26: pradogroup.com contact · 3700calsf.com | AB26: Bargains / distressed | AC26: SF YIMBY — EIR: https://sfyimby.com/2025/04/environmental-review-available-for-3700-california-street-in-presidio-heights-san-francisco.html SF Standard: https://sfstandard.com/2024/04/20/prado-group-redeveloping-hospitals-presidio-heights/ | AD26: Multi-year-vacant campus with a carrying-cost-burdened owner and 1–2+ years before demolition — textbook interim master lease. Caveat: hospital floorplates need change-of-use work; target the support/office buildings first. | AE26: =IF(LEFT(E26,2)="SF",IF(F26="",0,Weights!$B$2*MAX(0,MIN(1,(Weights!$B$9-F26)/(Weights!$B$9-Weights!$B$8)))),0) -> 0 | AF26: =IF(N26="",5,Weights!$B$3*MAX(0,MIN(1,(Weights!$B$7-N26)/(Weights!$B$7-Weights!$B$6)))) -> 5 | AG26: =IF(P26="none",0,IF(P26="unknown",5,Weights!$B$4)) -> 5 | AH26: =IF(K26="",4,IF(AND(K26>=Weights!$B$13,K26<=Weights!$B$14),Weights!$B$5,IF(K26>100,15,IF(K26>=20,12,4)))) -> 4 | AI26: =IF(OR(Q26="taken",Q26="sold",Q26="ruled-out"),0,MIN(IF(AND(H26="tourist-hotel",P26="none"),Weights!$B$11,100),AE26+AF26+AG26+AH26)+IF(T26="yes",Weights!$B$10,0)) -> 14 | AJ26: not-contacted | AK26: Jul 16 2026 (report)
A27: =RANK(AI27,$AI$2:$AI$70) -> 65 | B27: SF Archdiocese liquidation — get in before the brokers | C27: Citywide SF + St. Vincent's, San Rafael | D27: Citywide / San Rafael | E27: North Bay | F27: 90 | G27: est. by neighborhood (geocode in portal) | H27: campus | J27: 1 | K27: =IF(I27="","",I27*J27) | N27: =IF(L27="","",ROUND((L27+M27)/2/J27,0)) | O27: =IF(N27="","",N27*Weights!$B$12) | P27: unknown | Q27: dark | R27: Bargain / distressed | S27: q1-2027 | T27: no | W27: $395M abuse settlement (June 30, 2026) forces sales over 6–18 months | X27: Archdiocese Real Property office + Catholic Charities (Tony Alioto, AVAlioto@CatholicCharitiesSF.org) | Y27: Catholic Charities: Tony Alioto; Archdiocese Real Property office | Z27: — | AA27: AVAlioto@CatholicCharitiesSF.org | AB27: Bargains / distressed | AC27: ABC — settlement: https://abcnews.com/US/wireStory/san-francisco-archdiocese-agrees-pay-395-million-settle-134323951 Catholic Charities: https://catholiccharitiessf.org/st-vincents-school-for-boys/housing-site/ KTVU — surplus list: https://www.ktvu.com/news/advocates-of-sex-abuse-victims-want-sf-archdiocese-to-sell-unused-property-as-reparations | AD27: No public sale list exists yet — which is exactly why to call now. Flagged surplus: St. Thomas the Apostle school (~$25M), Menlo Park seminary acreage, St. Vincent's San Rafael (development 5+ years out; historic dorm buildings could take an interim lease). Oakland Diocese settled $143.5M — same dynamic. | AE27: =IF(LEFT(E27,2)="SF",IF(F27="",0,Weights!$B$2*MAX(0,MIN(1,(Weights!$B$9-F27)/(Weights!$B$9-Weights!$B$8)))),0) -> 0 | AF27: =IF(N27="",5,Weights!$B$3*MAX(0,MIN(1,(Weights!$B$7-N27)/(Weights!$B$7-Weights!$B$6)))) -> 5 | AG27: =IF(P27="none",0,IF(P27="unknown",5,Weights!$B$4)) -> 5 | AH27: =IF(K27="",4,IF(AND(K27>=Weights!$B$13,K27<=Weights!$B$14),Weights!$B$5,IF(K27>100,15,IF(K27>=20,12,4)))) -> 4 | AI27: =IF(OR(Q27="taken",Q27="sold",Q27="ruled-out"),0,MIN(IF(AND(H27="tourist-hotel",P27="none"),Weights!$B$11,100),AE27+AF27+AG27+AH27)+IF(T27="yes",Weights!$B$10,0)) -> 14 | AJ27: not-contacted | AK27: Jul 16 2026 (report)
A28: =RANK(AI28,$AI$2:$AI$70) -> 38 | B28: SureStay Plus Richmond — active default, 108 rooms | C28: Richmond (near I-80, ~20 min to Oakland) | D28: Richmond (East Bay) | E28: East Bay | F28: 75 | G28: est. by neighborhood (geocode in portal) | H28: tourist-hotel | I28: 108 | J28: 1 | K28: =IF(I28="","",I28*J28) -> 108 | L28: 900 | M28: 1300 | N28: =IF(L28="","",ROUND((L28+M28)/2/J28,0)) -> 1100 | O28: =IF(N28="","",N28*Weights!$B$12) -> 49500 | P28: none | Q28: receivership | R28: Bargain / distressed | T28: no | W28: In default on an $11.6M loan now | X28: Watch for receiver/auction; pitch the lender | Y28: monitor — pitch whoever takes the keys | Z28: — | AA28: via Bisnow coverage / county filings | AB28: Bargains / distressed | AC28: Bisnow, Jul 2026: https://www.bisnow.com/san-francisco/news/hotel/bay-area-hotel-market-recovering-distress-still-looms-135317 | AD28: Live distress in progress — the next Hyatt House-style giveaway could be here. Location is the tradeoff; monitor and pitch whoever takes the keys. | AE28: =IF(LEFT(E28,2)="SF",IF(F28="",0,Weights!$B$2*MAX(0,MIN(1,(Weights!$B$9-F28)/(Weights!$B$9-Weights!$B$8)))),0) -> 0 | AF28: =IF(N28="",5,Weights!$B$3*MAX(0,MIN(1,(Weights!$B$7-N28)/(Weights!$B$7-Weights!$B$6)))) -> 27.5 | AG28: =IF(P28="none",0,IF(P28="unknown",5,Weights!$B$4)) -> 0 | AH28: =IF(K28="",4,IF(AND(K28>=Weights!$B$13,K28<=Weights!$B$14),Weights!$B$5,IF(K28>100,15,IF(K28>=20,12,4)))) -> 15 | AI28: =IF(OR(Q28="taken",Q28="sold",Q28="ruled-out"),0,MIN(IF(AND(H28="tourist-hotel",P28="none"),Weights!$B$11,100),AE28+AF28+AG28+AH28)+IF(T28="yes",Weights!$B$10,0)) -> 40 | AJ28: not-contacted | AK28: Jul 16 2026 (report)
A29: =RANK(AI29,$AI$2:$AI$70) -> 38 | B29: Hotel Whitcomb floors — Blackstone wants an interim operator | C29: 1231 Market St, Mid-Market SF | D29: Civic Center | E29: SF-priority | F29: 3 | G29: est. by neighborhood (geocode in portal) | H29: tourist-hotel | I29: 80 | J29: 1 | K29: =IF(I29="","",I29*J29) -> 80 | L29: 1500 | M29: 2200 | N29: =IF(L29="","",ROUND((L29+M29)/2/J29,0)) -> 1850 | O29: =IF(N29="","",N29*Weights!$B$12) -> 83250 | P29: none | Q29: receivership | R29: Bargain / distressed | S29: q1-2027;expansion | T29: unknown | W29: Blackstone foreclosed Oct 2025; 'exploring new operators before offloading' | X29: Pitch Blackstone Mortgage Trust as the interim operator | Y29: Blackstone Real Estate — asset mgmt; 'exploring new operators' | Z29: — | AA29: via Blackstone RE press office / Hotel Whitcomb GM | AB29: Report §6e | AC29: SF Standard, Oct 2025: https://sfstandard.com/2025/10/02/hotel-whitcomb-mid-market-blackstone-rfr/ | AD29: UPGRADED from ruled-out: the lender is publicly looking for exactly what we are — an interim operator for a building that already housed people for 33 months (city shelter contract, ~$108M). Take a floor block, not the whole 459. Condition needs inspection after years dark. | AE29: =IF(LEFT(E29,2)="SF",IF(F29="",0,Weights!$B$2*MAX(0,MIN(1,(Weights!$B$9-F29)/(Weights!$B$9-Weights!$B$8)))),0) -> 35 | AF29: =IF(N29="",5,Weights!$B$3*MAX(0,MIN(1,(Weights!$B$7-N29)/(Weights!$B$7-Weights!$B$6)))) -> 8.75 | AG29: =IF(P29="none",0,IF(P29="unknown",5,Weights!$B$4)) -> 0 | AH29: =IF(K29="",4,IF(AND(K29>=Weights!$B$13,K29<=Weights!$B$14),Weights!$B$5,IF(K29>100,15,IF(K29>=20,12,4)))) -> 12 | AI29: =IF(OR(Q29="taken",Q29="sold",Q29="ruled-out"),0,MIN(IF(AND(H29="tourist-hotel",P29="none"),Weights!$B$11,100),AE29+AF29+AG29+AH29)+IF(T29="yes",Weights!$B$10,0)) -> 40 | AJ29: not-contacted | AK29: Jul 16 2026 (report)
A30: =RANK(AI30,$AI$2:$AI$70) -> 36 | B30: Salvation Army McFee Center — 96-bed building in entitlement limbo | C30: 1500 Valencia St + 3500 Cesar Chavez, Mission, SF | D30: Mission | E30: SF-other | F30: 35 | G30: est. by neighborhood (geocode in portal) | H30: dorm | I30: 48 | J30: 2 | K30: =IF(I30="","",I30*J30) -> 96 | N30: =IF(L30="","",ROUND((L30+M30)/2/J30,0)) | O30: =IF(N30="","",N30*Weights!$B$12) | P30: communal | Q30: on-market | R30: Bargain / distressed | S30: q1-2027;expansion | T30: no | W30: Listed Feb 2026 at $58M (land play) — interim income wanted | X30: Broker: Catherine Marcus Bassick, Douglas Elliman Commercial | Y30: Catherine Bassick — Douglas Elliman (listing broker) | Z30: — | AA30: elliman.com agent profile | AB30: Report §6e | AC30: SF Standard: https://sfstandard.com/2026/02/19/salvation-army-site-listing-mission/ TRD: https://therealdeal.com/san-francisco/2026/02/20/san-francisco-salvation-army-site-for-sale-for-58-million/ | AD30: $58M is a land-value ask that will take years to close and entitle. A seller holding a 96-bed residential building through a long sale/entitlement cycle is a textbook interim-master-lease counterparty — holding income strengthens their sale. | AE30: =IF(LEFT(E30,2)="SF",IF(F30="",0,Weights!$B$2*MAX(0,MIN(1,(Weights!$B$9-F30)/(Weights!$B$9-Weights!$B$8)))),0) -> 10 | AF30: =IF(N30="",5,Weights!$B$3*MAX(0,MIN(1,(Weights!$B$7-N30)/(Weights!$B$7-Weights!$B$6)))) -> 5 | AG30: =IF(P30="none",0,IF(P30="unknown",5,Weights!$B$4)) -> 15 | AH30: =IF(K30="",4,IF(AND(K30>=Weights!$B$13,K30<=Weights!$B$14),Weights!$B$5,IF(K30>100,15,IF(K30>=20,12,4)))) -> 12 | AI30: =IF(OR(Q30="taken",Q30="sold",Q30="ruled-out"),0,MIN(IF(AND(H30="tourist-hotel",P30="none"),Weights!$B$11,100),AE30+AF30+AG30+AH30)+IF(T30="yes",Weights!$B$10,0)) -> 42 | AJ30: not-contacted | AK30: Jul 16 2026 (report)
A31: =RANK(AI31,$AI$2:$AI$70) -> 29 | B31: ⏰ Mason at Hive — auction JULY 28 (12 days) | C31: 2350–2380 Valley St + 421 24th St, Uptown Oakland | D31: Uptown Oakland | E31: East Bay | F31: 45 | G31: est. by neighborhood (geocode in portal) | H31: apartment-block | I31: 105 | J31: 2 | K31: =IF(I31="","",I31*J31) -> 210 | L31: 2200 | M31: 2800 | N31: =IF(L31="","",ROUND((L31+M31)/2/J31,0)) -> 1250 | O31: =IF(N31="","",N31*Weights!$B$12) -> 56250 | P31: private | Q31: receivership | R31: Bargain / distressed | S31: expansion | T31: no | W31: $39.7M loan defaulted; assessed ~$36M; foreclosure auction July 28, 2026 | X31: Track the auction; approach the winner (or reverting lender) immediately after | AC31: TRD, Jul 13 2026: https://therealdeal.com/san-francisco/2026/07/13/oakland-apartments-headed-to-foreclosure-after-default/ | AD31: Foreclosure auction was July 28, 2026 — find out who won. | Verified July 16: auction still ON for July 28, no postponement/bankruptcy — and the building is already VACANT (FPI Management shows it closed), so the winner inherits 105 empty modern units and needs occupancy from day one. Ghielmetti says he's 'working with lenders on a resolution' — a pre-auction workout is possible; pitch both sides. Lenders: Chicago Title + Bellwether Enterprise. | AE31: =IF(LEFT(E31,2)="SF",IF(F31="",0,Weights!$B$2*MAX(0,MIN(1,(Weights!$B$9-F31)/(Weights!$B$9-Weights!$B$8)))),0) -> 0 | AF31: =IF(N31="",5,Weights!$B$3*MAX(0,MIN(1,(Weights!$B$7-N31)/(Weights!$B$7-Weights!$B$6)))) -> 23.75 | AG31: =IF(P31="none",0,IF(P31="unknown",5,Weights!$B$4)) -> 15 | AH31: =IF(K31="",4,IF(AND(K31>=Weights!$B$13,K31<=Weights!$B$14),Weights!$B$5,IF(K31>100,15,IF(K31>=20,12,4)))) -> 15 | AI31: =IF(OR(Q31="taken",Q31="sold",Q31="ruled-out"),0,MIN(IF(AND(H31="tourist-hotel",P31="none"),Weights!$B$11,100),AE31+AF31+AG31+AH31)+IF(T31="yes",Weights!$B$10,0)) -> 53.75 | AJ31: not-contacted | AK31: Jul 16 2026 (report)
A32: =RANK(AI32,$AI$2:$AI$70) -> 38 | B32: University Inn & Suites Berkeley — everyone is motivated | C32: 920 University Ave, Berkeley | D32: Berkeley | E32: East Bay | F32: 60 | G32: est. by neighborhood (geocode in portal) | H32: tourist-hotel | I32: 113 | J32: 1 | K32: =IF(I32="","",I32*J32) -> 113 | L32: 900 | M32: 1300 | N32: =IF(L32="","",ROUND((L32+M32)/2/J32,0)) -> 1100 | O32: =IF(N32="","",N32*Weights!$B$12) -> 49500 | P32: none | Q32: receivership | R32: Bargain / distressed | T32: no | W32: Bankruptcy, FOUR failed sales, lender (Wilmington Trust) moving to foreclose | X32: Approach via bankruptcy counsel / Wilmington Trust | AC32: TRD, Apr 2026: https://therealdeal.com/san-francisco/2026/04/16/berkeley-hotel-faces-foreclosure-after-sale-attempts-fail/ | AD32: An affordable-housing conversion buyer fell through in March 2026. A hotel nobody can sell, near UC Berkeley, with a lender trying to lift the stay = maximum desperation. 113 rooms covers 60+ with headroom; Berkeley location works for a split-campus model with the Southside rooming houses. | AE32: =IF(LEFT(E32,2)="SF",IF(F32="",0,Weights!$B$2*MAX(0,MIN(1,(Weights!$B$9-F32)/(Weights!$B$9-Weights!$B$8)))),0) -> 0 | AF32: =IF(N32="",5,Weights!$B$3*MAX(0,MIN(1,(Weights!$B$7-N32)/(Weights!$B$7-Weights!$B$6)))) -> 27.5 | AG32: =IF(P32="none",0,IF(P32="unknown",5,Weights!$B$4)) -> 0 | AH32: =IF(K32="",4,IF(AND(K32>=Weights!$B$13,K32<=Weights!$B$14),Weights!$B$5,IF(K32>100,15,IF(K32>=20,12,4)))) -> 15 | AI32: =IF(OR(Q32="taken",Q32="sold",Q32="ruled-out"),0,MIN(IF(AND(H32="tourist-hotel",P32="none"),Weights!$B$11,100),AE32+AF32+AG32+AH32)+IF(T32="yes",Weights!$B$10,0)) -> 40 | AJ32: not-contacted | AK32: Jul 16 2026 (report)
A33: =RANK(AI33,$AI$2:$AI$70) -> 55 | B33: Hotel Avante + Wild Palms — one owner, both in default (Peninsula) | C33: 860 E El Camino Real, Mountain View + 801 E Fremont Ave, Sunnyvale | D33: Mountain View / Sunnyvale | E33: Peninsula | F33: 120 | G33: est. by neighborhood (geocode in portal) | H33: tourist-hotel | I33: 299 | J33: 1 | K33: =IF(I33="","",I33*J33) -> 299 | L33: 1200 | M33: 1800 | N33: =IF(L33="","",ROUND((L33+M33)/2/J33,0)) -> 1500 | O33: =IF(N33="","",N33*Weights!$B$12) -> 67500 | P33: none | Q33: receivership | R33: Bargain / distressed | T33: no | W33: Combined $54.1M loan in default (NOD Mar 2026, matured Jan 2026) | X33: One conversation: owners Stephen Conley (JdV founder) & Jeffrey Eisenberg | AC33: TRD, Mar 2026: https://therealdeal.com/san-francisco/2026/03/25/default-looms-for-two-more-bay-area-hotels/ | AD33: A hospitality-literate owner facing a matured loan — a master lease that stabilizes NOI pre-foreclosure is a lifeline for him. 91-room Avante fits the cohort exactly; Wild Palms adds 200+ rooms of expansion. Peninsula/Caltrain geography if the program wants a South Bay campus. | AE33: =IF(LEFT(E33,2)="SF",IF(F33="",0,Weights!$B$2*MAX(0,MIN(1,(Weights!$B$9-F33)/(Weights!$B$9-Weights!$B$8)))),0) -> 0 | AF33: =IF(N33="",5,Weights!$B$3*MAX(0,MIN(1,(Weights!$B$7-N33)/(Weights!$B$7-Weights!$B$6)))) -> 17.5 | AG33: =IF(P33="none",0,IF(P33="unknown",5,Weights!$B$4)) -> 0 | AH33: =IF(K33="",4,IF(AND(K33>=Weights!$B$13,K33<=Weights!$B$14),Weights!$B$5,IF(K33>100,15,IF(K33>=20,12,4)))) -> 15 | AI33: =IF(OR(Q33="taken",Q33="sold",Q33="ruled-out"),0,MIN(IF(AND(H33="tourist-hotel",P33="none"),Weights!$B$11,100),AE33+AF33+AG33+AH33)+IF(T33="yes",Weights!$B$10,0)) -> 32.5 | AJ33: not-contacted | AK33: Jul 16 2026 (report)
A34: =RANK(AI34,$AI$2:$AI$70) -> 49 | B34: San Jose distress cluster | C34: La Quinta 1036 N 4th St (59 rms, built 2023) + Fontaine Rd cluster (256 rms) | D34: San Jose | E34: Peninsula | F34: 120 | G34: est. by neighborhood (geocode in portal) | H34: tourist-hotel | I34: 315 | J34: 1 | K34: =IF(I34="","",I34*J34) -> 315 | L34: 1000 | M34: 1500 | N34: =IF(L34="","",ROUND((L34+M34)/2/J34,0)) -> 1250 | O34: =IF(N34="","",N34*Weights!$B$12) -> 56250 | P34: none | Q34: receivership | R34: Bargain / distressed | T34: no | W34: All in active loan default | X34: Pitch owners/lenders; new-build La Quinta is the quality pick | AC34: TRD, May 2026: https://therealdeal.com/san-francisco/2026/05/28/another-bay-area-hotel-flops-into-loan-default/ TRD, Jun 2026: https://therealdeal.com/san-francisco/2026/06/05/another-san-jose-hotel-falls-into-default/ Hoodline — Fontaine: https://hoodline.com/2026/02/san-jose-motel-boss-slams-bankruptcy-brakes-on-foreclosure-fight/ | AD34: La Quinta: $16M construction loan in default on a 2023 building — new-build quality at distress leverage, near Civic Center VTA. Fontaine Rd: Fontaine Inn + Motel 6/Super 8 (204 rms) both in default; East SJ location is car-dependent. Only relevant if the program considers a South Bay campus. | AE34: =IF(LEFT(E34,2)="SF",IF(F34="",0,Weights!$B$2*MAX(0,MIN(1,(Weights!$B$9-F34)/(Weights!$B$9-Weights!$B$8)))),0) -> 0 | AF34: =IF(N34="",5,Weights!$B$3*MAX(0,MIN(1,(Weights!$B$7-N34)/(Weights!$B$7-Weights!$B$6)))) -> 23.75 | AG34: =IF(P34="none",0,IF(P34="unknown",5,Weights!$B$4)) -> 0 | AH34: =IF(K34="",4,IF(AND(K34>=Weights!$B$13,K34<=Weights!$B$14),Weights!$B$5,IF(K34>100,15,IF(K34>=20,12,4)))) -> 15 | AI34: =IF(OR(Q34="taken",Q34="sold",Q34="ruled-out"),0,MIN(IF(AND(H34="tourist-hotel",P34="none"),Weights!$B$11,100),AE34+AF34+AG34+AH34)+IF(T34="yes",Weights!$B$10,0)) -> 38.75 | AJ34: not-contacted | AK34: Jul 16 2026 (report)
A35: =RANK(AI35,$AI$2:$AI$70) -> 51 | B35: NDNU Belmont — six mothballed residence halls | C35: 1500 Ralston Ave, Belmont (Caltrain ~1 mi) | D35: Belmont | E35: Peninsula | F35: 90 | G35: est. by neighborhood (geocode in portal) | H35: dorm | I35: 250 | J35: 2 | K35: =IF(I35="","",I35*J35) -> 500 | N35: =IF(L35="","",ROUND((L35+M35)/2/J35,0)) | O35: =IF(N35="","",N35*Weights!$B$12) | P35: communal | Q35: dark | R35: Direct approach | S35: expansion | T35: no | W35: UC Investments bought Sept 2025; NDNU leases back up to 5 years | X35: Approach UC Investments (landlord) + NDNU (operator) jointly | AC35: GlobeNewswire: https://www.globenewswire.com/news-release/2025/09/29/3158017/0/en/Notre-Dame-de-Namur-University-Announces-the-Completed-Sale-of-the-Belmont-Campus-to-UC-Investments.html NDNU FAQ: https://www.ndnu.edu/wp-content/uploads/NDNU-Property-Sale-to-UC-Investments-FAQs.pdf | AD35: Round-5 check: NDNU's own site says 'on-campus housing is not available' — six residence buildings sit mothballed and NO public document accounts for them. That silence is the opening: nobody else is pitching for these beds. Peninsula option; bed counts need a direct ask. | AE35: =IF(LEFT(E35,2)="SF",IF(F35="",0,Weights!$B$2*MAX(0,MIN(1,(Weights!$B$9-F35)/(Weights!$B$9-Weights!$B$8)))),0) -> 0 | AF35: =IF(N35="",5,Weights!$B$3*MAX(0,MIN(1,(Weights!$B$7-N35)/(Weights!$B$7-Weights!$B$6)))) -> 5 | AG35: =IF(P35="none",0,IF(P35="unknown",5,Weights!$B$4)) -> 15 | AH35: =IF(K35="",4,IF(AND(K35>=Weights!$B$13,K35<=Weights!$B$14),Weights!$B$5,IF(K35>100,15,IF(K35>=20,12,4)))) -> 15 | AI35: =IF(OR(Q35="taken",Q35="sold",Q35="ruled-out"),0,MIN(IF(AND(H35="tourist-hotel",P35="none"),Weights!$B$11,100),AE35+AF35+AG35+AH35)+IF(T35="yes",Weights!$B$10,0)) -> 35 | AJ35: not-contacted | AK35: Jul 16 2026 (report)
A36: =RANK(AI36,$AI$2:$AI$70) -> 15 | B36: CCA surplus dorms — perfect bridge year | C36: Founders Hall, 188 Hooper St, Design District, SF | D36: Design District / Potrero | E36: SF-other | F36: 35 | G36: est. by neighborhood (geocode in portal) | H36: dorm | I36: 135 | J36: 2 | K36: =IF(I36="","",I36*J36) -> 270 | L36: 1100 | M36: 1500 | N36: =IF(L36="","",ROUND((L36+M36)/2/J36,0)) -> 650 | O36: =IF(N36="","",N36*Weights!$B$12) -> 29250 | P36: communal | Q36: active | R36: Co-living / bridge | S36: bridge-sept;q1-2027;expansion | T36: unknown | W36: School closing; Vanderbilt takes over 2027-28 | X36: Call CCA administration/housing about a 2026-27 block | Y36: Charles Eden, NCCD President → Capstone Management → housing@cca.edu | Z36: (512) 322-9650 | AA36: geden@nccdevelopment.org | AB36: Report §6e | AC36: NCCD project page: https://nccdevelopment.org/master-portfolio/california-college-of-the-arts CCA intern-housing precedent: https://portal.cca.edu/thriving/housing-dining-resed/resident-halls/summer-intern-housing-cca/ SF Standard — closure: https://sfstandard.com/2026/01/16/cca-president-david-howse-closure-shocked-art-world/ | AD36: ~270 surplus beds 2026-27. Attack order: Charles Eden, NCCD (512) 322-9650 geden@nccdevelopment.org → Capstone Management → housing@cca.edu. Precedent: Blattner Hall rents to non-CCA interns at $69/night. | Round-5 deep-dive strengthens this: Founders Hall is ~520 beds, owned via a $90M P3 with NCCD — and a bondholder-side owner has every incentive to backfill empty beds. PRECEDENT EXISTS: CCA already rents beds to non-CCA interns at Blattner Hall ($69/night, run by Capstone Management). Attack order: (1) Charles Eden, NCCD President, 512-322-9650, geden@nccdevelopment.org; (2) Capstone Management Partners; (3) housing@cca.edu / (415) 703-9500. | AE36: =IF(LEFT(E36,2)="SF",IF(F36="",0,Weights!$B$2*MAX(0,MIN(1,(Weights!$B$9-F36)/(Weights!$B$9-Weights!$B$8)))),0) -> 10 | AF36: =IF(N36="",5,Weights!$B$3*MAX(0,MIN(1,(Weights!$B$7-N36)/(Weights!$B$7-Weights!$B$6)))) -> 30 | AG36: =IF(P36="none",0,IF(P36="unknown",5,Weights!$B$4)) -> 15 | AH36: =IF(K36="",4,IF(AND(K36>=Weights!$B$13,K36<=Weights!$B$14),Weights!$B$5,IF(K36>100,15,IF(K36>=20,12,4)))) -> 15 | AI36: =IF(OR(Q36="taken",Q36="sold",Q36="ruled-out"),0,MIN(IF(AND(H36="tourist-hotel",P36="none"),Weights!$B$11,100),AE36+AF36+AG36+AH36)+IF(T36="yes",Weights!$B$10,0)) -> 70 | AJ36: not-contacted | AK36: Jul 16 2026 (report)
A37: =RANK(AI37,$AI$2:$AI$70) -> 9 | B37: Boston Hotel (SRO) | C37: 140 Turk St, SF | D37: Civic Center | E37: SF-priority | F37: 6 | G37: est. by neighborhood (geocode in portal) | H37: sro-hotel | I37: 32 | J37: 1 | K37: =IF(I37="","",I37*J37) -> 32 | L37: 1100 | M37: 1500 | N37: =IF(L37="","",ROUND((L37+M37)/2/J37,0)) -> 1300 | O37: =IF(N37="","",N37*Weights!$B$12) -> 58500 | P37: communal | Q37: on-market | R37: Pair / cluster | S37: q1-2027;femme-house | T37: unknown | W37: $1.95M (~$61k/key) | X37: Lowball both; Blue broker: Theodore Wong (Compass), 650-228-9930 | Y37: Jag Patel — Lee & Associates | Z37: (415) 517-9856 | AA37: jpatel@lee-associates.com | AB37: On-market listings | AC37: Blue Hotel LoopNet: https://www.loopnet.com/Listing/620-OFarrell-St-San-Francisco-CA/25102642/ LoopNet SF hotels: https://www.loopnet.com/search/hotels/san-francisco-ca/for-sale/ 620 O'Farrell Compass: https://www.compass.com/listing/620-ofarrell-street-san-francisco-ca-94109/1860335630965776937/ | AD37: The cheapest way to control ~45 rooms in SF ($4.25M combined ≈ 5 years of rent budget, or master-lease both). Blue Hotel's 415+ days on market and price cut = real desperation. Add Motel 6 Eddy St (68 rooms, 2 blocks away) to scale past 100. | AE37: =IF(LEFT(E37,2)="SF",IF(F37="",0,Weights!$B$2*MAX(0,MIN(1,(Weights!$B$9-F37)/(Weights!$B$9-Weights!$B$8)))),0) -> 35 | AF37: =IF(N37="",5,Weights!$B$3*MAX(0,MIN(1,(Weights!$B$7-N37)/(Weights!$B$7-Weights!$B$6)))) -> 22.5 | AG37: =IF(P37="none",0,IF(P37="unknown",5,Weights!$B$4)) -> 15 | AH37: =IF(K37="",4,IF(AND(K37>=Weights!$B$13,K37<=Weights!$B$14),Weights!$B$5,IF(K37>100,15,IF(K37>=20,12,4)))) -> 12 | AI37: =IF(OR(Q37="taken",Q37="sold",Q37="ruled-out"),0,MIN(IF(AND(H37="tourist-hotel",P37="none"),Weights!$B$11,100),AE37+AF37+AG37+AH37)+IF(T37="yes",Weights!$B$10,0)) -> 84.5 | AJ37: not-contacted | AK37: Jul 16 2026 (report)
A38: =RANK(AI38,$AI$2:$AI$70) -> 18 | B38: Blue Hotel | C38: 620–626 O'Farrell St, SF | D38: Civic Center | E38: SF-priority | F38: 10 | G38: est. by neighborhood (geocode in portal) | H38: sro-hotel | I38: 13 | J38: 1 | K38: =IF(I38="","",I38*J38) -> 13 | L38: 1100 | M38: 1500 | N38: =IF(L38="","",ROUND((L38+M38)/2/J38,0)) -> 1300 | O38: =IF(N38="","",N38*Weights!$B$12) -> 58500 | P38: unknown | Q38: on-market | R38: Pair / cluster | S38: femme-house | T38: unknown | W38: $2.3M (cut from $2.6M) | X38: Lowball both; Blue broker: Theodore Wong (Compass), 650-228-9930 | Y38: Theodore Wong — Compass Commercial | Z38: (650) 228-9930 | AA38: — | AB38: On-market listings | AC38: Blue Hotel LoopNet: https://www.loopnet.com/Listing/620-OFarrell-St-San-Francisco-CA/25102642/ LoopNet SF hotels: https://www.loopnet.com/search/hotels/san-francisco-ca/for-sale/ 620 O'Farrell Compass: https://www.compass.com/listing/620-ofarrell-street-san-francisco-ca-94109/1860335630965776937/ | AD38: The cheapest way to control ~45 rooms in SF ($4.25M combined ≈ 5 years of rent budget, or master-lease both). Blue Hotel's 415+ days on market and price cut = real desperation. Add Motel 6 Eddy St (68 rooms, 2 blocks away) to scale past 100. | AE38: =IF(LEFT(E38,2)="SF",IF(F38="",0,Weights!$B$2*MAX(0,MIN(1,(Weights!$B$9-F38)/(Weights!$B$9-Weights!$B$8)))),0) -> 35 | AF38: =IF(N38="",5,Weights!$B$3*MAX(0,MIN(1,(Weights!$B$7-N38)/(Weights!$B$7-Weights!$B$6)))) -> 22.5 | AG38: =IF(P38="none",0,IF(P38="unknown",5,Weights!$B$4)) -> 5 | AH38: =IF(K38="",4,IF(AND(K38>=Weights!$B$13,K38<=Weights!$B$14),Weights!$B$5,IF(K38>100,15,IF(K38>=20,12,4)))) -> 4 | AI38: =IF(OR(Q38="taken",Q38="sold",Q38="ruled-out"),0,MIN(IF(AND(H38="tourist-hotel",P38="none"),Weights!$B$11,100),AE38+AF38+AG38+AH38)+IF(T38="yes",Weights!$B$10,0)) -> 66.5 | AJ38: not-contacted | AK38: Jul 16 2026 (report)
A39: =RANK(AI39,$AI$2:$AI$70) -> 51 | B39: Adams Point cluster (6 listings) | C39: 469 Van Buren + 286 Lenox + 303 Lee + 369 Palm, Lake Merritt, Oakland | D39: Lake Merritt, Oakland | E39: East Bay | F39: 50 | G39: est. by neighborhood (geocode in portal) | H39: apartment-block | I39: 110 | J39: 1 | K39: =IF(I39="","",I39*J39) -> 110 | N39: =IF(L39="","",ROUND((L39+M39)/2/J39,0)) | O39: =IF(N39="","",N39*Weights!$B$12) | P39: private | Q39: on-market | R39: Pair / cluster | T39: no | W39: Pairs $11.9–12.1M | X39: Lease or buy any two, 3-min walk apart | Y39: Matt Treadway — The Lapham Company | Z39: (415) 640-6411 · office (510) 594-7600 | AA39: info@laphamcompany.com | AB39: Pairs & clusters | AC39: LoopNet Adams Point: https://www.loopnet.com/search/apartment-buildings/adams-point-oakland-ca/for-sale/ | AD39: Six active multifamily listings in one walkable pocket near Lake Merritt/19th St BART. Best pairing: 469 Van Buren + 286 Lenox ≈ 50–60 beds. Oakland's softness makes lease-with-option pitches credible on all of them. | AE39: =IF(LEFT(E39,2)="SF",IF(F39="",0,Weights!$B$2*MAX(0,MIN(1,(Weights!$B$9-F39)/(Weights!$B$9-Weights!$B$8)))),0) -> 0 | AF39: =IF(N39="",5,Weights!$B$3*MAX(0,MIN(1,(Weights!$B$7-N39)/(Weights!$B$7-Weights!$B$6)))) -> 5 | AG39: =IF(P39="none",0,IF(P39="unknown",5,Weights!$B$4)) -> 15 | AH39: =IF(K39="",4,IF(AND(K39>=Weights!$B$13,K39<=Weights!$B$14),Weights!$B$5,IF(K39>100,15,IF(K39>=20,12,4)))) -> 15 | AI39: =IF(OR(Q39="taken",Q39="sold",Q39="ruled-out"),0,MIN(IF(AND(H39="tourist-hotel",P39="none"),Weights!$B$11,100),AE39+AF39+AG39+AH39)+IF(T39="yes",Weights!$B$10,0)) -> 35 | AJ39: not-contacted | AK39: Jul 16 2026 (report)
A40: =RANK(AI40,$AI$2:$AI$70) -> 20 | B40: Berkeley rooming-house block (White House / G-House / Piedmont Palace / TBG) | C40: Piedmont Ave + Haste/Dwight, Southside Berkeley | D40: Berkeley | E40: East Bay | F40: 55 | G40: est. by neighborhood (geocode in portal) | H40: co-living | I40: 60 | J40: 1 | K40: =IF(I40="","",I40*J40) -> 60 | L40: 1050 | M40: 1480 | N40: =IF(L40="","",ROUND((L40+M40)/2/J40,0)) -> 1265 | O40: =IF(N40="","",N40*Weights!$B$12) -> 56925 | P40: communal | Q40: active | R40: Pair / cluster | T40: yes | W40: $1,050–1,480/bed | X40: Block-book across 2–3 buildings; TBG = one operator | Y40: TBG Property Management | Z40: (510) 907-6365 (call/text/WhatsApp) | AA40: leasing@tbgpm.com · hello@tbgpm.com | AB40: Pairs & clusters | AC40: White House — och.berkeley.edu: https://och.berkeley.edu/housing/property/white-house-rooming-house-3-blocks-to-ucb-southside-large-private-and-shared-furnished-rooms/ocp8826vp1 G-House: https://www.homes.com/property/g-house-berkeley-ca/17qx1jtb58wqq/ Piedmont Palace: https://www.homes.com/property/piedmont-palace-berkeley-ca/ktkh0krec3rf3/ TBG: https://tbgpm.com/ | AD40: An operating cluster of by-the-bed furnished buildings within ~3 blocks, with Aug/Sept academic-year move-ins. Lowest execution risk of any pair play; BART to SF. TBG manages multiple adjacent buildings — a single master-lease counterparty. | AE40: =IF(LEFT(E40,2)="SF",IF(F40="",0,Weights!$B$2*MAX(0,MIN(1,(Weights!$B$9-F40)/(Weights!$B$9-Weights!$B$8)))),0) -> 0 | AF40: =IF(N40="",5,Weights!$B$3*MAX(0,MIN(1,(Weights!$B$7-N40)/(Weights!$B$7-Weights!$B$6)))) -> 23.375 | AG40: =IF(P40="none",0,IF(P40="unknown",5,Weights!$B$4)) -> 15 | AH40: =IF(K40="",4,IF(AND(K40>=Weights!$B$13,K40<=Weights!$B$14),Weights!$B$5,IF(K40>100,15,IF(K40>=20,12,4)))) -> 20 | AI40: =IF(OR(Q40="taken",Q40="sold",Q40="ruled-out"),0,MIN(IF(AND(H40="tourist-hotel",P40="none"),Weights!$B$11,100),AE40+AF40+AG40+AH40)+IF(T40="yes",Weights!$B$10,0)) -> 63.375 | AJ40: not-contacted | AK40: Jul 16 2026 (report)
A41: =RANK(AI41,$AI$2:$AI$70) -> 23 | B41: 1538 Polk St + AAU cluster pairing | C41: Polk Gulch / Lower Nob Hill, SF | D41: Nob Hill | E41: SF-priority | F41: 22 | G41: est. by neighborhood (geocode in portal) | H41: apartment-block | I41: 43 | J41: 1 | K41: =IF(I41="","",I41*J41) -> 43 | L41: 1800 | M41: 2400 | N41: =IF(L41="","",ROUND((L41+M41)/2/J41,0)) -> 2100 | O41: =IF(N41="","",N41*Weights!$B$12) -> 94500 | P41: private | Q41: on-market | R41: Pair / cluster | S41: q1-2027 | T41: no | W41: $4.5M ask | X41: Pair with an AAU dorm lease | Y41: Brian Leung / Jeremy Lee — Compass Commercial | Z41: (415) 278-7838 / (650) 219-3989 | AA41: brian.leung@compass.com · jeremy.lee@compass.com | AB41: Pairs & clusters | AC41: LoopNet Nob Hill apartments: https://www.loopnet.com/search/apartment-buildings/nob-hill-san-francisco-ca/for-sale/ | AD41: Cheap 43-unit building walking distance from the AAU dorm cluster — a purchase-or-lease complement if AAU only gives up one building. | AE41: =IF(LEFT(E41,2)="SF",IF(F41="",0,Weights!$B$2*MAX(0,MIN(1,(Weights!$B$9-F41)/(Weights!$B$9-Weights!$B$8)))),0) -> 23 | AF41: =IF(N41="",5,Weights!$B$3*MAX(0,MIN(1,(Weights!$B$7-N41)/(Weights!$B$7-Weights!$B$6)))) -> 2.5 | AG41: =IF(P41="none",0,IF(P41="unknown",5,Weights!$B$4)) -> 15 | AH41: =IF(K41="",4,IF(AND(K41>=Weights!$B$13,K41<=Weights!$B$14),Weights!$B$5,IF(K41>100,15,IF(K41>=20,12,4)))) -> 20 | AI41: =IF(OR(Q41="taken",Q41="sold",Q41="ruled-out"),0,MIN(IF(AND(H41="tourist-hotel",P41="none"),Weights!$B$11,100),AE41+AF41+AG41+AH41)+IF(T41="yes",Weights!$B$10,0)) -> 60.5 | AJ41: not-contacted | AK41: Jul 16 2026 (report)
A42: =RANK(AI42,$AI$2:$AI$70) -> 17 | B42: Villages at Treasure Island — cheapest beds in SF proper | C42: 410 Avenue of the Palms, Treasure Island, SF | D42: Treasure Island | E42: SF-other | F42: 45 | G42: est. by neighborhood (geocode in portal) | H42: apartment-block | I42: 15 | J42: 3 | K42: =IF(I42="","",I42*J42) -> 45 | L42: 2600 | M42: 3900 | N42: =IF(L42="","",ROUND((L42+M42)/2/J42,0)) -> 1083 | O42: =IF(N42="","",N42*Weights!$B$12) -> 48735 | P42: private | Q42: active | R42: Premium value | S42: bridge-sept;expansion | T42: yes | W42: From ~$2,600/townhome = $870–1,300/bed | X42: Confirm 2026–27 unit runway with John Stewart Co. | Y42: John Stewart Co. leasing | Z42: (415) 834-0211 | AA42: jsco.net form | AB42: Premium value & co-living / bridge | AC42: Apartments.com: https://www.apartments.com/villages-at-treasure-island-san-francisco-ca/87189j0/ John Stewart Co.: https://jsco.net/management/affordable-market-rate-housing/the-villages-at-treasure-island/ tisf.com: https://www.tisf.com/live-here | AD42: Whole homes with living rooms and yards at pod prices. 15–20 townhomes = 40–60 beds. Caveats: redevelopment is phasing interim housing out (confirm runway), and it's a ferry/Muni commute. | AE42: =IF(LEFT(E42,2)="SF",IF(F42="",0,Weights!$B$2*MAX(0,MIN(1,(Weights!$B$9-F42)/(Weights!$B$9-Weights!$B$8)))),0) -> 0 | AF42: =IF(N42="",5,Weights!$B$3*MAX(0,MIN(1,(Weights!$B$7-N42)/(Weights!$B$7-Weights!$B$6)))) -> 27.925 | AG42: =IF(P42="none",0,IF(P42="unknown",5,Weights!$B$4)) -> 15 | AH42: =IF(K42="",4,IF(AND(K42>=Weights!$B$13,K42<=Weights!$B$14),Weights!$B$5,IF(K42>100,15,IF(K42>=20,12,4)))) -> 20 | AI42: =IF(OR(Q42="taken",Q42="sold",Q42="ruled-out"),0,MIN(IF(AND(H42="tourist-hotel",P42="none"),Weights!$B$11,100),AE42+AF42+AG42+AH42)+IF(T42="yes",Weights!$B$10,0)) -> 67.925 | AJ42: not-contacted | AK42: Jul 16 2026 (report)
A43: =RANK(AI43,$AI$2:$AI$70) -> 4 | B43: FOUND Study SF — built for exactly this | C43: 16 Turk St / 25 Mason St, Mid-Market SF | D43: Civic Center | E43: SF-priority | F43: 5 | G43: est. by neighborhood (geocode in portal) | H43: dorm | I43: 72 | J43: 2 | K43: =IF(I43="","",I43*J43) -> 144 | L43: 1400 | M43: 3800 | N43: =IF(L43="","",ROUND((L43+M43)/2/J43,0)) -> 1300 | O43: =IF(N43="","",N43*Weights!$B$12) -> 58500 | P43: communal | Q43: active | R43: Premium value | S43: bridge-sept;q1-2027;femme-house;expansion | T43: yes | W43: $700–1,900/bed ALL-IN (furniture, wifi, utilities), 4/5/9/12-mo terms | X43: Group contract (they already do university blocks) | Y43: Group/institutional advisor · SF GM | Z43: (917) 551-5588 · (628) 246-9210 ⚠ · corporate (866) 341-2818 | AA43: gm@sf.foundstudy.com | AB43: Premium value & co-living / bridge | AC43: foundstudy.com: https://www.foundstudy.com/sanfrancisco RentCafe pricing: https://www.rentcafe.com/apartments/ca/san-francisco/25-mason-street/default.aspx USF partnership: https://www.foundstudy.com/usfca | AD43: $700–1,900/bed all-in, 4/5/9/12-month terms, group contracts. Also in Notion tracker (shared from $850). | Purpose-built student residence with flexible Aug/Sept move-ins and existing institutional partnerships (USF). Interiors far nicer than any SRO; the block outside is still Tenderloin-edge. | AE43: =IF(LEFT(E43,2)="SF",IF(F43="",0,Weights!$B$2*MAX(0,MIN(1,(Weights!$B$9-F43)/(Weights!$B$9-Weights!$B$8)))),0) -> 35 | AF43: =IF(N43="",5,Weights!$B$3*MAX(0,MIN(1,(Weights!$B$7-N43)/(Weights!$B$7-Weights!$B$6)))) -> 22.5 | AG43: =IF(P43="none",0,IF(P43="unknown",5,Weights!$B$4)) -> 15 | AH43: =IF(K43="",4,IF(AND(K43>=Weights!$B$13,K43<=Weights!$B$14),Weights!$B$5,IF(K43>100,15,IF(K43>=20,12,4)))) -> 15 | AI43: =IF(OR(Q43="taken",Q43="sold",Q43="ruled-out"),0,MIN(IF(AND(H43="tourist-hotel",P43="none"),Weights!$B$11,100),AE43+AF43+AG43+AH43)+IF(T43="yes",Weights!$B$10,0)) -> 92.5 | AJ43: not-contacted | AK43: Jul 16 2026 (report)
A44: =RANK(AI44,$AI$2:$AI$70) -> 36 | B44: Presidio Residences — national-park living at target price | C44: Presidio, SF (24 neighborhoods, 1,100+ units) | D44: Presidio | E44: SF-other | F44: 60 | G44: est. by neighborhood (geocode in portal) | H44: apartment-block | I44: 10 | J44: 3 | K44: =IF(I44="","",I44*J44) -> 30 | L44: 4700 | M44: 6100 | N44: =IF(L44="","",ROUND((L44+M44)/2/J44,0)) -> 1800 | O44: =IF(N44="","",N44*Weights!$B$12) -> 81000 | P44: private | Q44: active | R44: Premium value | S44: femme-house | T44: yes | W44: At target for quality far beyond it | X44: Interest-form queue; slow at scale | Y44: Main / West office | Z44: (844) 808-6177 · (844) 729-8087 | AA44: leasing@presidio-residences.com | AB44: Premium value & co-living / bridge | AC44: Rate sheet (PDF): https://resource.rentcafe.com/image/upload/s3/2/15652/rental_rate_sheet.pdf presidio.gov leasing: https://www.presidio.gov/presidio-residences-leasing/ | AD44: Exceptional setting at exactly the number. Blockers: queue + Presidio-employee priority + you'd need 10–15 homes. Realistic for 15–25 people over time — a satellite, not the main campus. | AE44: =IF(LEFT(E44,2)="SF",IF(F44="",0,Weights!$B$2*MAX(0,MIN(1,(Weights!$B$9-F44)/(Weights!$B$9-Weights!$B$8)))),0) -> 0 | AF44: =IF(N44="",5,Weights!$B$3*MAX(0,MIN(1,(Weights!$B$7-N44)/(Weights!$B$7-Weights!$B$6)))) -> 10 | AG44: =IF(P44="none",0,IF(P44="unknown",5,Weights!$B$4)) -> 15 | AH44: =IF(K44="",4,IF(AND(K44>=Weights!$B$13,K44<=Weights!$B$14),Weights!$B$5,IF(K44>100,15,IF(K44>=20,12,4)))) -> 12 | AI44: =IF(OR(Q44="taken",Q44="sold",Q44="ruled-out"),0,MIN(IF(AND(H44="tourist-hotel",P44="none"),Weights!$B$11,100),AE44+AF44+AG44+AH44)+IF(T44="yes",Weights!$B$10,0)) -> 42 | AJ44: not-contacted | AK44: Jul 16 2026 (report)
A45: =RANK(AI45,$AI$2:$AI$70) -> 32 | B45: 17th & Broadway — Class A 2BR block | C45: 447 17th St, Uptown Oakland | D45: Uptown Oakland | E45: East Bay | F45: 40 | G45: est. by neighborhood (geocode in portal) | H45: apartment-block | I45: 25 | J45: 2 | K45: =IF(I45="","",I45*J45) -> 50 | L45: 3500 | M45: 3811 | N45: =IF(L45="","",ROUND((L45+M45)/2/J45,0)) -> 1828 | O45: =IF(N45="","",N45*Weights!$B$12) -> 82260 | P45: private | Q45: active | R45: Premium value | T45: yes | W45: ~$1,750–1,900/bed with negotiated concessions | X45: Corporate block (already on SilverDoor) | Y45: Leasing | Z45: (510) 621-6522 | AA45: 17thandbroadway.com | AB45: Premium value & co-living / bridge | AC45: Apartments.com: https://www.apartments.com/17th-and-broadway-oakland-ca/f6jbmws/ SilverDoor: https://www.silverdoor.com/17th-broadway-oakland-25793 | AD45: Pool, 34th-floor open-air lounge, furnished options; already sells through corporate-housing channels, so a 20–25 unit block is a familiar ask. | AE45: =IF(LEFT(E45,2)="SF",IF(F45="",0,Weights!$B$2*MAX(0,MIN(1,(Weights!$B$9-F45)/(Weights!$B$9-Weights!$B$8)))),0) -> 0 | AF45: =IF(N45="",5,Weights!$B$3*MAX(0,MIN(1,(Weights!$B$7-N45)/(Weights!$B$7-Weights!$B$6)))) -> 9.3 | AG45: =IF(P45="none",0,IF(P45="unknown",5,Weights!$B$4)) -> 15 | AH45: =IF(K45="",4,IF(AND(K45>=Weights!$B$13,K45<=Weights!$B$14),Weights!$B$5,IF(K45>100,15,IF(K45>=20,12,4)))) -> 20 | AI45: =IF(OR(Q45="taken",Q45="sold",Q45="ruled-out"),0,MIN(IF(AND(H45="tourist-hotel",P45="none"),Weights!$B$11,100),AE45+AF45+AG45+AH45)+IF(T45="yes",Weights!$B$10,0)) -> 49.3 | AJ45: not-contacted | AK45: Jul 16 2026 (report)
A46: =RANK(AI46,$AI$2:$AI$70) -> 34 | B46: Atlas Oakland — 3-per-2BR math works | C46: 385 14th St, Downtown Oakland | D46: Downtown Oakland | E46: East Bay | F46: 40 | G46: est. by neighborhood (geocode in portal) | H46: apartment-block | I46: 25 | J46: 3 | K46: =IF(I46="","",I46*J46) -> 75 | L46: 4340 | M46: 5335 | N46: =IF(L46="","",ROUND((L46+M46)/2/J46,0)) -> 1613 | O46: =IF(N46="","",N46*Weights!$B$12) -> 72585 | P46: private | Q46: active | R46: Premium value | T46: yes | W46: $1,447/bed at 3 sleepers per 2BR (den/living conversion) | X46: Call for block pricing ($500 look-and-lease running) | Y46: Leasing | Z46: (510) 983-5478 | AA46: atlasoakland.com | AB46: Premium value & co-living / bridge | AC46: atlasoakland.com: https://www.atlasoakland.com/floorplans | AD46: Oakland's tallest residential tower with lease-up pressure. Same submarket economics as 1900 Broadway — play them against each other. | AE46: =IF(LEFT(E46,2)="SF",IF(F46="",0,Weights!$B$2*MAX(0,MIN(1,(Weights!$B$9-F46)/(Weights!$B$9-Weights!$B$8)))),0) -> 0 | AF46: =IF(N46="",5,Weights!$B$3*MAX(0,MIN(1,(Weights!$B$7-N46)/(Weights!$B$7-Weights!$B$6)))) -> 14.675 | AG46: =IF(P46="none",0,IF(P46="unknown",5,Weights!$B$4)) -> 15 | AH46: =IF(K46="",4,IF(AND(K46>=Weights!$B$13,K46<=Weights!$B$14),Weights!$B$5,IF(K46>100,15,IF(K46>=20,12,4)))) -> 12 | AI46: =IF(OR(Q46="taken",Q46="sold",Q46="ruled-out"),0,MIN(IF(AND(H46="tourist-hotel",P46="none"),Weights!$B$11,100),AE46+AF46+AG46+AH46)+IF(T46="yes",Weights!$B$10,0)) -> 46.675 | AJ46: not-contacted | AK46: Jul 16 2026 (report)
A47: =RANK(AI47,$AI$2:$AI$70) -> 68 | B47: The Commodore — ambiguous, verify by phone | C47: 825 Sutter St, Lower Nob Hill, SF | D47: Nob Hill | E47: SF-priority | F47: 18 | G47: est. by neighborhood (geocode in portal) | H47: dorm | I47: 113 | J47: 1 | K47: =IF(I47="","",I47*J47) -> 113 | N47: =IF(L47="","",ROUND((L47+M47)/2/J47,0)) | O47: =IF(N47="","",N47*Weights!$B$12) | P47: unknown | Q47: sold | R47: Premium value | S47: q1-2027 | T47: unknown | W47: Sold Oct 2025 for $13M; Yelp shows CLOSED; also listed as apartments | X47: Title pull + call — possible whole-building lease | Y47: — | Z47: — | AA47: SF Assessor-Recorder deed pull (Oct 2025) or ask the M&M team above | AB47: Bargains / distressed | AC47: Yelp: https://www.yelp.com/biz/hotel-commodore-san-francisco ApartmentRatings: https://www.apartmentratings.com/ca/san-francisco/the-commodore_9199332346275178284/ | AD47: Verified: still CLOSED, buyer never publicly named — pull the Oct 2025 grant deed at the SF Assessor-Recorder to find the LLC, or ask Marcus & Millichap (they market AAU's remaining portfolio and likely know the buyer). Vacant + recently traded at ~$115k/key = strong master-lease candidate once the owner is found. | AE47: =IF(LEFT(E47,2)="SF",IF(F47="",0,Weights!$B$2*MAX(0,MIN(1,(Weights!$B$9-F47)/(Weights!$B$9-Weights!$B$8)))),0) -> 27 | AF47: =IF(N47="",5,Weights!$B$3*MAX(0,MIN(1,(Weights!$B$7-N47)/(Weights!$B$7-Weights!$B$6)))) -> 5 | AG47: =IF(P47="none",0,IF(P47="unknown",5,Weights!$B$4)) -> 5 | AH47: =IF(K47="",4,IF(AND(K47>=Weights!$B$13,K47<=Weights!$B$14),Weights!$B$5,IF(K47>100,15,IF(K47>=20,12,4)))) -> 15 | AI47: =IF(OR(Q47="taken",Q47="sold",Q47="ruled-out"),0,MIN(IF(AND(H47="tourist-hotel",P47="none"),Weights!$B$11,100),AE47+AF47+AG47+AH47)+IF(T47="yes",Weights!$B$10,0)) -> 0 | AJ47: not-contacted | AK47: Jul 16 2026 (report)
A48: =RANK(AI48,$AI$2:$AI$70) -> 21 | B48: Downtown Berkeley YMCA Hotel & Residence | C48: 2001 Allston Way, Berkeley (1 block from BART) | D48: Berkeley | E48: East Bay | F48: 55 | G48: est. by neighborhood (geocode in portal) | H48: sro-hotel | I48: 60 | J48: 1 | K48: =IF(I48="","",I48*J48) -> 60 | L48: 1200 | M48: 1400 | N48: =IF(L48="","",ROUND((L48+M48)/2/J48,0)) -> 1300 | O48: =IF(N48="","",N48*Weights!$B$12) -> 58500 | P48: communal | Q48: active | R48: Premium value | T48: yes | W48: $45–67/night rack ≈ $1,350–2,000/mo — block deal should land $1,200–1,400 | X48: Negotiate 40–60 room block with YMCA of the East Bay | AC48: Yelp: https://www.yelp.com/biz/berkeley-ymca-hotel-berkeley ymca.org: https://www.ymca.org/locations/downtown-berkeley-branch-ymca | AD48: Still-operating budget residence with soft demand and a nonprofit owner. Gym membership included; walkable Berkeley + BART to SF. Pairs naturally with the Southside rooming-house cluster for a Berkeley split-campus. | AE48: =IF(LEFT(E48,2)="SF",IF(F48="",0,Weights!$B$2*MAX(0,MIN(1,(Weights!$B$9-F48)/(Weights!$B$9-Weights!$B$8)))),0) -> 0 | AF48: =IF(N48="",5,Weights!$B$3*MAX(0,MIN(1,(Weights!$B$7-N48)/(Weights!$B$7-Weights!$B$6)))) -> 22.5 | AG48: =IF(P48="none",0,IF(P48="unknown",5,Weights!$B$4)) -> 15 | AH48: =IF(K48="",4,IF(AND(K48>=Weights!$B$13,K48<=Weights!$B$14),Weights!$B$5,IF(K48>100,15,IF(K48>=20,12,4)))) -> 20 | AI48: =IF(OR(Q48="taken",Q48="sold",Q48="ruled-out"),0,MIN(IF(AND(H48="tourist-hotel",P48="none"),Weights!$B$11,100),AE48+AF48+AG48+AH48)+IF(T48="yes",Weights!$B$10,0)) -> 62.5 | AJ48: not-contacted | AK48: Jul 16 2026 (report)
A49: =RANK(AI49,$AI$2:$AI$70) -> 58 | B49: 1515 Webster top floors — vacant ex-co-living space | C49: Julia Morgan YWCA building, Downtown Oakland | D49: Downtown Oakland | E49: East Bay | F49: 45 | G49: est. by neighborhood (geocode in portal) | H49: co-living | I49: 30 | J49: 1 | K49: =IF(I49="","",I49*J49) -> 30 | N49: =IF(L49="","",ROUND((L49+M49)/2/J49,0)) | O49: =IF(N49="","",N49*Weights!$B$12) | P49: communal | Q49: dark | R49: Direct approach | T49: no | W49: Envision Academy bought Aug 2024 ($22.5M); teacher-housing plans stated but likely unfunded | X49: Pitch Envision Academy interim revenue on the residential floors | AC49: SF YIMBY: https://sfyimby.com/2024/08/julia-morgan-designed-ywca-building-sells-for-22-5-million-downtown-oakland.html Colliers: https://www.colliers.com/en/news/san-francisco-bay-area/colliers-brokers-sale-of-the-historic-julia-morgan-ywca-building-in-oakland | AD49: A charter school owns a landmark with purpose-built co-living floors sitting empty. A master lease gives them revenue toward their own teacher-housing goal later — an easy mission-aligned pitch. | AE49: =IF(LEFT(E49,2)="SF",IF(F49="",0,Weights!$B$2*MAX(0,MIN(1,(Weights!$B$9-F49)/(Weights!$B$9-Weights!$B$8)))),0) -> 0 | AF49: =IF(N49="",5,Weights!$B$3*MAX(0,MIN(1,(Weights!$B$7-N49)/(Weights!$B$7-Weights!$B$6)))) -> 5 | AG49: =IF(P49="none",0,IF(P49="unknown",5,Weights!$B$4)) -> 15 | AH49: =IF(K49="",4,IF(AND(K49>=Weights!$B$13,K49<=Weights!$B$14),Weights!$B$5,IF(K49>100,15,IF(K49>=20,12,4)))) -> 12 | AI49: =IF(OR(Q49="taken",Q49="sold",Q49="ruled-out"),0,MIN(IF(AND(H49="tourist-hotel",P49="none"),Weights!$B$11,100),AE49+AF49+AG49+AH49)+IF(T49="yes",Weights!$B$10,0)) -> 32 | AJ49: not-contacted | AK49: Jul 16 2026 (report)
A50: =RANK(AI50,$AI$2:$AI$70) -> 38 | B50: 150 Hegenberger Rd hotel | C50: 150 Hegenberger Rd, Oakland | D50: Oakland Airport area | E50: East Bay | F50: 70 | G50: est. by neighborhood (geocode in portal) | H50: tourist-hotel | I50: 150 | J50: 1 | K50: =IF(I50="","",I50*J50) -> 150 | L50: 900 | M50: 1300 | N50: =IF(L50="","",ROUND((L50+M50)/2/J50,0)) -> 1100 | O50: =IF(N50="","",N50*Weights!$B$12) -> 49500 | P50: none | Q50: on-market | R50: On-market | T50: no | W50: $8.1M (~$50–55k/key) | X50: Diligence all three; Hegenberger = most capacity per dollar on the board | AC50: LoopNet Oakland hotels: https://www.loopnet.com/search/hotels/oakland-ca/for-sale/ LoopNet Oakland multifamily: https://www.loopnet.com/search/apartment-buildings/oakland-ca/for-sale/ LoopNet SF multifamily: https://www.loopnet.com/search/apartment-buildings/san-francisco-ca/for-sale/ | AD50: 150 Hegenberger is airport-corridor (location tradeoff) but ~$53k/key for 150+ keys is Hyatt-foreclosure economics on an open listing. 392 11th St puts 80 units downtown at $87k/unit. Princess Apartments (Hyde St) is 44 units in the Tenderloin at a real cap rate. | AE50: =IF(LEFT(E50,2)="SF",IF(F50="",0,Weights!$B$2*MAX(0,MIN(1,(Weights!$B$9-F50)/(Weights!$B$9-Weights!$B$8)))),0) -> 0 | AF50: =IF(N50="",5,Weights!$B$3*MAX(0,MIN(1,(Weights!$B$7-N50)/(Weights!$B$7-Weights!$B$6)))) -> 27.5 | AG50: =IF(P50="none",0,IF(P50="unknown",5,Weights!$B$4)) -> 0 | AH50: =IF(K50="",4,IF(AND(K50>=Weights!$B$13,K50<=Weights!$B$14),Weights!$B$5,IF(K50>100,15,IF(K50>=20,12,4)))) -> 15 | AI50: =IF(OR(Q50="taken",Q50="sold",Q50="ruled-out"),0,MIN(IF(AND(H50="tourist-hotel",P50="none"),Weights!$B$11,100),AE50+AF50+AG50+AH50)+IF(T50="yes",Weights!$B$10,0)) -> 40 | AJ50: not-contacted | AK50: Jul 16 2026 (report)
A51: =RANK(AI51,$AI$2:$AI$70) -> 58 | B51: 392 11th St, Oakland | C51: 392 11th St, Oakland | D51: Downtown Oakland | E51: East Bay | F51: 45 | G51: est. by neighborhood (geocode in portal) | H51: apartment-block | I51: 80 | J51: 1 | K51: =IF(I51="","",I51*J51) -> 80 | N51: =IF(L51="","",ROUND((L51+M51)/2/J51,0)) | O51: =IF(N51="","",N51*Weights!$B$12) | P51: private | Q51: on-market | R51: On-market | T51: no | W51: $6.95M ($87k/unit) | X51: Diligence all three; Hegenberger = most capacity per dollar on the board | AC51: LoopNet Oakland hotels: https://www.loopnet.com/search/hotels/oakland-ca/for-sale/ LoopNet Oakland multifamily: https://www.loopnet.com/search/apartment-buildings/oakland-ca/for-sale/ LoopNet SF multifamily: https://www.loopnet.com/search/apartment-buildings/san-francisco-ca/for-sale/ | AD51: 150 Hegenberger is airport-corridor (location tradeoff) but ~$53k/key for 150+ keys is Hyatt-foreclosure economics on an open listing. 392 11th St puts 80 units downtown at $87k/unit. Princess Apartments (Hyde St) is 44 units in the Tenderloin at a real cap rate. | AE51: =IF(LEFT(E51,2)="SF",IF(F51="",0,Weights!$B$2*MAX(0,MIN(1,(Weights!$B$9-F51)/(Weights!$B$9-Weights!$B$8)))),0) -> 0 | AF51: =IF(N51="",5,Weights!$B$3*MAX(0,MIN(1,(Weights!$B$7-N51)/(Weights!$B$7-Weights!$B$6)))) -> 5 | AG51: =IF(P51="none",0,IF(P51="unknown",5,Weights!$B$4)) -> 15 | AH51: =IF(K51="",4,IF(AND(K51>=Weights!$B$13,K51<=Weights!$B$14),Weights!$B$5,IF(K51>100,15,IF(K51>=20,12,4)))) -> 12 | AI51: =IF(OR(Q51="taken",Q51="sold",Q51="ruled-out"),0,MIN(IF(AND(H51="tourist-hotel",P51="none"),Weights!$B$11,100),AE51+AF51+AG51+AH51)+IF(T51="yes",Weights!$B$10,0)) -> 32 | AJ51: not-contacted | AK51: Jul 16 2026 (report)
A52: =RANK(AI52,$AI$2:$AI$70) -> 14 | B52: 149–161 Hyde St | C52: 149–161 Hyde St, SF | D52: Civic Center | E52: SF-priority | F52: 6 | G52: est. by neighborhood (geocode in portal) | H52: apartment-block | I52: 44 | J52: 1 | K52: =IF(I52="","",I52*J52) -> 44 | L52: 1800 | M52: 2400 | N52: =IF(L52="","",ROUND((L52+M52)/2/J52,0)) -> 2100 | O52: =IF(N52="","",N52*Weights!$B$12) -> 94500 | P52: private | Q52: on-market | R52: On-market | S52: q1-2027 | T52: no | W52: $7.5M (7.4% cap) | X52: Diligence all three; Hegenberger = most capacity per dollar on the board | Y52: Listing broker — see LoopNet (round-5 find) | Z52: — | AA52: LoopNet 149-161 Hyde St | AB52: Report §6e | AC52: LoopNet Oakland hotels: https://www.loopnet.com/search/hotels/oakland-ca/for-sale/ LoopNet Oakland multifamily: https://www.loopnet.com/search/apartment-buildings/oakland-ca/for-sale/ LoopNet SF multifamily: https://www.loopnet.com/search/apartment-buildings/san-francisco-ca/for-sale/ | AD52: 150 Hegenberger is airport-corridor (location tradeoff) but ~$53k/key for 150+ keys is Hyatt-foreclosure economics on an open listing. 392 11th St puts 80 units downtown at $87k/unit. Princess Apartments (Hyde St) is 44 units in the Tenderloin at a real cap rate. | AE52: =IF(LEFT(E52,2)="SF",IF(F52="",0,Weights!$B$2*MAX(0,MIN(1,(Weights!$B$9-F52)/(Weights!$B$9-Weights!$B$8)))),0) -> 35 | AF52: =IF(N52="",5,Weights!$B$3*MAX(0,MIN(1,(Weights!$B$7-N52)/(Weights!$B$7-Weights!$B$6)))) -> 2.5 | AG52: =IF(P52="none",0,IF(P52="unknown",5,Weights!$B$4)) -> 15 | AH52: =IF(K52="",4,IF(AND(K52>=Weights!$B$13,K52<=Weights!$B$14),Weights!$B$5,IF(K52>100,15,IF(K52>=20,12,4)))) -> 20 | AI52: =IF(OR(Q52="taken",Q52="sold",Q52="ruled-out"),0,MIN(IF(AND(H52="tourist-hotel",P52="none"),Weights!$B$11,100),AE52+AF52+AG52+AH52)+IF(T52="yes",Weights!$B$10,0)) -> 72.5 | AJ52: not-contacted | AK52: Jul 16 2026 (report)
A53: =RANK(AI53,$AI$2:$AI$70) -> 38 | B53: Union Square Plaza Hotel | C53: 418–432 Geary St, San Francisco | D53: Union Square | E53: SF-priority | F53: 10 | G53: est. by neighborhood (geocode in portal) | H53: tourist-hotel | I53: 69 | J53: 1 | K53: =IF(I53="","",I53*J53) -> 69 | L53: 1200 | M53: 2500 | N53: =IF(L53="","",ROUND((L53+M53)/2/J53,0)) -> 1850 | O53: =IF(N53="","",N53*Weights!$B$12) -> 83250 | P53: none | Q53: on-market | R53: On-market | S53: q1-2027 | T53: no | W53: Price on request (softness signal) | X53: Master lease + option | Y53: Ryan Clark — KW Commercial | Z53: (605) 228-6402 ⚠ | AA53: LoopNet/Crexi form | AB53: On-market listings | AC53: Crexi listing: https://www.crexi.com/properties/2373414/california-union-square-plaza-hotel LoopNet: https://www.loopnet.com/Listing/432-Geary-St-San-Francisco-CA/39664345/ | AD53: Whole cohort + staff in one operating hotel. Still renting rooms from $63/night — starved for occupancy; a guaranteed master lease is found money. | AE53: =IF(LEFT(E53,2)="SF",IF(F53="",0,Weights!$B$2*MAX(0,MIN(1,(Weights!$B$9-F53)/(Weights!$B$9-Weights!$B$8)))),0) -> 35 | AF53: =IF(N53="",5,Weights!$B$3*MAX(0,MIN(1,(Weights!$B$7-N53)/(Weights!$B$7-Weights!$B$6)))) -> 8.75 | AG53: =IF(P53="none",0,IF(P53="unknown",5,Weights!$B$4)) -> 0 | AH53: =IF(K53="",4,IF(AND(K53>=Weights!$B$13,K53<=Weights!$B$14),Weights!$B$5,IF(K53>100,15,IF(K53>=20,12,4)))) -> 12 | AI53: =IF(OR(Q53="taken",Q53="sold",Q53="ruled-out"),0,MIN(IF(AND(H53="tourist-hotel",P53="none"),Weights!$B$11,100),AE53+AF53+AG53+AH53)+IF(T53="yes",Weights!$B$10,0)) -> 40 | AJ53: not-contacted | AK53: Jul 16 2026 (report)
A54: =RANK(AI54,$AI$2:$AI$70) -> 38 | B54: Motel 6 Civic Center | C54: 583–585 Eddy St, San Francisco | D54: Civic Center | E54: SF-priority | F54: 10 | G54: est. by neighborhood (geocode in portal) | H54: tourist-hotel | I54: 68 | J54: 1 | K54: =IF(I54="","",I54*J54) -> 68 | L54: 1200 | M54: 2500 | N54: =IF(L54="","",ROUND((L54+M54)/2/J54,0)) -> 1850 | O54: =IF(N54="","",N54*Weights!$B$12) -> 83250 | P54: none | Q54: on-market | R54: On-market | S54: q1-2027 | T54: no | W54: Listed $8–9M (~$118–132k/key), 14.4% cap | X54: Lease + option pitch | Y54: Richard Ehmer + Jeramie Hamilton — Ehmer Group | Z54: (415) 225-5176 / (650) 454-5982 | AA54: rehmer@ehmergroup.com | AB54: On-market listings | AC54: LoopNet SF hotels: https://www.loopnet.com/search/hotels/san-francisco-ca/for-sale/ Showcase: https://www.showcase.com/ca/san-francisco/hotels/for-sale/ | AD54: Exact target size with 60+ headroom; a 14% cap listing = distress-signal pricing. 2–3 blocks from the Boston/Blue pair — could anchor a Tenderloin cluster at scale. | AE54: =IF(LEFT(E54,2)="SF",IF(F54="",0,Weights!$B$2*MAX(0,MIN(1,(Weights!$B$9-F54)/(Weights!$B$9-Weights!$B$8)))),0) -> 35 | AF54: =IF(N54="",5,Weights!$B$3*MAX(0,MIN(1,(Weights!$B$7-N54)/(Weights!$B$7-Weights!$B$6)))) -> 8.75 | AG54: =IF(P54="none",0,IF(P54="unknown",5,Weights!$B$4)) -> 0 | AH54: =IF(K54="",4,IF(AND(K54>=Weights!$B$13,K54<=Weights!$B$14),Weights!$B$5,IF(K54>100,15,IF(K54>=20,12,4)))) -> 12 | AI54: =IF(OR(Q54="taken",Q54="sold",Q54="ruled-out"),0,MIN(IF(AND(H54="tourist-hotel",P54="none"),Weights!$B$11,100),AE54+AF54+AG54+AH54)+IF(T54="yes",Weights!$B$10,0)) -> 40 | AJ54: not-contacted | AK54: Jul 16 2026 (report)
A55: =RANK(AI55,$AI$2:$AI$70) -> 12 | B55: 1055–1069 Pine St — 80-unit ex-dorm | C55: Nob Hill, SF (part of AAU cluster) | D55: Nob Hill | E55: SF-priority | F55: 20 | G55: est. by neighborhood (geocode in portal) | H55: dorm | I55: 80 | J55: 1 | K55: =IF(I55="","",I55*J55) -> 80 | L55: 1100 | M55: 1500 | N55: =IF(L55="","",ROUND((L55+M55)/2/J55,0)) -> 1300 | O55: =IF(N55="","",N55*Weights!$B$12) -> 58500 | P55: communal | Q55: on-market | R55: On-market | S55: q1-2027;expansion | T55: no | U55: yes | W55: $20M ask | X55: Lease / seller-finance | Y55: Marcus & Millichap: Jim Wright · J.J. Taughinbaugh · Taylor Flynn · Yuri Sergunin | Z55: (650) 391-1837 · (650) 391-1807 · (415) 963-3042 · (650) 391-1764 · SF office (415) 963-3000 | AA55: jim.wright@ / jj.taughinbaugh@ / taylor.flynn@ / yuri.sergunin@marcusmillichap.com | AB55: ⭐ Jewels — call these first | AC55: LoopNet: https://www.loopnet.com/Listing/1055-Pine-St-San-Francisco-CA/38157856/ Crexi: https://www.crexi.com/properties/2305070/california-1055-1069-pine-st | AD55: Marketed 'value-add,' historically student housing. Part of the AAU cluster play; also pairs with 1538 Polk. | AE55: =IF(LEFT(E55,2)="SF",IF(F55="",0,Weights!$B$2*MAX(0,MIN(1,(Weights!$B$9-F55)/(Weights!$B$9-Weights!$B$8)))),0) -> 25 | AF55: =IF(N55="",5,Weights!$B$3*MAX(0,MIN(1,(Weights!$B$7-N55)/(Weights!$B$7-Weights!$B$6)))) -> 22.5 | AG55: =IF(P55="none",0,IF(P55="unknown",5,Weights!$B$4)) -> 15 | AH55: =IF(K55="",4,IF(AND(K55>=Weights!$B$13,K55<=Weights!$B$14),Weights!$B$5,IF(K55>100,15,IF(K55>=20,12,4)))) -> 12 | AI55: =IF(OR(Q55="taken",Q55="sold",Q55="ruled-out"),0,MIN(IF(AND(H55="tourist-hotel",P55="none"),Weights!$B$11,100),AE55+AF55+AG55+AH55)+IF(T55="yes",Weights!$B$10,0)) -> 74.5 | AJ55: not-contacted | AK55: Jul 16 2026 (report)
A56: =RANK(AI56,$AI$2:$AI$70) -> 58 | B56: San Ramon assisted-living facility | C56: 19251 San Ramon Valley Blvd, San Ramon | D56: San Ramon | E56: East Bay | F56: 120 | G56: est. by neighborhood (geocode in portal) | H56: campus | I56: 72 | J56: 1 | K56: =IF(I56="","",I56*J56) -> 72 | N56: =IF(L56="","",ROUND((L56+M56)/2/J56,0)) | O56: =IF(N56="","",N56*Weights!$B$12) | P56: communal | Q56: on-market | R56: On-market | T56: no | W56: Listed $4.995M (~$69k/bed) — still unsold (leverage) | X56: Lease-with-option or lowball | Y56: Ken Kho — Legacy Real Estate, Fremont | Z56: (510) 396-5408 / office (510) 744-3500 | AA56: ken@kho.net | AB56: On-market listings | AC56: CityFeet listings: https://www.cityfeet.com/cont/bay-area-ca/assisted-living-facilities-for-sale | AD56: Most beds per dollar in the region; commercial kitchen + dining hall built in. Still on the market as of July 2026 — which is itself negotiating leverage. Broker: Ken Kho. | AE56: =IF(LEFT(E56,2)="SF",IF(F56="",0,Weights!$B$2*MAX(0,MIN(1,(Weights!$B$9-F56)/(Weights!$B$9-Weights!$B$8)))),0) -> 0 | AF56: =IF(N56="",5,Weights!$B$3*MAX(0,MIN(1,(Weights!$B$7-N56)/(Weights!$B$7-Weights!$B$6)))) -> 5 | AG56: =IF(P56="none",0,IF(P56="unknown",5,Weights!$B$4)) -> 15 | AH56: =IF(K56="",4,IF(AND(K56>=Weights!$B$13,K56<=Weights!$B$14),Weights!$B$5,IF(K56>100,15,IF(K56>=20,12,4)))) -> 12 | AI56: =IF(OR(Q56="taken",Q56="sold",Q56="ruled-out"),0,MIN(IF(AND(H56="tourist-hotel",P56="none"),Weights!$B$11,100),AE56+AF56+AG56+AH56)+IF(T56="yes",Weights!$B$10,0)) -> 32 | AJ56: not-contacted | AK56: Jul 16 2026 (report)
A57: =RANK(AI57,$AI$2:$AI$70) -> 64 | B57: Motel 6 Lombard St | C57: 2230 Lombard St, SF (Marina) | D57: Marina | E57: SF-other | F57: 50 | G57: est. by neighborhood (geocode in portal) | H57: tourist-hotel | I57: 29 | J57: 1 | K57: =IF(I57="","",I57*J57) -> 29 | L57: 1500 | M57: 2500 | N57: =IF(L57="","",ROUND((L57+M57)/2/J57,0)) -> 2000 | O57: =IF(N57="","",N57*Weights!$B$12) -> 90000 | P57: none | Q57: on-market | R57: On-market | T57: no | W57: Listed $6.5–7M (~$225k/key) | X57: Lease pitch (needs pairing) | Y57: Taylor Flynn — Marcus & Millichap | Z57: (415) 963-3042 | AA57: taylor.flynn@marcusmillichap.com | AB57: On-market listings | AC57: LoopNet SF motels: https://www.loopnet.com/search/listings/motels/san-francisco-ca/for-sale/ | AD57: Best neighborhood of the motel options; pair with a second building. Note: Lombard motel row shows no distress — pricing power is against you here. | AE57: =IF(LEFT(E57,2)="SF",IF(F57="",0,Weights!$B$2*MAX(0,MIN(1,(Weights!$B$9-F57)/(Weights!$B$9-Weights!$B$8)))),0) -> 0 | AF57: =IF(N57="",5,Weights!$B$3*MAX(0,MIN(1,(Weights!$B$7-N57)/(Weights!$B$7-Weights!$B$6)))) -> 5 | AG57: =IF(P57="none",0,IF(P57="unknown",5,Weights!$B$4)) -> 0 | AH57: =IF(K57="",4,IF(AND(K57>=Weights!$B$13,K57<=Weights!$B$14),Weights!$B$5,IF(K57>100,15,IF(K57>=20,12,4)))) -> 12 | AI57: =IF(OR(Q57="taken",Q57="sold",Q57="ruled-out"),0,MIN(IF(AND(H57="tourist-hotel",P57="none"),Weights!$B$11,100),AE57+AF57+AG57+AH57)+IF(T57="yes",Weights!$B$10,0)) -> 17 | AJ57: not-contacted | AK57: Jul 16 2026 (report)
A58: =RANK(AI58,$AI$2:$AI$70) -> 51 | B58: The Land Wellness & Eco-Retreat | C58: 18501 Van Zandt Resort Rd, Philo (Mendocino Co.) | D58: Philo (Mendocino) | E58: Remote | F58: 240 | G58: est. by neighborhood (geocode in portal) | H58: campus | I58: 100 | J58: 2 | K58: =IF(I58="","",I58*J58) -> 200 | N58: =IF(L58="","",ROUND((L58+M58)/2/J58,0)) | O58: =IF(N58="","",N58*Weights!$B$12) | P58: communal | Q58: on-market | R58: On-market | T58: no | W58: Listed $12M | X58: Lease pitch — remote campus only | Y58: Tim Allen — Coldwell Banker Carmel | Z58: (831) 214-1990 | AA58: tim@timallenproperties.com | AB58: On-market listings | AC58: FindTheDivine listings: https://findthedivine.com/retreats-online/listing-category/retreat-centers-sale/ | AD58: Fully solves capacity + events, but 2.5 hrs out. Closer alternative now on the board: Santa Sabina (San Rafael). | AE58: =IF(LEFT(E58,2)="SF",IF(F58="",0,Weights!$B$2*MAX(0,MIN(1,(Weights!$B$9-F58)/(Weights!$B$9-Weights!$B$8)))),0) -> 0 | AF58: =IF(N58="",5,Weights!$B$3*MAX(0,MIN(1,(Weights!$B$7-N58)/(Weights!$B$7-Weights!$B$6)))) -> 5 | AG58: =IF(P58="none",0,IF(P58="unknown",5,Weights!$B$4)) -> 15 | AH58: =IF(K58="",4,IF(AND(K58>=Weights!$B$13,K58<=Weights!$B$14),Weights!$B$5,IF(K58>100,15,IF(K58>=20,12,4)))) -> 15 | AI58: =IF(OR(Q58="taken",Q58="sold",Q58="ruled-out"),0,MIN(IF(AND(H58="tourist-hotel",P58="none"),Weights!$B$11,100),AE58+AF58+AG58+AH58)+IF(T58="yes",Weights!$B$10,0)) -> 35 | AJ58: not-contacted | AK58: Jul 16 2026 (report)
A59: =RANK(AI59,$AI$2:$AI$70) -> 24 | B59: Holy Names University dorms | C59: 3500 Mountain Blvd, Oakland hills | D59: Oakland Hills | E59: East Bay | F59: 70 | G59: est. by neighborhood (geocode in portal) | H59: dorm | I59: 200 | J59: 2 | K59: =IF(I59="","",I59*J59) -> 400 | L59: 1100 | M59: 1500 | N59: =IF(L59="","",ROUND((L59+M59)/2/J59,0)) -> 650 | O59: =IF(N59="","",N59*Weights!$B$12) -> 29250 | P59: communal | Q59: dark | R59: Direct approach | S59: expansion | T59: no | W59: Pitch: interim 2–4 yr master lease | X59: BH Properties runs an interim-leasing site | Y59: Dan Cardenas / Luis Guerra — BH Properties | Z59: 341-236-7757 / 602-899-5635 | AA59: daniel.cardenas@bhproperties.com · luis.guerra@bhproperties.com | AB59: Bargains / distressed | AC59: SF YIMBY: https://sfyimby.com/2026/02/permits-filed-for-holy-names-university-campus-redevelopment-oakland.html theoaklandcampus.com: https://theoaklandcampus.com/ BH Properties: https://www.bhproperties.com/bh-properties-purchases-60-acre-oakland-hills-campus-of-holy-names-university | AD59: Verified: BH's interim-leasing site advertises the 181,200 sf Upper Campus Complex (contains the residence halls) plus dining, gym, theatre — and one building is already 'reserved,' so interim deals are getting done. Contacts: Dan Cardenas 341-236-7757, daniel.cardenas@bhproperties.com · Luis Guerra 602-899-5635. Downside: hillside, car-dependent. | AE59: =IF(LEFT(E59,2)="SF",IF(F59="",0,Weights!$B$2*MAX(0,MIN(1,(Weights!$B$9-F59)/(Weights!$B$9-Weights!$B$8)))),0) -> 0 | AF59: =IF(N59="",5,Weights!$B$3*MAX(0,MIN(1,(Weights!$B$7-N59)/(Weights!$B$7-Weights!$B$6)))) -> 30 | AG59: =IF(P59="none",0,IF(P59="unknown",5,Weights!$B$4)) -> 15 | AH59: =IF(K59="",4,IF(AND(K59>=Weights!$B$13,K59<=Weights!$B$14),Weights!$B$5,IF(K59>100,15,IF(K59>=20,12,4)))) -> 15 | AI59: =IF(OR(Q59="taken",Q59="sold",Q59="ruled-out"),0,MIN(IF(AND(H59="tourist-hotel",P59="none"),Weights!$B$11,100),AE59+AF59+AG59+AH59)+IF(T59="yes",Weights!$B$10,0)) -> 60 | AJ59: not-contacted | AK59: Jul 16 2026 (report)
A60: =RANK(AI60,$AI$2:$AI$70) -> 16 | B60: Kenmore Residence Club | C60: 1570 Sutter St, Lower Nob Hill, SF | D60: Nob Hill | E60: SF-priority | F60: 26 | G60: est. by neighborhood (geocode in portal) | H60: sro-hotel | I60: 50 | J60: 1 | K60: =IF(I60="","",I60*J60) -> 50 | L60: 1800 | M60: 1800 | N60: =IF(L60="","",ROUND((L60+M60)/2/J60,0)) -> 1800 | O60: =IF(N60="","",N60*Weights!$B$12) -> 81000 | P60: communal | Q60: active | R60: Direct approach | S60: bridge-sept;femme-house | T60: yes | W60: ~$75/night w/ meals (~$1,800/mo) | X60: Direct approach | Y60: — | Z60: (415) 776-5815 | AA60: office@kenmorehotelsf.com | AB60: Premium value & co-living / bridge | AC60: Kenmore: http://www.kenmorehotelsf.com/ Monroe: http://www.monroeresidenceclub.com/ | AD60: Operating boarding houses — private rooms, shared baths, meals included. The meals-included master-lease target. | AE60: =IF(LEFT(E60,2)="SF",IF(F60="",0,Weights!$B$2*MAX(0,MIN(1,(Weights!$B$9-F60)/(Weights!$B$9-Weights!$B$8)))),0) -> 19 | AF60: =IF(N60="",5,Weights!$B$3*MAX(0,MIN(1,(Weights!$B$7-N60)/(Weights!$B$7-Weights!$B$6)))) -> 10 | AG60: =IF(P60="none",0,IF(P60="unknown",5,Weights!$B$4)) -> 15 | AH60: =IF(K60="",4,IF(AND(K60>=Weights!$B$13,K60<=Weights!$B$14),Weights!$B$5,IF(K60>100,15,IF(K60>=20,12,4)))) -> 20 | AI60: =IF(OR(Q60="taken",Q60="sold",Q60="ruled-out"),0,MIN(IF(AND(H60="tourist-hotel",P60="none"),Weights!$B$11,100),AE60+AF60+AG60+AH60)+IF(T60="yes",Weights!$B$10,0)) -> 69 | AJ60: not-contacted | AK60: Jul 16 2026 (report)
A61: =RANK(AI61,$AI$2:$AI$70) -> 13 | B61: Monroe Residence Club | C61: 1870 Sacramento St, Nob Hill, SF | D61: Nob Hill | E61: SF-priority | F61: 27 | G61: est. by neighborhood (geocode in portal) | H61: sro-hotel | I61: 50 | J61: 1 | K61: =IF(I61="","",I61*J61) -> 50 | L61: 1600 | M61: 1600 | N61: =IF(L61="","",ROUND((L61+M61)/2/J61,0)) -> 1600 | O61: =IF(N61="","",N61*Weights!$B$12) -> 72000 | P61: communal | Q61: active | R61: Direct approach | S61: bridge-sept;femme-house | T61: yes | W61: Verify (incl. meals) ~$1,600/mo | X61: Direct approach | Y61: — | Z61: (415) 474-6200 | AA61: reservations@monroeresidenceclub.com | AB61: Premium value & co-living / bridge | AC61: Kenmore: http://www.kenmorehotelsf.com/ Monroe: http://www.monroeresidenceclub.com/ | AD61: Operating boarding houses — private rooms, shared baths, meals included. The meals-included master-lease target. | AE61: =IF(LEFT(E61,2)="SF",IF(F61="",0,Weights!$B$2*MAX(0,MIN(1,(Weights!$B$9-F61)/(Weights!$B$9-Weights!$B$8)))),0) -> 18 | AF61: =IF(N61="",5,Weights!$B$3*MAX(0,MIN(1,(Weights!$B$7-N61)/(Weights!$B$7-Weights!$B$6)))) -> 15 | AG61: =IF(P61="none",0,IF(P61="unknown",5,Weights!$B$4)) -> 15 | AH61: =IF(K61="",4,IF(AND(K61>=Weights!$B$13,K61<=Weights!$B$14),Weights!$B$5,IF(K61>100,15,IF(K61>=20,12,4)))) -> 20 | AI61: =IF(OR(Q61="taken",Q61="sold",Q61="ruled-out"),0,MIN(IF(AND(H61="tourist-hotel",P61="none"),Weights!$B$11,100),AE61+AF61+AG61+AH61)+IF(T61="yes",Weights!$B$10,0)) -> 73 | AJ61: not-contacted | AK61: Jul 16 2026 (report)
A62: =RANK(AI62,$AI$2:$AI$70) -> 51 | B62: East Bay foreclosure hotels — new owners | C62: Hyatt House Pleasanton / Pleasant Hill / Hyatt Place Newark | D62: Pleasanton / Pleasant Hill / Newark | E62: East Bay | F62: 90 | G62: est. by neighborhood (geocode in portal) | H62: tourist-hotel | I62: 120 | J62: 1 | K62: =IF(I62="","",I62*J62) -> 120 | L62: 1500 | M62: 2500 | N62: =IF(L62="","",ROUND((L62+M62)/2/J62,0)) -> 2000 | O62: =IF(N62="","",N62*Weights!$B$12) -> 90000 | P62: private | Q62: active | R62: Direct approach | T62: unknown | W62: New owners paid $6k–27k/key | X62: Master-lease pitch to foreclosure buyers | AC62: TRD, May 2026: https://therealdeal.com/san-francisco/2026/05/08/another-east-bay-hotel-sells-after-foreclosure/ TRD, Apr 2026: https://therealdeal.com/san-francisco/2026/04/02/hyatt-house-hotels-in-east-bay-sell-at-foreclosure/ | AD62: Buyers at these bases can profitably lease 40–60 extended-stay suites well inside budget. Tri-Valley location is the tradeoff. | AE62: =IF(LEFT(E62,2)="SF",IF(F62="",0,Weights!$B$2*MAX(0,MIN(1,(Weights!$B$9-F62)/(Weights!$B$9-Weights!$B$8)))),0) -> 0 | AF62: =IF(N62="",5,Weights!$B$3*MAX(0,MIN(1,(Weights!$B$7-N62)/(Weights!$B$7-Weights!$B$6)))) -> 5 | AG62: =IF(P62="none",0,IF(P62="unknown",5,Weights!$B$4)) -> 15 | AH62: =IF(K62="",4,IF(AND(K62>=Weights!$B$13,K62<=Weights!$B$14),Weights!$B$5,IF(K62>100,15,IF(K62>=20,12,4)))) -> 15 | AI62: =IF(OR(Q62="taken",Q62="sold",Q62="ruled-out"),0,MIN(IF(AND(H62="tourist-hotel",P62="none"),Weights!$B$11,100),AE62+AF62+AG62+AH62)+IF(T62="yes",Weights!$B$10,0)) -> 35 | AJ62: not-contacted | AK62: Jul 16 2026 (report)
A63: =RANK(AI63,$AI$2:$AI$70) -> 65 | B63: Sonder leaseholds · Oakland surplus · CCA wind-down | C63: Various | D63: Various | E63: SF-other | G63: est. by neighborhood (geocode in portal) | H63: other | J63: 1 | K63: =IF(I63="","",I63*J63) | N63: =IF(L63="","",ROUND((L63+M63)/2/J63,0)) | O63: =IF(N63="","",N63*Weights!$B$12) | P63: unknown | Q63: active | R63: Direct approach | S63: q1-2027 | T63: unknown | W63: Assume a lease / negotiate | X63: Three cheap calls | AC63: Hotel Dive — Sonder: https://www.hoteldive.com/news/sonder-properties-available-leasehold-interest-after-bankruptcy/808243/ Oakland surplus: https://www.oaklandca.gov/Business/Oakland-Economic-Development/City-Property/City-Property-for-Sale-or-Lease KQED — CCA: https://www.kqed.org/arts/13985359/california-college-of-the-arts-closing-vanderbilt-university | AD63: Gordon Brothers — Sonder leasehold assumptions, furnished buildings. | Sonder's bankruptcy leaseholds are turnkey furnished. Oakland lists surplus city property. CCA (closing, Vanderbilt buying) has ~750 beds vs ~484 remaining students — a bridge-year block lease of surplus beds is a real conversation. | AE63: =IF(LEFT(E63,2)="SF",IF(F63="",0,Weights!$B$2*MAX(0,MIN(1,(Weights!$B$9-F63)/(Weights!$B$9-Weights!$B$8)))),0) -> 0 | AF63: =IF(N63="",5,Weights!$B$3*MAX(0,MIN(1,(Weights!$B$7-N63)/(Weights!$B$7-Weights!$B$6)))) -> 5 | AG63: =IF(P63="none",0,IF(P63="unknown",5,Weights!$B$4)) -> 5 | AH63: =IF(K63="",4,IF(AND(K63>=Weights!$B$13,K63<=Weights!$B$14),Weights!$B$5,IF(K63>100,15,IF(K63>=20,12,4)))) -> 4 | AI63: =IF(OR(Q63="taken",Q63="sold",Q63="ruled-out"),0,MIN(IF(AND(H63="tourist-hotel",P63="none"),Weights!$B$11,100),AE63+AF63+AG63+AH63)+IF(T63="yes",Weights!$B$10,0)) -> 14 | AJ63: not-contacted | AK63: Jul 16 2026 (report)
A64: =RANK(AI64,$AI$2:$AI$70) -> 28 | B64: 20mish | C64: Mission District, SF | D64: Mission | E64: SF-other | F64: 40 | G64: est. by neighborhood (geocode in portal) | H64: co-living | I64: 40 | J64: 1 | K64: =IF(I64="","",I64*J64) -> 40 | L64: 1625 | M64: 1625 | N64: =IF(L64="","",ROUND((L64+M64)/2/J64,0)) -> 1625 | O64: =IF(N64="","",N64*Weights!$B$12) -> 73125 | P64: communal | Q64: active | R64: Co-living / bridge | S64: bridge-sept;femme-house | T64: unknown | W64: $1,625/room all-in ≈ $65k/mo | X64: Bridge or long-term takeover | Y64: Resident manager Stephanie | Z64: — | AA64: Interest form: forms.gle/5tP3NrDf7ZgKzRtm7 · Discord via 20mish.com | AB64: Premium value & co-living / bridge | AC64: 20mish.com: https://20mish.com/ | AD64: Exactly 40 rooms in a single building, operating since 2012. 12-month minimum works if the incubator holds the master term. | AE64: =IF(LEFT(E64,2)="SF",IF(F64="",0,Weights!$B$2*MAX(0,MIN(1,(Weights!$B$9-F64)/(Weights!$B$9-Weights!$B$8)))),0) -> 5 | AF64: =IF(N64="",5,Weights!$B$3*MAX(0,MIN(1,(Weights!$B$7-N64)/(Weights!$B$7-Weights!$B$6)))) -> 14.375 | AG64: =IF(P64="none",0,IF(P64="unknown",5,Weights!$B$4)) -> 15 | AH64: =IF(K64="",4,IF(AND(K64>=Weights!$B$13,K64<=Weights!$B$14),Weights!$B$5,IF(K64>100,15,IF(K64>=20,12,4)))) -> 20 | AI64: =IF(OR(Q64="taken",Q64="sold",Q64="ruled-out"),0,MIN(IF(AND(H64="tourist-hotel",P64="none"),Weights!$B$11,100),AE64+AF64+AG64+AH64)+IF(T64="yes",Weights!$B$10,0)) -> 54.375 | AJ64: not-contacted | AK64: Jul 16 2026 (report)
A65: =RANK(AI65,$AI$2:$AI$70) -> 1 | B65: Brownstone Shared Housing | C65: 1049 Market St + 12 Mint Plaza, SF | D65: Civic Center | E65: SF-priority | F65: 3 | G65: est. by neighborhood (geocode in portal) | H65: co-living | I65: 400 | J65: 1 | K65: =IF(I65="","",I65*J65) -> 400 | L65: 700 | M65: 1200 | N65: =IF(L65="","",ROUND((L65+M65)/2/J65,0)) -> 950 | O65: =IF(N65="","",N65*Weights!$B$12) -> 42750 | P65: communal | Q65: active | R65: Co-living / bridge | S65: bridge-sept;expansion | T65: yes | W65: $700–1,200/pod ≈ $28–60k/mo | X65: Bridge — cheapest | Y65: James Stallworth | Z65: (650) 470-9278 | AA65: hey@brownstone.live | AB65: Premium value & co-living / bridge | AC65: ABC7: https://abc7news.com/post/sf-sleeping-pods-brownstone-shared-housing-san-francisco-mint-plaza-market-street/18251283/ KQED: https://www.kqed.org/news/12080289/700-a-month-sleeping-pods-make-sf-more-affordable-but-at-what-cost | AD65: Pods, not rooms. Density trade-off. | Cheapest possible block, now permitted, timing matches September. Pods, not rooms. | AE65: =IF(LEFT(E65,2)="SF",IF(F65="",0,Weights!$B$2*MAX(0,MIN(1,(Weights!$B$9-F65)/(Weights!$B$9-Weights!$B$8)))),0) -> 35 | AF65: =IF(N65="",5,Weights!$B$3*MAX(0,MIN(1,(Weights!$B$7-N65)/(Weights!$B$7-Weights!$B$6)))) -> 30 | AG65: =IF(P65="none",0,IF(P65="unknown",5,Weights!$B$4)) -> 15 | AH65: =IF(K65="",4,IF(AND(K65>=Weights!$B$13,K65<=Weights!$B$14),Weights!$B$5,IF(K65>100,15,IF(K65>=20,12,4)))) -> 15 | AI65: =IF(OR(Q65="taken",Q65="sold",Q65="ruled-out"),0,MIN(IF(AND(H65="tourist-hotel",P65="none"),Weights!$B$11,100),AE65+AF65+AG65+AH65)+IF(T65="yes",Weights!$B$10,0)) -> 100 | AJ65: not-contacted | AK65: Jul 16 2026 (report)
A66: =RANK(AI66,$AI$2:$AI$70) -> 1 | B66: Urbanests — partnership angle | C66: 1412 Market (ex-Inn at Market) + SoMa buildings | D66: SoMa | E66: SF-priority | F66: 10 | G66: est. by neighborhood (geocode in portal) | H66: co-living | I66: 440 | J66: 1 | K66: =IF(I66="","",I66*J66) -> 440 | L66: 595 | M66: 1095 | N66: =IF(L66="","",ROUND((L66+M66)/2/J66,0)) -> 845 | O66: =IF(N66="","",N66*Weights!$B$12) -> 38025 | P66: communal | Q66: active | R66: Co-living / bridge | S66: bridge-sept;q1-2027;expansion | T66: yes | W66: $595–1,095/bed; 'tech dorm' rooms $1,000 | X66: Block or partnership/sublease inquiry | Y66: Reservations/partnerships | Z66: (415) 949-0067 | AA66: reservations@urbanests.com | AB66: Premium value & co-living / bridge | AC66: TRD — co-living bounce-back: https://therealdeal.com/san-francisco/2025/04/01/co-living-biz-bounces-back-with-ai-boom-in-sf/ Urbanests: https://www.urbanests.com/post/the-new-hacker-houses-why-co-living-is-the-secret-engine-of-san-francisco-s-ai-boom | AD66: Competitor watch: UrbaNests handed back ~560 SoMa rooms — trace those landlords. | They converted the Inn at Market into an AI hacker house and have master-leased buildings before — could be a partner that runs a building FOR the program, not just a landlord. | AE66: =IF(LEFT(E66,2)="SF",IF(F66="",0,Weights!$B$2*MAX(0,MIN(1,(Weights!$B$9-F66)/(Weights!$B$9-Weights!$B$8)))),0) -> 35 | AF66: =IF(N66="",5,Weights!$B$3*MAX(0,MIN(1,(Weights!$B$7-N66)/(Weights!$B$7-Weights!$B$6)))) -> 30 | AG66: =IF(P66="none",0,IF(P66="unknown",5,Weights!$B$4)) -> 15 | AH66: =IF(K66="",4,IF(AND(K66>=Weights!$B$13,K66<=Weights!$B$14),Weights!$B$5,IF(K66>100,15,IF(K66>=20,12,4)))) -> 15 | AI66: =IF(OR(Q66="taken",Q66="sold",Q66="ruled-out"),0,MIN(IF(AND(H66="tourist-hotel",P66="none"),Weights!$B$11,100),AE66+AF66+AG66+AH66)+IF(T66="yes",Weights!$B$10,0)) -> 100 | AJ66: not-contacted | AK66: Jul 16 2026 (report)
A67: =RANK(AI67,$AI$2:$AI$70) -> 35 | B67: Foundry Coliving (4 houses) | C67: 550 Guerrero St + 3 SF houses | D67: Mission | E67: SF-other | F67: 42 | G67: est. by neighborhood (geocode in portal) | H67: co-living | I67: 47 | J67: 1 | K67: =IF(I67="","",I67*J67) -> 47 | L67: 1990 | M67: 2190 | N67: =IF(L67="","",ROUND((L67+M67)/2/J67,0)) -> 2090 | O67: =IF(N67="","",N67*Weights!$B$12) -> 94050 | P67: communal | Q67: active | R67: Co-living / bridge | S67: bridge-sept | T67: yes | W67: $1,990–2,190/room rack | X67: Portfolio takeover / block | Y67: — | Z67: (415) 610-2405 | AA67: support@foundry.today | AB67: Premium value & co-living / bridge | AC67: Foundry: https://foundry.today/ Hive: https://www.hivecolivingsf.com/rooms-privates | AD67: Foundry's whole portfolio ≈ one cohort (negotiate a discount). Hive's 4-month leases match 3-month cohorts. | AE67: =IF(LEFT(E67,2)="SF",IF(F67="",0,Weights!$B$2*MAX(0,MIN(1,(Weights!$B$9-F67)/(Weights!$B$9-Weights!$B$8)))),0) -> 3 | AF67: =IF(N67="",5,Weights!$B$3*MAX(0,MIN(1,(Weights!$B$7-N67)/(Weights!$B$7-Weights!$B$6)))) -> 2.75 | AG67: =IF(P67="none",0,IF(P67="unknown",5,Weights!$B$4)) -> 15 | AH67: =IF(K67="",4,IF(AND(K67>=Weights!$B$13,K67<=Weights!$B$14),Weights!$B$5,IF(K67>100,15,IF(K67>=20,12,4)))) -> 20 | AI67: =IF(OR(Q67="taken",Q67="sold",Q67="ruled-out"),0,MIN(IF(AND(H67="tourist-hotel",P67="none"),Weights!$B$11,100),AE67+AF67+AG67+AH67)+IF(T67="yes",Weights!$B$10,0)) -> 45.75 | AJ67: not-contacted | AK67: Jul 16 2026 (report)
A68: =RANK(AI68,$AI$2:$AI$70) -> 3 | B68: Hive Coliving (was Tribe) | C68: 1040 Folsom St, SoMa, SF | D68: SoMa | E68: SF-priority | F68: 10 | G68: est. by neighborhood (geocode in portal) | H68: co-living | I68: 40 | J68: 2 | K68: =IF(I68="","",I68*J68) -> 80 | L68: 950 | M68: 1400 | N68: =IF(L68="","",ROUND((L68+M68)/2/J68,0)) -> 588 | O68: =IF(N68="","",N68*Weights!$B$12) -> 26460 | P68: communal | Q68: active | R68: Co-living / bridge | S68: bridge-sept;q1-2027;femme-house | T68: yes | W68: Triples $475–600, privates $1,275–1,400 + $150 util | X68: Portfolio takeover / block | Y68: — | Z68: (845) 304-8555 | AA68: hivecolivingsf.com | AB68: Premium value & co-living / bridge | AC68: Foundry: https://foundry.today/ Hive: https://www.hivecolivingsf.com/rooms-privates | AD68: Foundry's whole portfolio ≈ one cohort (negotiate a discount). Hive's 4-month leases match 3-month cohorts. | AE68: =IF(LEFT(E68,2)="SF",IF(F68="",0,Weights!$B$2*MAX(0,MIN(1,(Weights!$B$9-F68)/(Weights!$B$9-Weights!$B$8)))),0) -> 35 | AF68: =IF(N68="",5,Weights!$B$3*MAX(0,MIN(1,(Weights!$B$7-N68)/(Weights!$B$7-Weights!$B$6)))) -> 30 | AG68: =IF(P68="none",0,IF(P68="unknown",5,Weights!$B$4)) -> 15 | AH68: =IF(K68="",4,IF(AND(K68>=Weights!$B$13,K68<=Weights!$B$14),Weights!$B$5,IF(K68>100,15,IF(K68>=20,12,4)))) -> 12 | AI68: =IF(OR(Q68="taken",Q68="sold",Q68="ruled-out"),0,MIN(IF(AND(H68="tourist-hotel",P68="none"),Weights!$B$11,100),AE68+AF68+AG68+AH68)+IF(T68="yes",Weights!$B$10,0)) -> 97 | AJ68: not-contacted | AK68: Jul 16 2026 (report)
A69: =RANK(AI69,$AI$2:$AI$70) -> 22 | B69: BASELINE — Fitzgerald co-living floors (current deal) | C69: 620 Post St, Nob Hill/Union Sq, SF | D69: Nob Hill | E69: SF-priority | F69: 15 | G69: est. by neighborhood (geocode in portal) | H69: co-living | I69: 20 | J69: 1 | K69: =IF(I69="","",I69*J69) -> 20 | L69: 1595 | M69: 1595 | N69: =IF(L69="","",ROUND((L69+M69)/2/J69,0)) -> 1595 | O69: =IF(N69="","",N69*Weights!$B$12) -> 71775 | P69: unknown | Q69: active | R69: Baseline | S69: q1-2027 | T69: no | V69: yes | W69: Singles from $1,595/mo | X69: Current deal — every row is compared to this | AD69: Move-in Sept 27. Common room has mini-fridge + sink; confirm full kitchen. | AE69: =IF(LEFT(E69,2)="SF",IF(F69="",0,Weights!$B$2*MAX(0,MIN(1,(Weights!$B$9-F69)/(Weights!$B$9-Weights!$B$8)))),0) -> 30 | AF69: =IF(N69="",5,Weights!$B$3*MAX(0,MIN(1,(Weights!$B$7-N69)/(Weights!$B$7-Weights!$B$6)))) -> 15.125 | AG69: =IF(P69="none",0,IF(P69="unknown",5,Weights!$B$4)) -> 5 | AH69: =IF(K69="",4,IF(AND(K69>=Weights!$B$13,K69<=Weights!$B$14),Weights!$B$5,IF(K69>100,15,IF(K69>=20,12,4)))) -> 12 | AI69: =IF(OR(Q69="taken",Q69="sold",Q69="ruled-out"),0,MIN(IF(AND(H69="tourist-hotel",P69="none"),Weights!$B$11,100),AE69+AF69+AG69+AH69)+IF(T69="yes",Weights!$B$10,0)) -> 62.125 | AJ69: not-contacted | AK69: Jul 16 2026 (report)
A70: =RANK(AI70,$AI$2:$AI$70) -> 38 | B70: BASELINE — Fitzgerald Hotel nightly side | C70: 620 Post St, SF | D70: Nob Hill | E70: SF-priority | F70: 15 | G70: est. by neighborhood (geocode in portal) | H70: tourist-hotel | I70: 50 | J70: 1 | K70: =IF(I70="","",I70*J70) -> 50 | L70: 3300 | M70: 3300 | N70: =IF(L70="","",ROUND((L70+M70)/2/J70,0)) -> 3300 | O70: =IF(N70="","",N70*Weights!$B$12) -> 148500 | P70: none | Q70: active | R70: Baseline | T70: no | V70: yes | W70: ~$110–140/night (~$3,300/mo) | X70: The hotel-swap setup we are leaving | AD70: No kitchen (mini-fridge/microwave only). 30-day room swaps = 14% TOT paid and no tenancy. | AE70: =IF(LEFT(E70,2)="SF",IF(F70="",0,Weights!$B$2*MAX(0,MIN(1,(Weights!$B$9-F70)/(Weights!$B$9-Weights!$B$8)))),0) -> 30 | AF70: =IF(N70="",5,Weights!$B$3*MAX(0,MIN(1,(Weights!$B$7-N70)/(Weights!$B$7-Weights!$B$6)))) -> 0 | AG70: =IF(P70="none",0,IF(P70="unknown",5,Weights!$B$4)) -> 0 | AH70: =IF(K70="",4,IF(AND(K70>=Weights!$B$13,K70<=Weights!$B$14),Weights!$B$5,IF(K70>100,15,IF(K70>=20,12,4)))) -> 20 | AI70: =IF(OR(Q70="taken",Q70="sold",Q70="ruled-out"),0,MIN(IF(AND(H70="tourist-hotel",P70="none"),Weights!$B$11,100),AE70+AF70+AG70+AH70)+IF(T70="yes",Weights!$B$10,0)) -> 40 | AJ70: not-contacted | AK70: Jul 16 2026 (report)

Sheet Inventory
A1: Rank | B1: Name | C1: Address / area | D1: Neighborhood | E1: Region | F1: Walk min to Frontier | G1: Walk source | H1: Type (norm.) | I1: Type (as tracked) | J1: Capacity (as tracked) | K1: Beds est | L1: Price as listed | M1: $/bed est (sort) | N1: Monthly for cohort ($) | O1: Kitchen (norm.) | P1: Kitchen (as tracked) | Q1: Status | R1: Sept-15 ready? | S1: Notion round | T1: Outreach status | U1: Contacted by | V1: Transit pts | W1: Price pts | X1: Kitchen pts | Y1: Beds pts | Z1: SCORE | AA1: Last checked
A2: =RANK(Z2,$Z$2:$Z$78) -> 15 | B2: Soma House | C2: 121 7th St, SoMa | D2: SoMa | E2: SF-priority | F2: 8 | G2: Notion tracker | H2: dorm | I2: Student housing | J2: Verify | L2: Verify | M2: 1200 | N2: =M2*Weights!$B$12 -> 54000 | O2: communal | P2: Yes | Q2: active | R2: unknown | S2: 1 | T2: contacted | U2: Alex | V2: =IF(LEFT(E2,2)="SF",IF(F2="",0,Weights!$B$2*MAX(0,MIN(1,(Weights!$B$9-F2)/(Weights!$B$9-Weights!$B$8)))),0) -> 35 | W2: =IF(M2="",5,Weights!$B$3*MAX(0,MIN(1,(Weights!$B$7-M2)/(Weights!$B$7-Weights!$B$6)))) -> 25 | X2: =IF(O2="none",0,IF(O2="unknown",5,Weights!$B$4)) -> 15 | Y2: =IF(K2="",4,IF(AND(K2>=Weights!$B$13,K2<=Weights!$B$14),Weights!$B$5,IF(K2>100,15,IF(K2>=20,12,4)))) -> 4 | Z2: =IF(OR(Q2="taken",Q2="sold",Q2="ruled-out"),0,MIN(IF(AND(H2="tourist-hotel",O2="none"),Weights!$B$11,100),V2+W2+X2+Y2)+IF(R2="yes",Weights!$B$10,0)) -> 79 | AA2: Aug 2026 (Notion)
A3: =RANK(Z3,$Z$2:$Z$78) -> 3 | B3: Panoramic Residences | C3: 1321 Mission St (9th & Mission), SoMa | D3: SoMa | E3: SF-other | F3: 10 | G3: Notion tracker | H3: co-living | I3: Co-living (micro-units) | J3: 160 units | K3: 160 | L3: shared kitchen, in micro unit | M3: 1200 | N3: =M3*Weights!$B$12 -> 54000 | O3: communal | P3: Yes | Q3: active | R3: unknown | S3: 1 | T3: contacted | U3: Alex | V3: =IF(LEFT(E3,2)="SF",IF(F3="",0,Weights!$B$2*MAX(0,MIN(1,(Weights!$B$9-F3)/(Weights!$B$9-Weights!$B$8)))),0) -> 35 | W3: =IF(M3="",5,Weights!$B$3*MAX(0,MIN(1,(Weights!$B$7-M3)/(Weights!$B$7-Weights!$B$6)))) -> 25 | X3: =IF(O3="none",0,IF(O3="unknown",5,Weights!$B$4)) -> 15 | Y3: =IF(K3="",4,IF(AND(K3>=Weights!$B$13,K3<=Weights!$B$14),Weights!$B$5,IF(K3>100,15,IF(K3>=20,12,4)))) -> 15 | Z3: =IF(OR(Q3="taken",Q3="sold",Q3="ruled-out"),0,MIN(IF(AND(H3="tourist-hotel",O3="none"),Weights!$B$11,100),V3+W3+X3+Y3)+IF(R3="yes",Weights!$B$10,0)) -> 90 | AA3: Aug 2026 (Notion)
A4: =RANK(Z4,$Z$2:$Z$78) -> 32 | B4: City Gardens Apartments | C4: 333 12th St, SoMa | D4: SoMa | E4: SF-priority | F4: 15 | G4: Notion tracker | H4: apartment-block | I4: Apartments | J4: 200 units | K4: 200 | L4: Verify (market-rate $2,000+ studio) | M4: 2000 | N4: =M4*Weights!$B$12 -> 90000 | O4: communal | P4: Yes | Q4: active | R4: unknown | S4: 1 | T4: contacted | U4: Alex | V4: =IF(LEFT(E4,2)="SF",IF(F4="",0,Weights!$B$2*MAX(0,MIN(1,(Weights!$B$9-F4)/(Weights!$B$9-Weights!$B$8)))),0) -> 30 | W4: =IF(M4="",5,Weights!$B$3*MAX(0,MIN(1,(Weights!$B$7-M4)/(Weights!$B$7-Weights!$B$6)))) -> 5 | X4: =IF(O4="none",0,IF(O4="unknown",5,Weights!$B$4)) -> 15 | Y4: =IF(K4="",4,IF(AND(K4>=Weights!$B$13,K4<=Weights!$B$14),Weights!$B$5,IF(K4>100,15,IF(K4>=20,12,4)))) -> 15 | Z4: =IF(OR(Q4="taken",Q4="sold",Q4="ruled-out"),0,MIN(IF(AND(H4="tourist-hotel",O4="none"),Weights!$B$11,100),V4+W4+X4+Y4)+IF(R4="yes",Weights!$B$10,0)) -> 65 | AA4: Aug 2026 (Notion)
A5: =RANK(Z5,$Z$2:$Z$78) -> 29 | B5: TL Residences | C5: 361 Turk St, Tenderloin | D5: Tenderloin | E5: SF-priority | F5: 10 | G5: Notion tracker | H5: apartment-block | I5: Apartments | J5: 240 units | K5: 240 | L5: Verify (market-rate $2,000+ studio) | M5: 2100 | N5: =M5*Weights!$B$12 -> 94500 | O5: communal | P5: Yes | Q5: active | R5: unknown | S5: 1 | T5: contacted | U5: Alex | V5: =IF(LEFT(E5,2)="SF",IF(F5="",0,Weights!$B$2*MAX(0,MIN(1,(Weights!$B$9-F5)/(Weights!$B$9-Weights!$B$8)))),0) -> 35 | W5: =IF(M5="",5,Weights!$B$3*MAX(0,MIN(1,(Weights!$B$7-M5)/(Weights!$B$7-Weights!$B$6)))) -> 2.5 | X5: =IF(O5="none",0,IF(O5="unknown",5,Weights!$B$4)) -> 15 | Y5: =IF(K5="",4,IF(AND(K5>=Weights!$B$13,K5<=Weights!$B$14),Weights!$B$5,IF(K5>100,15,IF(K5>=20,12,4)))) -> 15 | Z5: =IF(OR(Q5="taken",Q5="sold",Q5="ruled-out"),0,MIN(IF(AND(H5="tourist-hotel",O5="none"),Weights!$B$11,100),V5+W5+X5+Y5)+IF(R5="yes",Weights!$B$10,0)) -> 67.5 | AA5: Aug 2026 (Notion)
A6: =RANK(Z6,$Z$2:$Z$78) -> 40 | B6: Hive Coliving (was Tribe) | C6: 1040 Folsom St, SoMa | D6: SoMa | E6: SF-priority | F6: 10 | G6: Notion tracker | H6: co-living | I6: Co-living | J6: Shared + private | M6: 1500 | N6: =M6*Weights!$B$12 -> 67500 | O6: unknown | Q6: active | R6: unknown | S6: 1 | T6: contacted | U6: Alex | V6: =IF(LEFT(E6,2)="SF",IF(F6="",0,Weights!$B$2*MAX(0,MIN(1,(Weights!$B$9-F6)/(Weights!$B$9-Weights!$B$8)))),0) -> 35 | W6: =IF(M6="",5,Weights!$B$3*MAX(0,MIN(1,(Weights!$B$7-M6)/(Weights!$B$7-Weights!$B$6)))) -> 17.5 | X6: =IF(O6="none",0,IF(O6="unknown",5,Weights!$B$4)) -> 5 | Y6: =IF(K6="",4,IF(AND(K6>=Weights!$B$13,K6<=Weights!$B$14),Weights!$B$5,IF(K6>100,15,IF(K6>=20,12,4)))) -> 4 | Z6: =IF(OR(Q6="taken",Q6="sold",Q6="ruled-out"),0,MIN(IF(AND(H6="tourist-hotel",O6="none"),Weights!$B$11,100),V6+W6+X6+Y6)+IF(R6="yes",Weights!$B$10,0)) -> 61.5 | AA6: Aug 2026 (Notion)
A7: =RANK(Z7,$Z$2:$Z$78) -> 35 | B7: Found Study (Nob Hill) | C7: Nob Hill | D7: Nob Hill | E7: SF-priority | F7: 30 | G7: Notion tracker | H7: dorm | I7: Housing | J7: 50+ | M7: 1000 | N7: =M7*Weights!$B$12 -> 45000 | O7: communal | P7: Yes | Q7: active | R7: unknown | S7: 1 | T7: contacted | U7: Alex | V7: =IF(LEFT(E7,2)="SF",IF(F7="",0,Weights!$B$2*MAX(0,MIN(1,(Weights!$B$9-F7)/(Weights!$B$9-Weights!$B$8)))),0) -> 15 | W7: =IF(M7="",5,Weights!$B$3*MAX(0,MIN(1,(Weights!$B$7-M7)/(Weights!$B$7-Weights!$B$6)))) -> 30 | X7: =IF(O7="none",0,IF(O7="unknown",5,Weights!$B$4)) -> 15 | Y7: =IF(K7="",4,IF(AND(K7>=Weights!$B$13,K7<=Weights!$B$14),Weights!$B$5,IF(K7>100,15,IF(K7>=20,12,4)))) -> 4 | Z7: =IF(OR(Q7="taken",Q7="sold",Q7="ruled-out"),0,MIN(IF(AND(H7="tourist-hotel",O7="none"),Weights!$B$11,100),V7+W7+X7+Y7)+IF(R7="yes",Weights!$B$10,0)) -> 64 | AA7: Aug 2026 (Notion)
A8: =RANK(Z8,$Z$2:$Z$78) -> 1 | B8: European Hostel | C8: Civic Center | D8: Civic Center | E8: SF-priority | F8: 10 | G8: Notion tracker | H8: hostel | I8: Hostel / co-living | J8: 25 rooms (4–6p shared) | K8: 25 | L8: $545/mo per bed | M8: 545 | N8: =M8*Weights!$B$12 -> 24525 | O8: communal | P8: Yes | Q8: active | R8: yes | S8: 1 | T8: contacted | U8: Alex | V8: =IF(LEFT(E8,2)="SF",IF(F8="",0,Weights!$B$2*MAX(0,MIN(1,(Weights!$B$9-F8)/(Weights!$B$9-Weights!$B$8)))),0) -> 35 | W8: =IF(M8="",5,Weights!$B$3*MAX(0,MIN(1,(Weights!$B$7-M8)/(Weights!$B$7-Weights!$B$6)))) -> 30 | X8: =IF(O8="none",0,IF(O8="unknown",5,Weights!$B$4)) -> 15 | Y8: =IF(K8="",4,IF(AND(K8>=Weights!$B$13,K8<=Weights!$B$14),Weights!$B$5,IF(K8>100,15,IF(K8>=20,12,4)))) -> 12 | Z8: =IF(OR(Q8="taken",Q8="sold",Q8="ruled-out"),0,MIN(IF(AND(H8="tourist-hotel",O8="none"),Weights!$B$11,100),V8+W8+X8+Y8)+IF(R8="yes",Weights!$B$10,0)) -> 97 | AA8: Aug 2026 (Notion)
A9: =RANK(Z9,$Z$2:$Z$78) -> 11 | B9: FOUND Study 16 Turk St | C9: 16 Turk St, Mid-Market | D9: Mid-Market | E9: SF-priority | F9: 5 | G9: Notion tracker | H9: dorm | I9: Student co-living | J9: Multi-floor | L9: Shared from $850; private $1,650+ | M9: 850 | N9: =M9*Weights!$B$12 -> 38250 | O9: communal | P9: Yes | Q9: active | R9: unknown | S9: 1 | T9: contacted | U9: Alex | V9: =IF(LEFT(E9,2)="SF",IF(F9="",0,Weights!$B$2*MAX(0,MIN(1,(Weights!$B$9-F9)/(Weights!$B$9-Weights!$B$8)))),0) -> 35 | W9: =IF(M9="",5,Weights!$B$3*MAX(0,MIN(1,(Weights!$B$7-M9)/(Weights!$B$7-Weights!$B$6)))) -> 30 | X9: =IF(O9="none",0,IF(O9="unknown",5,Weights!$B$4)) -> 15 | Y9: =IF(K9="",4,IF(AND(K9>=Weights!$B$13,K9<=Weights!$B$14),Weights!$B$5,IF(K9>100,15,IF(K9>=20,12,4)))) -> 4 | Z9: =IF(OR(Q9="taken",Q9="sold",Q9="ruled-out"),0,MIN(IF(AND(H9="tourist-hotel",O9="none"),Weights!$B$11,100),V9+W9+X9+Y9)+IF(R9="yes",Weights!$B$10,0)) -> 84 | AA9: Aug 2026 (Notion)
A10: =RANK(Z10,$Z$2:$Z$78) -> 4 | B10: HI San Francisco Downtown | C10: 312 Mason St | D10: 312 Mason St | E10: SF-priority | F10: 10 | G10: Notion tracker | H10: hostel | I10: Hostel | J10: Large; dorms + private | L10: Dorm from $31.50/night | M10: 945 | N10: =M10*Weights!$B$12 -> 42525 | O10: communal | P10: Yes | Q10: active | R10: yes | S10: 1 | T10: contacted | U10: Alex | V10: =IF(LEFT(E10,2)="SF",IF(F10="",0,Weights!$B$2*MAX(0,MIN(1,(Weights!$B$9-F10)/(Weights!$B$9-Weights!$B$8)))),0) -> 35 | W10: =IF(M10="",5,Weights!$B$3*MAX(0,MIN(1,(Weights!$B$7-M10)/(Weights!$B$7-Weights!$B$6)))) -> 30 | X10: =IF(O10="none",0,IF(O10="unknown",5,Weights!$B$4)) -> 15 | Y10: =IF(K10="",4,IF(AND(K10>=Weights!$B$13,K10<=Weights!$B$14),Weights!$B$5,IF(K10>100,15,IF(K10>=20,12,4)))) -> 4 | Z10: =IF(OR(Q10="taken",Q10="sold",Q10="ruled-out"),0,MIN(IF(AND(H10="tourist-hotel",O10="none"),Weights!$B$11,100),V10+W10+X10+Y10)+IF(R10="yes",Weights!$B$10,0)) -> 89 | AA10: Aug 2026 (Notion)
A11: =RANK(Z11,$Z$2:$Z$78) -> 2 | B11: UpMarket Residences | C11: 221 7th St | D11: 221 7th St | E11: SF-priority | F11: 11 | G11: Notion tracker | H11: co-living | I11: Co-living | J11: 110 rooms | K11: 110 | L11: $995/mo (20% off) | M11: 995 | N11: =M11*Weights!$B$12 -> 44775 | O11: communal | P11: Yes | Q11: active | R11: unknown | S11: 1 | T11: contacted | U11: Alex | V11: =IF(LEFT(E11,2)="SF",IF(F11="",0,Weights!$B$2*MAX(0,MIN(1,(Weights!$B$9-F11)/(Weights!$B$9-Weights!$B$8)))),0) -> 34 | W11: =IF(M11="",5,Weights!$B$3*MAX(0,MIN(1,(Weights!$B$7-M11)/(Weights!$B$7-Weights!$B$6)))) -> 30 | X11: =IF(O11="none",0,IF(O11="unknown",5,Weights!$B$4)) -> 15 | Y11: =IF(K11="",4,IF(AND(K11>=Weights!$B$13,K11<=Weights!$B$14),Weights!$B$5,IF(K11>100,15,IF(K11>=20,12,4)))) -> 15 | Z11: =IF(OR(Q11="taken",Q11="sold",Q11="ruled-out"),0,MIN(IF(AND(H11="tourist-hotel",O11="none"),Weights!$B$11,100),V11+W11+X11+Y11)+IF(R11="yes",Weights!$B$10,0)) -> 94 | AA11: Aug 2026 (Notion)
A12: =RANK(Z12,$Z$2:$Z$78) -> 6 | B12: Orange Village Hostel | C12: Central SF (nr Union Sq) | D12: Central SF (nr Union Sq) | E12: SF-priority | F12: 12 | G12: Notion tracker | H12: hostel | I12: Hostel | J12: Private + 4p dorms | L12: Ask, not clear | M12: 1000 | N12: =M12*Weights!$B$12 -> 45000 | O12: communal | P12: Yes | Q12: active | R12: yes | S12: 1 | T12: contacted | U12: Alex | V12: =IF(LEFT(E12,2)="SF",IF(F12="",0,Weights!$B$2*MAX(0,MIN(1,(Weights!$B$9-F12)/(Weights!$B$9-Weights!$B$8)))),0) -> 33 | W12: =IF(M12="",5,Weights!$B$3*MAX(0,MIN(1,(Weights!$B$7-M12)/(Weights!$B$7-Weights!$B$6)))) -> 30 | X12: =IF(O12="none",0,IF(O12="unknown",5,Weights!$B$4)) -> 15 | Y12: =IF(K12="",4,IF(AND(K12>=Weights!$B$13,K12<=Weights!$B$14),Weights!$B$5,IF(K12>100,15,IF(K12>=20,12,4)))) -> 4 | Z12: =IF(OR(Q12="taken",Q12="sold",Q12="ruled-out"),0,MIN(IF(AND(H12="tourist-hotel",O12="none"),Weights!$B$11,100),V12+W12+X12+Y12)+IF(R12="yes",Weights!$B$10,0)) -> 87 | AA12: Aug 2026 (Notion)
A13: =RANK(Z13,$Z$2:$Z$78) -> 8 | B13: USA Hostels SF | C13: 411 O'Farrell St | D13: 411 O'Farrell St | E13: SF-priority | F13: 12 | G13: Notion tracker | H13: hostel | I13: Hostel | J13: Dorms + private | L13: $30–40/night | M13: 1050 | N13: =M13*Weights!$B$12 -> 47250 | O13: communal | P13: Yes | Q13: active | R13: yes | S13: 1 | T13: contacted | U13: Alex | V13: =IF(LEFT(E13,2)="SF",IF(F13="",0,Weights!$B$2*MAX(0,MIN(1,(Weights!$B$9-F13)/(Weights!$B$9-Weights!$B$8)))),0) -> 33 | W13: =IF(M13="",5,Weights!$B$3*MAX(0,MIN(1,(Weights!$B$7-M13)/(Weights!$B$7-Weights!$B$6)))) -> 28.75 | X13: =IF(O13="none",0,IF(O13="unknown",5,Weights!$B$4)) -> 15 | Y13: =IF(K13="",4,IF(AND(K13>=Weights!$B$13,K13<=Weights!$B$14),Weights!$B$5,IF(K13>100,15,IF(K13>=20,12,4)))) -> 4 | Z13: =IF(OR(Q13="taken",Q13="sold",Q13="ruled-out"),0,MIN(IF(AND(H13="tourist-hotel",O13="none"),Weights!$B$11,100),V13+W13+X13+Y13)+IF(R13="yes",Weights!$B$10,0)) -> 85.75 | AA13: Aug 2026 (Notion)
A14: =RANK(Z14,$Z$2:$Z$78) -> 10 | B14: Adelaide Hostel | C14: Isadora Duncan Ln (Taylor/Post) | D14: Isadora Duncan Ln (Taylor/Post) | E14: SF-priority | F14: 13 | G14: Notion tracker | H14: hostel | I14: Hostel | J14: Dorms + private | M14: 1050 | N14: =M14*Weights!$B$12 -> 47250 | O14: communal | P14: Yes | Q14: active | R14: yes | S14: 1 | T14: contacted | U14: Alex | V14: =IF(LEFT(E14,2)="SF",IF(F14="",0,Weights!$B$2*MAX(0,MIN(1,(Weights!$B$9-F14)/(Weights!$B$9-Weights!$B$8)))),0) -> 32 | W14: =IF(M14="",5,Weights!$B$3*MAX(0,MIN(1,(Weights!$B$7-M14)/(Weights!$B$7-Weights!$B$6)))) -> 28.75 | X14: =IF(O14="none",0,IF(O14="unknown",5,Weights!$B$4)) -> 15 | Y14: =IF(K14="",4,IF(AND(K14>=Weights!$B$13,K14<=Weights!$B$14),Weights!$B$5,IF(K14>100,15,IF(K14>=20,12,4)))) -> 4 | Z14: =IF(OR(Q14="taken",Q14="sold",Q14="ruled-out"),0,MIN(IF(AND(H14="tourist-hotel",O14="none"),Weights!$B$11,100),V14+W14+X14+Y14)+IF(R14="yes",Weights!$B$10,0)) -> 84.75 | AA14: Aug 2026 (Notion)
A15: =RANK(Z15,$Z$2:$Z$78) -> 5 | B15: 221 7th Street Residences | C15: 221 7th St, SoMa | D15: SoMa | E15: SF-priority | F15: 9 | G15: Notion tracker | H15: co-living | I15: Co-living | J15: 22 rooms | K15: 22 | L15: $1,195/mo (10% off) | M15: 1195 | N15: =M15*Weights!$B$12 -> 53775 | O15: communal | P15: Yes | Q15: active | R15: unknown | S15: 1 | T15: contacted | U15: Alex | V15: =IF(LEFT(E15,2)="SF",IF(F15="",0,Weights!$B$2*MAX(0,MIN(1,(Weights!$B$9-F15)/(Weights!$B$9-Weights!$B$8)))),0) -> 35 | W15: =IF(M15="",5,Weights!$B$3*MAX(0,MIN(1,(Weights!$B$7-M15)/(Weights!$B$7-Weights!$B$6)))) -> 25.125 | X15: =IF(O15="none",0,IF(O15="unknown",5,Weights!$B$4)) -> 15 | Y15: =IF(K15="",4,IF(AND(K15>=Weights!$B$13,K15<=Weights!$B$14),Weights!$B$5,IF(K15>100,15,IF(K15>=20,12,4)))) -> 12 | Z15: =IF(OR(Q15="taken",Q15="sold",Q15="ruled-out"),0,MIN(IF(AND(H15="tourist-hotel",O15="none"),Weights!$B$11,100),V15+W15+X15+Y15)+IF(R15="yes",Weights!$B$10,0)) -> 87.125 | AA15: Aug 2026 (Notion)
A16: =RANK(Z16,$Z$2:$Z$78) -> 9 | B16: 251 9th Street Residences | C16: 251 9th St, SoMa | D16: SoMa | E16: SF-priority | F16: 12 | G16: Notion tracker | H16: co-living | I16: Co-living | J16: 22 rooms | K16: 22 | L16: $1,195/mo (10% off) | M16: 1195 | N16: =M16*Weights!$B$12 -> 53775 | O16: communal | P16: Yes | Q16: active | R16: unknown | S16: 1 | T16: contacted | U16: Alex | V16: =IF(LEFT(E16,2)="SF",IF(F16="",0,Weights!$B$2*MAX(0,MIN(1,(Weights!$B$9-F16)/(Weights!$B$9-Weights!$B$8)))),0) -> 33 | W16: =IF(M16="",5,Weights!$B$3*MAX(0,MIN(1,(Weights!$B$7-M16)/(Weights!$B$7-Weights!$B$6)))) -> 25.125 | X16: =IF(O16="none",0,IF(O16="unknown",5,Weights!$B$4)) -> 15 | Y16: =IF(K16="",4,IF(AND(K16>=Weights!$B$13,K16<=Weights!$B$14),Weights!$B$5,IF(K16>100,15,IF(K16>=20,12,4)))) -> 12 | Z16: =IF(OR(Q16="taken",Q16="sold",Q16="ruled-out"),0,MIN(IF(AND(H16="tourist-hotel",O16="none"),Weights!$B$11,100),V16+W16+X16+Y16)+IF(R16="yes",Weights!$B$10,0)) -> 85.125 | AA16: Aug 2026 (Notion)
A17: =RANK(Z17,$Z$2:$Z$78) -> 22 | B17: Hotel Epik Residences | C17: 706 Polk St | D17: 706 Polk St | E17: SF-priority | F17: 15 | G17: Notion tracker | H17: co-living | I17: Co-living | J17: 18 rooms | K17: 18 | L17: $1,200/mo (23% off) | M17: 1200 | N17: =M17*Weights!$B$12 -> 54000 | O17: communal | P17: Yes | Q17: active | R17: unknown | S17: 1 | T17: contacted | U17: Alex | V17: =IF(LEFT(E17,2)="SF",IF(F17="",0,Weights!$B$2*MAX(0,MIN(1,(Weights!$B$9-F17)/(Weights!$B$9-Weights!$B$8)))),0) -> 30 | W17: =IF(M17="",5,Weights!$B$3*MAX(0,MIN(1,(Weights!$B$7-M17)/(Weights!$B$7-Weights!$B$6)))) -> 25 | X17: =IF(O17="none",0,IF(O17="unknown",5,Weights!$B$4)) -> 15 | Y17: =IF(K17="",4,IF(AND(K17>=Weights!$B$13,K17<=Weights!$B$14),Weights!$B$5,IF(K17>100,15,IF(K17>=20,12,4)))) -> 4 | Z17: =IF(OR(Q17="taken",Q17="sold",Q17="ruled-out"),0,MIN(IF(AND(H17="tourist-hotel",O17="none"),Weights!$B$11,100),V17+W17+X17+Y17)+IF(R17="yes",Weights!$B$10,0)) -> 74 | AA17: Aug 2026 (Notion)
A18: =RANK(Z18,$Z$2:$Z$78) -> 18 | B18: The Bartlett Residences | C18: Union Square | D18: Union Square | E18: SF-priority | F18: 10 | G18: Notion tracker | H18: co-living | I18: Co-living | J18: 10 rooms | K18: 10 | L18: $1,295/mo | M18: 1295 | N18: =M18*Weights!$B$12 -> 58275 | O18: communal | P18: Yes | Q18: active | R18: unknown | S18: 1 | T18: contacted | U18: Alex | V18: =IF(LEFT(E18,2)="SF",IF(F18="",0,Weights!$B$2*MAX(0,MIN(1,(Weights!$B$9-F18)/(Weights!$B$9-Weights!$B$8)))),0) -> 35 | W18: =IF(M18="",5,Weights!$B$3*MAX(0,MIN(1,(Weights!$B$7-M18)/(Weights!$B$7-Weights!$B$6)))) -> 22.625 | X18: =IF(O18="none",0,IF(O18="unknown",5,Weights!$B$4)) -> 15 | Y18: =IF(K18="",4,IF(AND(K18>=Weights!$B$13,K18<=Weights!$B$14),Weights!$B$5,IF(K18>100,15,IF(K18>=20,12,4)))) -> 4 | Z18: =IF(OR(Q18="taken",Q18="sold",Q18="ruled-out"),0,MIN(IF(AND(H18="tourist-hotel",O18="none"),Weights!$B$11,100),V18+W18+X18+Y18)+IF(R18="yes",Weights!$B$10,0)) -> 76.625 | AA18: Aug 2026 (Notion)
A19: =RANK(Z19,$Z$2:$Z$78) -> 18 | B19: The Herbert Residences | C19: Union Square (~161 Powell St) | D19: Union Square (~161 Powell St) | E19: SF-priority | F19: 9 | G19: Notion tracker | H19: co-living | I19: Co-living | J19: 12 rooms | K19: 12 | L19: $1,295/mo | M19: 1295 | N19: =M19*Weights!$B$12 -> 58275 | O19: communal | P19: Yes | Q19: active | R19: unknown | S19: 1 | T19: contacted | U19: Alex | V19: =IF(LEFT(E19,2)="SF",IF(F19="",0,Weights!$B$2*MAX(0,MIN(1,(Weights!$B$9-F19)/(Weights!$B$9-Weights!$B$8)))),0) -> 35 | W19: =IF(M19="",5,Weights!$B$3*MAX(0,MIN(1,(Weights!$B$7-M19)/(Weights!$B$7-Weights!$B$6)))) -> 22.625 | X19: =IF(O19="none",0,IF(O19="unknown",5,Weights!$B$4)) -> 15 | Y19: =IF(K19="",4,IF(AND(K19>=Weights!$B$13,K19<=Weights!$B$14),Weights!$B$5,IF(K19>100,15,IF(K19>=20,12,4)))) -> 4 | Z19: =IF(OR(Q19="taken",Q19="sold",Q19="ruled-out"),0,MIN(IF(AND(H19="tourist-hotel",O19="none"),Weights!$B$11,100),V19+W19+X19+Y19)+IF(R19="yes",Weights!$B$10,0)) -> 76.625 | AA19: Aug 2026 (Notion)
A20: =RANK(Z20,$Z$2:$Z$78) -> 26 | B20: 1214 Polk Street Residences | C20: 1214 Polk St, Nob Hill | D20: Nob Hill | E20: SF-priority | F20: 19 | G20: Notion tracker | H20: co-living | I20: Co-living | J20: 30 rooms | K20: 30 | L20: $1,395/mo (21% off for groups) | M20: 1395 | N20: =M20*Weights!$B$12 -> 62775 | O20: communal | P20: Yes | Q20: active | R20: unknown | S20: 1 | T20: contacted | U20: Alex | V20: =IF(LEFT(E20,2)="SF",IF(F20="",0,Weights!$B$2*MAX(0,MIN(1,(Weights!$B$9-F20)/(Weights!$B$9-Weights!$B$8)))),0) -> 26 | W20: =IF(M20="",5,Weights!$B$3*MAX(0,MIN(1,(Weights!$B$7-M20)/(Weights!$B$7-Weights!$B$6)))) -> 20.125 | X20: =IF(O20="none",0,IF(O20="unknown",5,Weights!$B$4)) -> 15 | Y20: =IF(K20="",4,IF(AND(K20>=Weights!$B$13,K20<=Weights!$B$14),Weights!$B$5,IF(K20>100,15,IF(K20>=20,12,4)))) -> 12 | Z20: =IF(OR(Q20="taken",Q20="sold",Q20="ruled-out"),0,MIN(IF(AND(H20="tourist-hotel",O20="none"),Weights!$B$11,100),V20+W20+X20+Y20)+IF(R20="yes",Weights!$B$10,0)) -> 73.125 | AA20: Aug 2026 (Notion)
A21: =RANK(Z21,$Z$2:$Z$78) -> 14 | B21: Sweden House | C21: Tenderloin | D21: Tenderloin | E21: SF-priority | F21: 11 | G21: Notion tracker | H21: co-living | I21: Co-living | J21: 35 rooms | K21: 35 | L21: $1,395/mo | M21: 1395 | N21: =M21*Weights!$B$12 -> 62775 | O21: communal | P21: Yes | Q21: active | R21: unknown | S21: 1 | T21: contacted | U21: Alex | V21: =IF(LEFT(E21,2)="SF",IF(F21="",0,Weights!$B$2*MAX(0,MIN(1,(Weights!$B$9-F21)/(Weights!$B$9-Weights!$B$8)))),0) -> 34 | W21: =IF(M21="",5,Weights!$B$3*MAX(0,MIN(1,(Weights!$B$7-M21)/(Weights!$B$7-Weights!$B$6)))) -> 20.125 | X21: =IF(O21="none",0,IF(O21="unknown",5,Weights!$B$4)) -> 15 | Y21: =IF(K21="",4,IF(AND(K21>=Weights!$B$13,K21<=Weights!$B$14),Weights!$B$5,IF(K21>100,15,IF(K21>=20,12,4)))) -> 12 | Z21: =IF(OR(Q21="taken",Q21="sold",Q21="ruled-out"),0,MIN(IF(AND(H21="tourist-hotel",O21="none"),Weights!$B$11,100),V21+W21+X21+Y21)+IF(R21="yes",Weights!$B$10,0)) -> 81.125 | AA21: Aug 2026 (Notion)
A22: =RANK(Z22,$Z$2:$Z$78) -> 39 | B22: 620 Post St Residences (Fitzgerald co-living) — CURRENT | C22: 620 Post St, Nob Hill/Union Sq | D22: Nob Hill/Union Sq | E22: SF-priority | F22: 15 | G22: Notion tracker | H22: co-living | I22: Co-living | J22: ~20 bedrooms | K22: 20 | L22: Singles from $1,595/mo | M22: 1595 | N22: =M22*Weights!$B$12 -> 71775 | O22: unknown | P22: Common room has mini-fridge+sink (confirm full kitchen) | Q22: active | R22: no | S22: 1 | T22: contacted | U22: Alex | V22: =IF(LEFT(E22,2)="SF",IF(F22="",0,Weights!$B$2*MAX(0,MIN(1,(Weights!$B$9-F22)/(Weights!$B$9-Weights!$B$8)))),0) -> 30 | W22: =IF(M22="",5,Weights!$B$3*MAX(0,MIN(1,(Weights!$B$7-M22)/(Weights!$B$7-Weights!$B$6)))) -> 15.125 | X22: =IF(O22="none",0,IF(O22="unknown",5,Weights!$B$4)) -> 5 | Y22: =IF(K22="",4,IF(AND(K22>=Weights!$B$13,K22<=Weights!$B$14),Weights!$B$5,IF(K22>100,15,IF(K22>=20,12,4)))) -> 12 | Z22: =IF(OR(Q22="taken",Q22="sold",Q22="ruled-out"),0,MIN(IF(AND(H22="tourist-hotel",O22="none"),Weights!$B$11,100),V22+W22+X22+Y22)+IF(R22="yes",Weights!$B$10,0)) -> 62.125 | AA22: Aug 2026 (Notion)
A23: =RANK(Z23,$Z$2:$Z$78) -> 49 | B23: Hive Coliving (bunks) | C23: SF (verify block) | D23: SF (verify block) | E23: SF-other | G23: Notion tracker | H23: co-living | I23: Co-living | J23: Bunks | L23: Bunk from ~$900 | M23: 900 | N23: =M23*Weights!$B$12 -> 40500 | O23: communal | P23: Yes | Q23: active | R23: unknown | S23: 1 | T23: contacted | U23: Alex | V23: =IF(LEFT(E23,2)="SF",IF(F23="",0,Weights!$B$2*MAX(0,MIN(1,(Weights!$B$9-F23)/(Weights!$B$9-Weights!$B$8)))),0) -> 0 | W23: =IF(M23="",5,Weights!$B$3*MAX(0,MIN(1,(Weights!$B$7-M23)/(Weights!$B$7-Weights!$B$6)))) -> 30 | X23: =IF(O23="none",0,IF(O23="unknown",5,Weights!$B$4)) -> 15 | Y23: =IF(K23="",4,IF(AND(K23>=Weights!$B$13,K23<=Weights!$B$14),Weights!$B$5,IF(K23>100,15,IF(K23>=20,12,4)))) -> 4 | Z23: =IF(OR(Q23="taken",Q23="sold",Q23="ruled-out"),0,MIN(IF(AND(H23="tourist-hotel",O23="none"),Weights!$B$11,100),V23+W23+X23+Y23)+IF(R23="yes",Weights!$B$10,0)) -> 49 | AA23: Aug 2026 (Notion)
A24: =RANK(Z24,$Z$2:$Z$78) -> 22 | B24: Green Tortoise Hostel | C24: 494 Broadway, North Beach | D24: North Beach | E24: SF-other | F24: 25 | G24: Notion tracker | H24: hostel | I24: Hostel | J24: Dorms + private | L24: Budget | M24: 1000 | N24: =M24*Weights!$B$12 -> 45000 | O24: communal | P24: Yes | Q24: active | R24: yes | S24: 1 | T24: contacted | U24: Alex | V24: =IF(LEFT(E24,2)="SF",IF(F24="",0,Weights!$B$2*MAX(0,MIN(1,(Weights!$B$9-F24)/(Weights!$B$9-Weights!$B$8)))),0) -> 20 | W24: =IF(M24="",5,Weights!$B$3*MAX(0,MIN(1,(Weights!$B$7-M24)/(Weights!$B$7-Weights!$B$6)))) -> 30 | X24: =IF(O24="none",0,IF(O24="unknown",5,Weights!$B$4)) -> 15 | Y24: =IF(K24="",4,IF(AND(K24>=Weights!$B$13,K24<=Weights!$B$14),Weights!$B$5,IF(K24>100,15,IF(K24>=20,12,4)))) -> 4 | Z24: =IF(OR(Q24="taken",Q24="sold",Q24="ruled-out"),0,MIN(IF(AND(H24="tourist-hotel",O24="none"),Weights!$B$11,100),V24+W24+X24+Y24)+IF(R24="yes",Weights!$B$10,0)) -> 74 | AA24: Aug 2026 (Notion)
A25: =RANK(Z25,$Z$2:$Z$78) -> 30 | B25: 371 Columbus Residences | C25: North Beach | D25: North Beach | E25: SF-other | F25: 30 | G25: Notion tracker | H25: co-living | I25: Co-living | J25: 34 rooms | K25: 34 | L25: $1,195/mo (10% off) | M25: 1195 | N25: =M25*Weights!$B$12 -> 53775 | O25: communal | P25: Yes | Q25: active | R25: unknown | S25: 1 | T25: contacted | U25: Alex | V25: =IF(LEFT(E25,2)="SF",IF(F25="",0,Weights!$B$2*MAX(0,MIN(1,(Weights!$B$9-F25)/(Weights!$B$9-Weights!$B$8)))),0) -> 15 | W25: =IF(M25="",5,Weights!$B$3*MAX(0,MIN(1,(Weights!$B$7-M25)/(Weights!$B$7-Weights!$B$6)))) -> 25.125 | X25: =IF(O25="none",0,IF(O25="unknown",5,Weights!$B$4)) -> 15 | Y25: =IF(K25="",4,IF(AND(K25>=Weights!$B$13,K25<=Weights!$B$14),Weights!$B$5,IF(K25>100,15,IF(K25>=20,12,4)))) -> 12 | Z25: =IF(OR(Q25="taken",Q25="sold",Q25="ruled-out"),0,MIN(IF(AND(H25="tourist-hotel",O25="none"),Weights!$B$11,100),V25+W25+X25+Y25)+IF(R25="yes",Weights!$B$10,0)) -> 67.125 | AA25: Aug 2026 (Notion)
A26: =RANK(Z26,$Z$2:$Z$78) -> 21 | B26: 524 Columbus Residences | C26: North Beach | D26: North Beach | E26: SF-other | F26: 30 | G26: Notion tracker | H26: co-living | I26: Co-living | J26: 45 rooms | K26: 45 | L26: $1,195/mo (10% off) | M26: 1195 | N26: =M26*Weights!$B$12 -> 53775 | O26: communal | P26: Yes | Q26: active | R26: unknown | S26: 1 | T26: contacted | U26: Alex | V26: =IF(LEFT(E26,2)="SF",IF(F26="",0,Weights!$B$2*MAX(0,MIN(1,(Weights!$B$9-F26)/(Weights!$B$9-Weights!$B$8)))),0) -> 15 | W26: =IF(M26="",5,Weights!$B$3*MAX(0,MIN(1,(Weights!$B$7-M26)/(Weights!$B$7-Weights!$B$6)))) -> 25.125 | X26: =IF(O26="none",0,IF(O26="unknown",5,Weights!$B$4)) -> 15 | Y26: =IF(K26="",4,IF(AND(K26>=Weights!$B$13,K26<=Weights!$B$14),Weights!$B$5,IF(K26>100,15,IF(K26>=20,12,4)))) -> 20 | Z26: =IF(OR(Q26="taken",Q26="sold",Q26="ruled-out"),0,MIN(IF(AND(H26="tourist-hotel",O26="none"),Weights!$B$11,100),V26+W26+X26+Y26)+IF(R26="yes",Weights!$B$10,0)) -> 75.125 | AA26: Aug 2026 (Notion)
A27: =RANK(Z27,$Z$2:$Z$78) -> 31 | B27: 556 Green St Residences | C27: North Beach | D27: North Beach | E27: SF-other | F27: 29 | G27: Notion tracker | H27: co-living | I27: Co-living | J27: 22 rooms | K27: 22 | L27: $1,300/mo (13% off) | M27: 1300 | N27: =M27*Weights!$B$12 -> 58500 | O27: communal | P27: Yes | Q27: active | R27: unknown | S27: 1 | T27: contacted | U27: Alex | V27: =IF(LEFT(E27,2)="SF",IF(F27="",0,Weights!$B$2*MAX(0,MIN(1,(Weights!$B$9-F27)/(Weights!$B$9-Weights!$B$8)))),0) -> 16 | W27: =IF(M27="",5,Weights!$B$3*MAX(0,MIN(1,(Weights!$B$7-M27)/(Weights!$B$7-Weights!$B$6)))) -> 22.5 | X27: =IF(O27="none",0,IF(O27="unknown",5,Weights!$B$4)) -> 15 | Y27: =IF(K27="",4,IF(AND(K27>=Weights!$B$13,K27<=Weights!$B$14),Weights!$B$5,IF(K27>100,15,IF(K27>=20,12,4)))) -> 12 | Z27: =IF(OR(Q27="taken",Q27="sold",Q27="ruled-out"),0,MIN(IF(AND(H27="tourist-hotel",O27="none"),Weights!$B$11,100),V27+W27+X27+Y27)+IF(R27="yes",Weights!$B$10,0)) -> 65.5 | AA27: Aug 2026 (Notion)
A28: =RANK(Z28,$Z$2:$Z$78) -> 6 | B28: Amsterdam Hostel | C28: 749 Taylor St (Union Sq) | D28: 749 Taylor St (Union Sq) | E28: SF-priority | F28: 12 | G28: Notion tracker | H28: hostel | I28: Hostel | J28: Dorms + private | L28: From ~$19/night | M28: 570 | N28: =M28*Weights!$B$12 -> 25650 | O28: communal | P28: Yes | Q28: active | R28: yes | S28: 1 | T28: contacted | U28: Alex | V28: =IF(LEFT(E28,2)="SF",IF(F28="",0,Weights!$B$2*MAX(0,MIN(1,(Weights!$B$9-F28)/(Weights!$B$9-Weights!$B$8)))),0) -> 33 | W28: =IF(M28="",5,Weights!$B$3*MAX(0,MIN(1,(Weights!$B$7-M28)/(Weights!$B$7-Weights!$B$6)))) -> 30 | X28: =IF(O28="none",0,IF(O28="unknown",5,Weights!$B$4)) -> 15 | Y28: =IF(K28="",4,IF(AND(K28>=Weights!$B$13,K28<=Weights!$B$14),Weights!$B$5,IF(K28>100,15,IF(K28>=20,12,4)))) -> 4 | Z28: =IF(OR(Q28="taken",Q28="sold",Q28="ruled-out"),0,MIN(IF(AND(H28="tourist-hotel",O28="none"),Weights!$B$11,100),V28+W28+X28+Y28)+IF(R28="yes",Weights!$B$10,0)) -> 87 | AA28: Aug 2026 (Notion)
A29: =RANK(Z29,$Z$2:$Z$78) -> 22 | B29: Samesun San Francisco | C29: North Beach (verify) | D29: North Beach (verify) | E29: SF-other | F29: 25 | G29: Notion tracker | H29: hostel | I29: Hostel | J29: Dorms + private | L29: From $32/night | M29: 960 | N29: =M29*Weights!$B$12 -> 43200 | O29: communal | P29: Yes | Q29: active | R29: yes | S29: 1 | T29: contacted | U29: Alex | V29: =IF(LEFT(E29,2)="SF",IF(F29="",0,Weights!$B$2*MAX(0,MIN(1,(Weights!$B$9-F29)/(Weights!$B$9-Weights!$B$8)))),0) -> 20 | W29: =IF(M29="",5,Weights!$B$3*MAX(0,MIN(1,(Weights!$B$7-M29)/(Weights!$B$7-Weights!$B$6)))) -> 30 | X29: =IF(O29="none",0,IF(O29="unknown",5,Weights!$B$4)) -> 15 | Y29: =IF(K29="",4,IF(AND(K29>=Weights!$B$13,K29<=Weights!$B$14),Weights!$B$5,IF(K29>100,15,IF(K29>=20,12,4)))) -> 4 | Z29: =IF(OR(Q29="taken",Q29="sold",Q29="ruled-out"),0,MIN(IF(AND(H29="tourist-hotel",O29="none"),Weights!$B$11,100),V29+W29+X29+Y29)+IF(R29="yes",Weights!$B$10,0)) -> 74 | AA29: Aug 2026 (Notion)
A30: =RANK(Z30,$Z$2:$Z$78) -> 17 | B30: Bposhtels SF Union Square | C30: Union Square area (verify) | D30: Union Square area (verify) | E30: SF-priority | F30: 11 | G30: Notion tracker | H30: hostel | I30: Hostel | J30: Dorms + private | L30: From $33/night | M30: 990 | N30: =M30*Weights!$B$12 -> 44550 | O30: unknown | P30: Yes (verify) | Q30: active | R30: yes | S30: 1 | T30: contacted | U30: Alex | V30: =IF(LEFT(E30,2)="SF",IF(F30="",0,Weights!$B$2*MAX(0,MIN(1,(Weights!$B$9-F30)/(Weights!$B$9-Weights!$B$8)))),0) -> 34 | W30: =IF(M30="",5,Weights!$B$3*MAX(0,MIN(1,(Weights!$B$7-M30)/(Weights!$B$7-Weights!$B$6)))) -> 30 | X30: =IF(O30="none",0,IF(O30="unknown",5,Weights!$B$4)) -> 5 | Y30: =IF(K30="",4,IF(AND(K30>=Weights!$B$13,K30<=Weights!$B$14),Weights!$B$5,IF(K30>100,15,IF(K30>=20,12,4)))) -> 4 | Z30: =IF(OR(Q30="taken",Q30="sold",Q30="ruled-out"),0,MIN(IF(AND(H30="tourist-hotel",O30="none"),Weights!$B$11,100),V30+W30+X30+Y30)+IF(R30="yes",Weights!$B$10,0)) -> 78 | AA30: Aug 2026 (Notion)
A31: =RANK(Z31,$Z$2:$Z$78) -> 13 | B31: ITH Pacific Tradewinds | C31: 680 Sacramento St (Chinatown/FiDi) | D31: 680 Sacramento St (Chinatown/FiDi) | E31: SF-priority | F31: 13 | G31: Notion tracker | H31: hostel | I31: Hostel | J31: 8-bed dorms | L31: From $39/night | M31: 1170 | N31: =M31*Weights!$B$12 -> 52650 | O31: communal | P31: Yes | Q31: active | R31: yes | S31: 1 | T31: contacted | U31: Alex | V31: =IF(LEFT(E31,2)="SF",IF(F31="",0,Weights!$B$2*MAX(0,MIN(1,(Weights!$B$9-F31)/(Weights!$B$9-Weights!$B$8)))),0) -> 32 | W31: =IF(M31="",5,Weights!$B$3*MAX(0,MIN(1,(Weights!$B$7-M31)/(Weights!$B$7-Weights!$B$6)))) -> 25.75 | X31: =IF(O31="none",0,IF(O31="unknown",5,Weights!$B$4)) -> 15 | Y31: =IF(K31="",4,IF(AND(K31>=Weights!$B$13,K31<=Weights!$B$14),Weights!$B$5,IF(K31>100,15,IF(K31>=20,12,4)))) -> 4 | Z31: =IF(OR(Q31="taken",Q31="sold",Q31="ruled-out"),0,MIN(IF(AND(H31="tourist-hotel",O31="none"),Weights!$B$11,100),V31+W31+X31+Y31)+IF(R31="yes",Weights!$B$10,0)) -> 81.75 | AA31: Aug 2026 (Notion)
A32: =RANK(Z32,$Z$2:$Z$78) -> 70 | B32: 908 Coliving | C32: SF (verify) | D32: SF (verify) | E32: SF-other | G32: Notion tracker | H32: co-living | I32: Co-living | J32: Rooms | L32: $1,700+ | M32: 1700 | N32: =M32*Weights!$B$12 -> 76500 | O32: communal | P32: Yes | Q32: active | R32: unknown | S32: 1 | T32: contacted | U32: Alex | V32: =IF(LEFT(E32,2)="SF",IF(F32="",0,Weights!$B$2*MAX(0,MIN(1,(Weights!$B$9-F32)/(Weights!$B$9-Weights!$B$8)))),0) -> 0 | W32: =IF(M32="",5,Weights!$B$3*MAX(0,MIN(1,(Weights!$B$7-M32)/(Weights!$B$7-Weights!$B$6)))) -> 12.5 | X32: =IF(O32="none",0,IF(O32="unknown",5,Weights!$B$4)) -> 15 | Y32: =IF(K32="",4,IF(AND(K32>=Weights!$B$13,K32<=Weights!$B$14),Weights!$B$5,IF(K32>100,15,IF(K32>=20,12,4)))) -> 4 | Z32: =IF(OR(Q32="taken",Q32="sold",Q32="ruled-out"),0,MIN(IF(AND(H32="tourist-hotel",O32="none"),Weights!$B$11,100),V32+W32+X32+Y32)+IF(R32="yes",Weights!$B$10,0)) -> 31.5 | AA32: Aug 2026 (Notion)
A33: =RANK(Z33,$Z$2:$Z$78) -> 42 | B33: HI Fisherman's Wharf Hostel | C33: Fort Mason | D33: Fort Mason | E33: SF-other | F33: 40 | G33: Notion tracker | H33: hostel | I33: Hostel | J33: Dorms + private | L33: Budget | M33: 1000 | N33: =M33*Weights!$B$12 -> 45000 | O33: communal | P33: Yes | Q33: active | R33: yes | S33: 1 | T33: contacted | U33: Alex | V33: =IF(LEFT(E33,2)="SF",IF(F33="",0,Weights!$B$2*MAX(0,MIN(1,(Weights!$B$9-F33)/(Weights!$B$9-Weights!$B$8)))),0) -> 5 | W33: =IF(M33="",5,Weights!$B$3*MAX(0,MIN(1,(Weights!$B$7-M33)/(Weights!$B$7-Weights!$B$6)))) -> 30 | X33: =IF(O33="none",0,IF(O33="unknown",5,Weights!$B$4)) -> 15 | Y33: =IF(K33="",4,IF(AND(K33>=Weights!$B$13,K33<=Weights!$B$14),Weights!$B$5,IF(K33>100,15,IF(K33>=20,12,4)))) -> 4 | Z33: =IF(OR(Q33="taken",Q33="sold",Q33="ruled-out"),0,MIN(IF(AND(H33="tourist-hotel",O33="none"),Weights!$B$11,100),V33+W33+X33+Y33)+IF(R33="yes",Weights!$B$10,0)) -> 59 | AA33: Aug 2026 (Notion)
A34: =RANK(Z34,$Z$2:$Z$78) -> 37 | B34: 2436 Mission Residences | C34: 2436 Mission St | D34: 2436 Mission St | E34: SF-other | F34: 26 | G34: Notion tracker | H34: co-living | I34: Co-living | J34: 8 rooms | K34: 8 | L34: $1,195/mo | M34: 1195 | N34: =M34*Weights!$B$12 -> 53775 | O34: communal | P34: Yes | Q34: active | R34: unknown | S34: 1 | T34: contacted | U34: Alex | V34: =IF(LEFT(E34,2)="SF",IF(F34="",0,Weights!$B$2*MAX(0,MIN(1,(Weights!$B$9-F34)/(Weights!$B$9-Weights!$B$8)))),0) -> 19 | W34: =IF(M34="",5,Weights!$B$3*MAX(0,MIN(1,(Weights!$B$7-M34)/(Weights!$B$7-Weights!$B$6)))) -> 25.125 | X34: =IF(O34="none",0,IF(O34="unknown",5,Weights!$B$4)) -> 15 | Y34: =IF(K34="",4,IF(AND(K34>=Weights!$B$13,K34<=Weights!$B$14),Weights!$B$5,IF(K34>100,15,IF(K34>=20,12,4)))) -> 4 | Z34: =IF(OR(Q34="taken",Q34="sold",Q34="ruled-out"),0,MIN(IF(AND(H34="tourist-hotel",O34="none"),Weights!$B$11,100),V34+W34+X34+Y34)+IF(R34="yes",Weights!$B$10,0)) -> 63.125 | AA34: Aug 2026 (Notion)
A35: =RANK(Z35,$Z$2:$Z$78) -> 59 | B35: The Perramont | C35: Castro | D35: Castro | E35: SF-other | F35: 40 | G35: Notion tracker | H35: co-living | I35: Co-living | J35: 10 rooms | K35: 10 | L35: $1,395/mo | M35: 1395 | N35: =M35*Weights!$B$12 -> 62775 | O35: communal | P35: Yes | Q35: active | R35: unknown | S35: 1 | T35: contacted | U35: Alex | V35: =IF(LEFT(E35,2)="SF",IF(F35="",0,Weights!$B$2*MAX(0,MIN(1,(Weights!$B$9-F35)/(Weights!$B$9-Weights!$B$8)))),0) -> 5 | W35: =IF(M35="",5,Weights!$B$3*MAX(0,MIN(1,(Weights!$B$7-M35)/(Weights!$B$7-Weights!$B$6)))) -> 20.125 | X35: =IF(O35="none",0,IF(O35="unknown",5,Weights!$B$4)) -> 15 | Y35: =IF(K35="",4,IF(AND(K35>=Weights!$B$13,K35<=Weights!$B$14),Weights!$B$5,IF(K35>100,15,IF(K35>=20,12,4)))) -> 4 | Z35: =IF(OR(Q35="taken",Q35="sold",Q35="ruled-out"),0,MIN(IF(AND(H35="tourist-hotel",O35="none"),Weights!$B$11,100),V35+W35+X35+Y35)+IF(R35="yes",Weights!$B$10,0)) -> 44.125 | AA35: Aug 2026 (Notion)
A36: =RANK(Z36,$Z$2:$Z$78) -> 38 | B36: Lovely North Beach / Chinatown Hotel | C36: North Beach | D36: North Beach | E36: SF-other | F36: 29 | G36: Notion tracker | H36: tourist-hotel | I36: Co-living / hotel | J36: 20 rooms | K36: 20 | L36: $1,600/mo | M36: 1600 | N36: =M36*Weights!$B$12 -> 72000 | O36: communal | P36: Yes | Q36: active | R36: yes | S36: 1 | T36: contacted | U36: Alex | V36: =IF(LEFT(E36,2)="SF",IF(F36="",0,Weights!$B$2*MAX(0,MIN(1,(Weights!$B$9-F36)/(Weights!$B$9-Weights!$B$8)))),0) -> 16 | W36: =IF(M36="",5,Weights!$B$3*MAX(0,MIN(1,(Weights!$B$7-M36)/(Weights!$B$7-Weights!$B$6)))) -> 15 | X36: =IF(O36="none",0,IF(O36="unknown",5,Weights!$B$4)) -> 15 | Y36: =IF(K36="",4,IF(AND(K36>=Weights!$B$13,K36<=Weights!$B$14),Weights!$B$5,IF(K36>100,15,IF(K36>=20,12,4)))) -> 12 | Z36: =IF(OR(Q36="taken",Q36="sold",Q36="ruled-out"),0,MIN(IF(AND(H36="tourist-hotel",O36="none"),Weights!$B$11,100),V36+W36+X36+Y36)+IF(R36="yes",Weights!$B$10,0)) -> 63 | AA36: Aug 2026 (Notion)
A37: =RANK(Z37,$Z$2:$Z$78) -> 63 | B37: Standard Union Square hotels (Adante, Powell, Union Sq Plaza, Ram's, etc.) | C37: Union Sq / SoMa | D37: Union Sq / SoMa | E37: SF-priority | F37: 12 | G37: Notion tracker | H37: tourist-hotel | I37: Hotel | J37: Varies | L37: Nightly (high long-term) | M37: 3000 | N37: =M37*Weights!$B$12 -> 135000 | O37: none | P37: Mostly none | Q37: active | R37: yes | S37: 1 | T37: contacted | U37: Alex | V37: =IF(LEFT(E37,2)="SF",IF(F37="",0,Weights!$B$2*MAX(0,MIN(1,(Weights!$B$9-F37)/(Weights!$B$9-Weights!$B$8)))),0) -> 33 | W37: =IF(M37="",5,Weights!$B$3*MAX(0,MIN(1,(Weights!$B$7-M37)/(Weights!$B$7-Weights!$B$6)))) -> 0 | X37: =IF(O37="none",0,IF(O37="unknown",5,Weights!$B$4)) -> 0 | Y37: =IF(K37="",4,IF(AND(K37>=Weights!$B$13,K37<=Weights!$B$14),Weights!$B$5,IF(K37>100,15,IF(K37>=20,12,4)))) -> 4 | Z37: =IF(OR(Q37="taken",Q37="sold",Q37="ruled-out"),0,MIN(IF(AND(H37="tourist-hotel",O37="none"),Weights!$B$11,100),V37+W37+X37+Y37)+IF(R37="yes",Weights!$B$10,0)) -> 42 | AA37: Aug 2026 (Notion)
A38: =RANK(Z38,$Z$2:$Z$78) -> 65 | B38: Fitzgerald Hotel (nightly hotel side) — CURRENT | C38: 620 Post St | D38: 620 Post St | E38: SF-priority | F38: 15 | G38: Notion tracker | H38: tourist-hotel | I38: Hotel | J38: 50 rooms | K38: 50 | L38: ~$110–140/night | M38: 3300 | N38: =M38*Weights!$B$12 -> 148500 | O38: none | P38: No (mini-fridge/microwave only) | Q38: active | R38: no | S38: 1 | T38: contacted | U38: Alex | V38: =IF(LEFT(E38,2)="SF",IF(F38="",0,Weights!$B$2*MAX(0,MIN(1,(Weights!$B$9-F38)/(Weights!$B$9-Weights!$B$8)))),0) -> 30 | W38: =IF(M38="",5,Weights!$B$3*MAX(0,MIN(1,(Weights!$B$7-M38)/(Weights!$B$7-Weights!$B$6)))) -> 0 | X38: =IF(O38="none",0,IF(O38="unknown",5,Weights!$B$4)) -> 0 | Y38: =IF(K38="",4,IF(AND(K38>=Weights!$B$13,K38<=Weights!$B$14),Weights!$B$5,IF(K38>100,15,IF(K38>=20,12,4)))) -> 20 | Z38: =IF(OR(Q38="taken",Q38="sold",Q38="ruled-out"),0,MIN(IF(AND(H38="tourist-hotel",O38="none"),Weights!$B$11,100),V38+W38+X38+Y38)+IF(R38="yes",Weights!$B$10,0)) -> 40 | AA38: Aug 2026 (Notion)
A39: =RANK(Z39,$Z$2:$Z$78) -> 41 | B39: The Mission Hotel Apartments | C39: 520 S Van Ness Ave, Mission | D39: Mission | E39: SF-other | F39: 34 | G39: Notion tracker | H39: sro-hotel | I39: SRO | J39: Large (largest SRO) | L39: Low | M39: 900 | N39: =M39*Weights!$B$12 -> 40500 | O39: communal | P39: Shared | Q39: active | R39: unknown | S39: 2 | T39: not-contacted | V39: =IF(LEFT(E39,2)="SF",IF(F39="",0,Weights!$B$2*MAX(0,MIN(1,(Weights!$B$9-F39)/(Weights!$B$9-Weights!$B$8)))),0) -> 11 | W39: =IF(M39="",5,Weights!$B$3*MAX(0,MIN(1,(Weights!$B$7-M39)/(Weights!$B$7-Weights!$B$6)))) -> 30 | X39: =IF(O39="none",0,IF(O39="unknown",5,Weights!$B$4)) -> 15 | Y39: =IF(K39="",4,IF(AND(K39>=Weights!$B$13,K39<=Weights!$B$14),Weights!$B$5,IF(K39>100,15,IF(K39>=20,12,4)))) -> 4 | Z39: =IF(OR(Q39="taken",Q39="sold",Q39="ruled-out"),0,MIN(IF(AND(H39="tourist-hotel",O39="none"),Weights!$B$11,100),V39+W39+X39+Y39)+IF(R39="yes",Weights!$B$10,0)) -> 60 | AA39: Aug 2026 (Notion)
A40: =RANK(Z40,$Z$2:$Z$78) -> 20 | B40: Harcourt Hotel (residence) | C40: 1105 Larkin St, Nob Hill/TL | D40: Nob Hill/TL | E40: SF-priority | F40: 18 | G40: Notion tracker | H40: sro-hotel | I40: Residence hotel / SRO | J40: Many | L40: ~$200–250/wk | M40: 1000 | N40: =M40*Weights!$B$12 -> 45000 | O40: communal | P40: Shared | Q40: active | R40: unknown | S40: 2 | T40: not-contacted | V40: =IF(LEFT(E40,2)="SF",IF(F40="",0,Weights!$B$2*MAX(0,MIN(1,(Weights!$B$9-F40)/(Weights!$B$9-Weights!$B$8)))),0) -> 27 | W40: =IF(M40="",5,Weights!$B$3*MAX(0,MIN(1,(Weights!$B$7-M40)/(Weights!$B$7-Weights!$B$6)))) -> 30 | X40: =IF(O40="none",0,IF(O40="unknown",5,Weights!$B$4)) -> 15 | Y40: =IF(K40="",4,IF(AND(K40>=Weights!$B$13,K40<=Weights!$B$14),Weights!$B$5,IF(K40>100,15,IF(K40>=20,12,4)))) -> 4 | Z40: =IF(OR(Q40="taken",Q40="sold",Q40="ruled-out"),0,MIN(IF(AND(H40="tourist-hotel",O40="none"),Weights!$B$11,100),V40+W40+X40+Y40)+IF(R40="yes",Weights!$B$10,0)) -> 76 | AA40: Aug 2026 (Notion)
A41: =RANK(Z41,$Z$2:$Z$78) -> 12 | B41: The 6th Collective Coliving | C41: Howard & 6th St, SoMa | D41: SoMa | E41: SF-priority | F41: 5 | G41: Notion tracker | H41: co-living | I41: Co-living | J41: Verify | L41: $1,050 | M41: 1050 | N41: =M41*Weights!$B$12 -> 47250 | O41: communal | P41: Yes (commercial) | Q41: active | R41: unknown | S41: 2 | T41: not-contacted | V41: =IF(LEFT(E41,2)="SF",IF(F41="",0,Weights!$B$2*MAX(0,MIN(1,(Weights!$B$9-F41)/(Weights!$B$9-Weights!$B$8)))),0) -> 35 | W41: =IF(M41="",5,Weights!$B$3*MAX(0,MIN(1,(Weights!$B$7-M41)/(Weights!$B$7-Weights!$B$6)))) -> 28.75 | X41: =IF(O41="none",0,IF(O41="unknown",5,Weights!$B$4)) -> 15 | Y41: =IF(K41="",4,IF(AND(K41>=Weights!$B$13,K41<=Weights!$B$14),Weights!$B$5,IF(K41>100,15,IF(K41>=20,12,4)))) -> 4 | Z41: =IF(OR(Q41="taken",Q41="sold",Q41="ruled-out"),0,MIN(IF(AND(H41="tourist-hotel",O41="none"),Weights!$B$11,100),V41+W41+X41+Y41)+IF(R41="yes",Weights!$B$10,0)) -> 82.75 | AA41: Aug 2026 (Notion)
A42: =RANK(Z42,$Z$2:$Z$78) -> 25 | B42: The Annex at Hayes Valley | C42: 420 Hayes St, Hayes Valley | D42: Hayes Valley | E42: SF-other | F42: 23 | G42: Notion tracker | H42: hostel | I42: Hostel / co-living | J42: Rooms; shared bath | L42: Budget | M42: 1100 | N42: =M42*Weights!$B$12 -> 49500 | O42: communal | P42: Yes (big kitchen) | Q42: active | R42: yes | S42: 2 | T42: not-contacted | V42: =IF(LEFT(E42,2)="SF",IF(F42="",0,Weights!$B$2*MAX(0,MIN(1,(Weights!$B$9-F42)/(Weights!$B$9-Weights!$B$8)))),0) -> 22 | W42: =IF(M42="",5,Weights!$B$3*MAX(0,MIN(1,(Weights!$B$7-M42)/(Weights!$B$7-Weights!$B$6)))) -> 27.5 | X42: =IF(O42="none",0,IF(O42="unknown",5,Weights!$B$4)) -> 15 | Y42: =IF(K42="",4,IF(AND(K42>=Weights!$B$13,K42<=Weights!$B$14),Weights!$B$5,IF(K42>100,15,IF(K42>=20,12,4)))) -> 4 | Z42: =IF(OR(Q42="taken",Q42="sold",Q42="ruled-out"),0,MIN(IF(AND(H42="tourist-hotel",O42="none"),Weights!$B$11,100),V42+W42+X42+Y42)+IF(R42="yes",Weights!$B$10,0)) -> 73.5 | AA42: Aug 2026 (Notion)
A43: =RANK(Z43,$Z$2:$Z$78) -> 15 | B43: UrbaNests 1080 Folsom Residences | C43: 1080 Folsom St, SoMa | D43: SoMa | E43: SF-priority | F43: 9 | G43: Notion tracker | H43: co-living | I43: Co-living | J43: Verify | L43: ~$1,200 verify | M43: 1200 | N43: =M43*Weights!$B$12 -> 54000 | O43: communal | P43: Yes | Q43: active | R43: unknown | S43: 2 | T43: not-contacted | V43: =IF(LEFT(E43,2)="SF",IF(F43="",0,Weights!$B$2*MAX(0,MIN(1,(Weights!$B$9-F43)/(Weights!$B$9-Weights!$B$8)))),0) -> 35 | W43: =IF(M43="",5,Weights!$B$3*MAX(0,MIN(1,(Weights!$B$7-M43)/(Weights!$B$7-Weights!$B$6)))) -> 25 | X43: =IF(O43="none",0,IF(O43="unknown",5,Weights!$B$4)) -> 15 | Y43: =IF(K43="",4,IF(AND(K43>=Weights!$B$13,K43<=Weights!$B$14),Weights!$B$5,IF(K43>100,15,IF(K43>=20,12,4)))) -> 4 | Z43: =IF(OR(Q43="taken",Q43="sold",Q43="ruled-out"),0,MIN(IF(AND(H43="tourist-hotel",O43="none"),Weights!$B$11,100),V43+W43+X43+Y43)+IF(R43="yes",Weights!$B$10,0)) -> 79 | AA43: Aug 2026 (Notion)
A44: =RANK(Z44,$Z$2:$Z$78) -> 32 | B44: Chapter San Francisco | C44: 1533 Franklin St, Cathedral Hill | D44: Cathedral Hill | E44: SF-other | F44: 24 | G44: Notion tracker | H44: hostel | I44: Co-living hostel | J44: Shared+private | L44: Verify | M44: 1200 | N44: =M44*Weights!$B$12 -> 54000 | O44: communal | P44: Yes | Q44: active | R44: unknown | S44: 2 | T44: not-contacted | V44: =IF(LEFT(E44,2)="SF",IF(F44="",0,Weights!$B$2*MAX(0,MIN(1,(Weights!$B$9-F44)/(Weights!$B$9-Weights!$B$8)))),0) -> 21 | W44: =IF(M44="",5,Weights!$B$3*MAX(0,MIN(1,(Weights!$B$7-M44)/(Weights!$B$7-Weights!$B$6)))) -> 25 | X44: =IF(O44="none",0,IF(O44="unknown",5,Weights!$B$4)) -> 15 | Y44: =IF(K44="",4,IF(AND(K44>=Weights!$B$13,K44<=Weights!$B$14),Weights!$B$5,IF(K44>100,15,IF(K44>=20,12,4)))) -> 4 | Z44: =IF(OR(Q44="taken",Q44="sold",Q44="ruled-out"),0,MIN(IF(AND(H44="tourist-hotel",O44="none"),Weights!$B$11,100),V44+W44+X44+Y44)+IF(R44="yes",Weights!$B$10,0)) -> 65 | AA44: Aug 2026 (Notion)
A45: =RANK(Z45,$Z$2:$Z$78) -> 49 | B45: PodShare SF Marina | C45: 2424 Lombard St, Marina | D45: Marina | E45: SF-other | F45: 56 | G45: Notion tracker | H45: hostel | I45: Hostel / co-living pods | J45: Pods | L45: Per-bed | M45: 1200 | N45: =M45*Weights!$B$12 -> 54000 | O45: communal | P45: Yes | Q45: active | R45: yes | S45: 2 | T45: not-contacted | V45: =IF(LEFT(E45,2)="SF",IF(F45="",0,Weights!$B$2*MAX(0,MIN(1,(Weights!$B$9-F45)/(Weights!$B$9-Weights!$B$8)))),0) -> 0 | W45: =IF(M45="",5,Weights!$B$3*MAX(0,MIN(1,(Weights!$B$7-M45)/(Weights!$B$7-Weights!$B$6)))) -> 25 | X45: =IF(O45="none",0,IF(O45="unknown",5,Weights!$B$4)) -> 15 | Y45: =IF(K45="",4,IF(AND(K45>=Weights!$B$13,K45<=Weights!$B$14),Weights!$B$5,IF(K45>100,15,IF(K45>=20,12,4)))) -> 4 | Z45: =IF(OR(Q45="taken",Q45="sold",Q45="ruled-out"),0,MIN(IF(AND(H45="tourist-hotel",O45="none"),Weights!$B$11,100),V45+W45+X45+Y45)+IF(R45="yes",Weights!$B$10,0)) -> 49 | AA45: Aug 2026 (Notion)
A46: =RANK(Z46,$Z$2:$Z$78) -> 43 | B46: 20 Mission SF (20mish) | C46: 3491 20th St, Mission | D46: Mission | E46: SF-other | F46: 45 | G46: Notion tracker | H46: co-living | I46: Co-living / startup | J46: ~40 rooms | K46: 40 | L46: Verify | M46: 1300 | N46: =M46*Weights!$B$12 -> 58500 | O46: communal | P46: Yes | Q46: active | R46: unknown | S46: 2 | T46: not-contacted | V46: =IF(LEFT(E46,2)="SF",IF(F46="",0,Weights!$B$2*MAX(0,MIN(1,(Weights!$B$9-F46)/(Weights!$B$9-Weights!$B$8)))),0) -> 0 | W46: =IF(M46="",5,Weights!$B$3*MAX(0,MIN(1,(Weights!$B$7-M46)/(Weights!$B$7-Weights!$B$6)))) -> 22.5 | X46: =IF(O46="none",0,IF(O46="unknown",5,Weights!$B$4)) -> 15 | Y46: =IF(K46="",4,IF(AND(K46>=Weights!$B$13,K46<=Weights!$B$14),Weights!$B$5,IF(K46>100,15,IF(K46>=20,12,4)))) -> 20 | Z46: =IF(OR(Q46="taken",Q46="sold",Q46="ruled-out"),0,MIN(IF(AND(H46="tourist-hotel",O46="none"),Weights!$B$11,100),V46+W46+X46+Y46)+IF(R46="yes",Weights!$B$10,0)) -> 57.5 | AA46: Aug 2026 (Notion)
A47: =RANK(Z47,$Z$2:$Z$78) -> 48 | B47: Blok Living Lower Haight | C47: 565 Page St, Lower Haight | D47: Lower Haight | E47: SF-other | F47: 35 | G47: Notion tracker | H47: co-living | I47: Co-living | J47: Verify | L47: Verify | M47: 1300 | N47: =M47*Weights!$B$12 -> 58500 | O47: communal | P47: Yes | Q47: active | R47: unknown | S47: 2 | T47: not-contacted | V47: =IF(LEFT(E47,2)="SF",IF(F47="",0,Weights!$B$2*MAX(0,MIN(1,(Weights!$B$9-F47)/(Weights!$B$9-Weights!$B$8)))),0) -> 10 | W47: =IF(M47="",5,Weights!$B$3*MAX(0,MIN(1,(Weights!$B$7-M47)/(Weights!$B$7-Weights!$B$6)))) -> 22.5 | X47: =IF(O47="none",0,IF(O47="unknown",5,Weights!$B$4)) -> 15 | Y47: =IF(K47="",4,IF(AND(K47>=Weights!$B$13,K47<=Weights!$B$14),Weights!$B$5,IF(K47>100,15,IF(K47>=20,12,4)))) -> 4 | Z47: =IF(OR(Q47="taken",Q47="sold",Q47="ruled-out"),0,MIN(IF(AND(H47="tourist-hotel",O47="none"),Weights!$B$11,100),V47+W47+X47+Y47)+IF(R47="yes",Weights!$B$10,0)) -> 51.5 | AA47: Aug 2026 (Notion)
A48: =RANK(Z48,$Z$2:$Z$78) -> 27 | B48: Vantaggio Suites Garland | C48: 505 O'Farrell St, Tenderloin | D48: Tenderloin | E48: SF-priority | F48: 9 | G48: Notion tracker | H48: tourist-hotel | I48: Extended-stay suites | J48: Many | L48: 7-night min; monthly avail | M48: 1400 | N48: =M48*Weights!$B$12 -> 63000 | O48: unknown | P48: Some (fridge/micro) | Q48: active | R48: yes | S48: 2 | T48: not-contacted | V48: =IF(LEFT(E48,2)="SF",IF(F48="",0,Weights!$B$2*MAX(0,MIN(1,(Weights!$B$9-F48)/(Weights!$B$9-Weights!$B$8)))),0) -> 35 | W48: =IF(M48="",5,Weights!$B$3*MAX(0,MIN(1,(Weights!$B$7-M48)/(Weights!$B$7-Weights!$B$6)))) -> 20 | X48: =IF(O48="none",0,IF(O48="unknown",5,Weights!$B$4)) -> 5 | Y48: =IF(K48="",4,IF(AND(K48>=Weights!$B$13,K48<=Weights!$B$14),Weights!$B$5,IF(K48>100,15,IF(K48>=20,12,4)))) -> 4 | Z48: =IF(OR(Q48="taken",Q48="sold",Q48="ruled-out"),0,MIN(IF(AND(H48="tourist-hotel",O48="none"),Weights!$B$11,100),V48+W48+X48+Y48)+IF(R48="yes",Weights!$B$10,0)) -> 69 | AA48: Aug 2026 (Notion)
A49: =RANK(Z49,$Z$2:$Z$78) -> 27 | B49: Vantaggio Suites Abigail | C49: 246 McAllister St, Civic Center | D49: Civic Center | E49: SF-priority | F49: 10 | G49: Notion tracker | H49: tourist-hotel | I49: Extended-stay suites | J49: Many | L49: 7-night min; monthly avail | M49: 1400 | N49: =M49*Weights!$B$12 -> 63000 | O49: unknown | P49: Some (fridge/micro) | Q49: active | R49: yes | S49: 2 | T49: not-contacted | V49: =IF(LEFT(E49,2)="SF",IF(F49="",0,Weights!$B$2*MAX(0,MIN(1,(Weights!$B$9-F49)/(Weights!$B$9-Weights!$B$8)))),0) -> 35 | W49: =IF(M49="",5,Weights!$B$3*MAX(0,MIN(1,(Weights!$B$7-M49)/(Weights!$B$7-Weights!$B$6)))) -> 20 | X49: =IF(O49="none",0,IF(O49="unknown",5,Weights!$B$4)) -> 5 | Y49: =IF(K49="",4,IF(AND(K49>=Weights!$B$13,K49<=Weights!$B$14),Weights!$B$5,IF(K49>100,15,IF(K49>=20,12,4)))) -> 4 | Z49: =IF(OR(Q49="taken",Q49="sold",Q49="ruled-out"),0,MIN(IF(AND(H49="tourist-hotel",O49="none"),Weights!$B$11,100),V49+W49+X49+Y49)+IF(R49="yes",Weights!$B$10,0)) -> 69 | AA49: Aug 2026 (Notion)
A50: =RANK(Z50,$Z$2:$Z$78) -> 60 | B50: Mission Control | C50: 2211 Mission St, Mission | D50: Mission | E50: SF-other | F50: 40 | G50: Notion tracker | H50: co-living | I50: Hacker house | J50: Verify | L50: Verify | M50: 1400 | N50: =M50*Weights!$B$12 -> 63000 | O50: communal | P50: Yes | Q50: active | R50: unknown | S50: 2 | T50: not-contacted | V50: =IF(LEFT(E50,2)="SF",IF(F50="",0,Weights!$B$2*MAX(0,MIN(1,(Weights!$B$9-F50)/(Weights!$B$9-Weights!$B$8)))),0) -> 5 | W50: =IF(M50="",5,Weights!$B$3*MAX(0,MIN(1,(Weights!$B$7-M50)/(Weights!$B$7-Weights!$B$6)))) -> 20 | X50: =IF(O50="none",0,IF(O50="unknown",5,Weights!$B$4)) -> 15 | Y50: =IF(K50="",4,IF(AND(K50>=Weights!$B$13,K50<=Weights!$B$14),Weights!$B$5,IF(K50>100,15,IF(K50>=20,12,4)))) -> 4 | Z50: =IF(OR(Q50="taken",Q50="sold",Q50="ruled-out"),0,MIN(IF(AND(H50="tourist-hotel",O50="none"),Weights!$B$11,100),V50+W50+X50+Y50)+IF(R50="yes",Weights!$B$10,0)) -> 44 | AA50: Aug 2026 (Notion)
A51: =RANK(Z51,$Z$2:$Z$78) -> 68 | B51: The Red Victorian | C51: 1665 Haight St, Haight | D51: Haight | E51: SF-other | F51: 63 | G51: Notion tracker | H51: co-living | I51: Co-living / commune | J51: ~18 rooms | K51: 18 | L51: Verify | M51: 1400 | N51: =M51*Weights!$B$12 -> 63000 | O51: communal | P51: Yes | Q51: active | R51: unknown | S51: 2 | T51: not-contacted | V51: =IF(LEFT(E51,2)="SF",IF(F51="",0,Weights!$B$2*MAX(0,MIN(1,(Weights!$B$9-F51)/(Weights!$B$9-Weights!$B$8)))),0) -> 0 | W51: =IF(M51="",5,Weights!$B$3*MAX(0,MIN(1,(Weights!$B$7-M51)/(Weights!$B$7-Weights!$B$6)))) -> 20 | X51: =IF(O51="none",0,IF(O51="unknown",5,Weights!$B$4)) -> 15 | Y51: =IF(K51="",4,IF(AND(K51>=Weights!$B$13,K51<=Weights!$B$14),Weights!$B$5,IF(K51>100,15,IF(K51>=20,12,4)))) -> 4 | Z51: =IF(OR(Q51="taken",Q51="sold",Q51="ruled-out"),0,MIN(IF(AND(H51="tourist-hotel",O51="none"),Weights!$B$11,100),V51+W51+X51+Y51)+IF(R51="yes",Weights!$B$10,0)) -> 39 | AA51: Aug 2026 (Notion)
A52: =RANK(Z52,$Z$2:$Z$78) -> 66 | B52: Foundry Coliving | C52: 550 Guerrero St, Mission | D52: Mission | E52: SF-other | F52: 42 | G52: Notion tracker | H52: co-living | I52: Founder co-living | J52: ~15–20 | L52: Verify | M52: 1500 | N52: =M52*Weights!$B$12 -> 67500 | O52: communal | P52: Yes | Q52: active | R52: unknown | S52: 2 | T52: not-contacted | V52: =IF(LEFT(E52,2)="SF",IF(F52="",0,Weights!$B$2*MAX(0,MIN(1,(Weights!$B$9-F52)/(Weights!$B$9-Weights!$B$8)))),0) -> 3 | W52: =IF(M52="",5,Weights!$B$3*MAX(0,MIN(1,(Weights!$B$7-M52)/(Weights!$B$7-Weights!$B$6)))) -> 17.5 | X52: =IF(O52="none",0,IF(O52="unknown",5,Weights!$B$4)) -> 15 | Y52: =IF(K52="",4,IF(AND(K52>=Weights!$B$13,K52<=Weights!$B$14),Weights!$B$5,IF(K52>100,15,IF(K52>=20,12,4)))) -> 4 | Z52: =IF(OR(Q52="taken",Q52="sold",Q52="ruled-out"),0,MIN(IF(AND(H52="tourist-hotel",O52="none"),Weights!$B$11,100),V52+W52+X52+Y52)+IF(R52="yes",Weights!$B$10,0)) -> 39.5 | AA52: Aug 2026 (Notion)
A53: =RANK(Z53,$Z$2:$Z$78) -> 66 | B53: Mission Dolores Manor | C53: 822 S Van Ness Ave, Mission | D53: Mission | E53: SF-other | F53: 42 | G53: Notion tracker | H53: co-living | I53: Founder co-living | J53: Verify | L53: Verify | M53: 1500 | N53: =M53*Weights!$B$12 -> 67500 | O53: communal | P53: Yes | Q53: active | R53: unknown | S53: 2 | T53: not-contacted | V53: =IF(LEFT(E53,2)="SF",IF(F53="",0,Weights!$B$2*MAX(0,MIN(1,(Weights!$B$9-F53)/(Weights!$B$9-Weights!$B$8)))),0) -> 3 | W53: =IF(M53="",5,Weights!$B$3*MAX(0,MIN(1,(Weights!$B$7-M53)/(Weights!$B$7-Weights!$B$6)))) -> 17.5 | X53: =IF(O53="none",0,IF(O53="unknown",5,Weights!$B$4)) -> 15 | Y53: =IF(K53="",4,IF(AND(K53>=Weights!$B$13,K53<=Weights!$B$14),Weights!$B$5,IF(K53>100,15,IF(K53>=20,12,4)))) -> 4 | Z53: =IF(OR(Q53="taken",Q53="sold",Q53="ruled-out"),0,MIN(IF(AND(H53="tourist-hotel",O53="none"),Weights!$B$11,100),V53+W53+X53+Y53)+IF(R53="yes",Weights!$B$10,0)) -> 39.5 | AA53: Aug 2026 (Notion)
A54: =RANK(Z54,$Z$2:$Z$78) -> 36 | B54: Vybe Living (operator) | C54: SoMa / TL / Mission rooms | D54: SoMa / TL / Mission rooms | E54: SF-priority | F54: 18 | G54: Notion tracker | H54: co-living | I54: Co-living operator | J54: Many rooms | L54: $1,200–1,800 | M54: 1500 | N54: =M54*Weights!$B$12 -> 67500 | O54: communal | P54: Yes | Q54: active | R54: unknown | S54: 2 | T54: not-contacted | V54: =IF(LEFT(E54,2)="SF",IF(F54="",0,Weights!$B$2*MAX(0,MIN(1,(Weights!$B$9-F54)/(Weights!$B$9-Weights!$B$8)))),0) -> 27 | W54: =IF(M54="",5,Weights!$B$3*MAX(0,MIN(1,(Weights!$B$7-M54)/(Weights!$B$7-Weights!$B$6)))) -> 17.5 | X54: =IF(O54="none",0,IF(O54="unknown",5,Weights!$B$4)) -> 15 | Y54: =IF(K54="",4,IF(AND(K54>=Weights!$B$13,K54<=Weights!$B$14),Weights!$B$5,IF(K54>100,15,IF(K54>=20,12,4)))) -> 4 | Z54: =IF(OR(Q54="taken",Q54="sold",Q54="ruled-out"),0,MIN(IF(AND(H54="tourist-hotel",O54="none"),Weights!$B$11,100),V54+W54+X54+Y54)+IF(R54="yes",Weights!$B$10,0)) -> 63.5 | AA54: Aug 2026 (Notion)
A55: =RANK(Z55,$Z$2:$Z$78) -> 46 | B55: Monroe Residence Club | C55: 1870 Sacramento St, Nob Hill | D55: Nob Hill | E55: SF-priority | F55: 27 | G55: Notion tracker | H55: sro-hotel | I55: Residence club (meals) | J55: Many | L55: Verify (incl. meals) | M55: 1600 | N55: =M55*Weights!$B$12 -> 72000 | O55: communal | P55: Meals incl. | Q55: active | R55: unknown | S55: 2 | T55: not-contacted | V55: =IF(LEFT(E55,2)="SF",IF(F55="",0,Weights!$B$2*MAX(0,MIN(1,(Weights!$B$9-F55)/(Weights!$B$9-Weights!$B$8)))),0) -> 18 | W55: =IF(M55="",5,Weights!$B$3*MAX(0,MIN(1,(Weights!$B$7-M55)/(Weights!$B$7-Weights!$B$6)))) -> 15 | X55: =IF(O55="none",0,IF(O55="unknown",5,Weights!$B$4)) -> 15 | Y55: =IF(K55="",4,IF(AND(K55>=Weights!$B$13,K55<=Weights!$B$14),Weights!$B$5,IF(K55>100,15,IF(K55>=20,12,4)))) -> 4 | Z55: =IF(OR(Q55="taken",Q55="sold",Q55="ruled-out"),0,MIN(IF(AND(H55="tourist-hotel",O55="none"),Weights!$B$11,100),V55+W55+X55+Y55)+IF(R55="yes",Weights!$B$10,0)) -> 52 | AA55: Aug 2026 (Notion)
A56: =RANK(Z56,$Z$2:$Z$78) -> 63 | B56: Neighbourgood Mission | C56: 2072 Mission St, Mission | D56: Mission | E56: SF-other | F56: 37 | G56: Notion tracker | H56: tourist-hotel | I56: Co-living / aparthotel | J56: Verify | L56: Verify | M56: 1600 | N56: =M56*Weights!$B$12 -> 72000 | O56: communal | P56: Yes | Q56: active | R56: unknown | S56: 2 | T56: not-contacted | V56: =IF(LEFT(E56,2)="SF",IF(F56="",0,Weights!$B$2*MAX(0,MIN(1,(Weights!$B$9-F56)/(Weights!$B$9-Weights!$B$8)))),0) -> 8 | W56: =IF(M56="",5,Weights!$B$3*MAX(0,MIN(1,(Weights!$B$7-M56)/(Weights!$B$7-Weights!$B$6)))) -> 15 | X56: =IF(O56="none",0,IF(O56="unknown",5,Weights!$B$4)) -> 15 | Y56: =IF(K56="",4,IF(AND(K56>=Weights!$B$13,K56<=Weights!$B$14),Weights!$B$5,IF(K56>100,15,IF(K56>=20,12,4)))) -> 4 | Z56: =IF(OR(Q56="taken",Q56="sold",Q56="ruled-out"),0,MIN(IF(AND(H56="tourist-hotel",O56="none"),Weights!$B$11,100),V56+W56+X56+Y56)+IF(R56="yes",Weights!$B$10,0)) -> 42 | AA56: Aug 2026 (Notion)
A57: =RANK(Z57,$Z$2:$Z$78) -> 55 | B57: Globe Hotel SoMa | C57: 10 Hallam St, SoMa | D57: SoMa | E57: SF-priority | F57: 12 | G57: Notion tracker | H57: tourist-hotel | I57: Budget hotel | J57: Small | L57: Nightly; ask monthly | M57: 1800 | N57: =M57*Weights!$B$12 -> 81000 | O57: none | P57: No (breakfast incl.) | Q57: active | R57: yes | S57: 2 | T57: not-contacted | V57: =IF(LEFT(E57,2)="SF",IF(F57="",0,Weights!$B$2*MAX(0,MIN(1,(Weights!$B$9-F57)/(Weights!$B$9-Weights!$B$8)))),0) -> 33 | W57: =IF(M57="",5,Weights!$B$3*MAX(0,MIN(1,(Weights!$B$7-M57)/(Weights!$B$7-Weights!$B$6)))) -> 10 | X57: =IF(O57="none",0,IF(O57="unknown",5,Weights!$B$4)) -> 0 | Y57: =IF(K57="",4,IF(AND(K57>=Weights!$B$13,K57<=Weights!$B$14),Weights!$B$5,IF(K57>100,15,IF(K57>=20,12,4)))) -> 4 | Z57: =IF(OR(Q57="taken",Q57="sold",Q57="ruled-out"),0,MIN(IF(AND(H57="tourist-hotel",O57="none"),Weights!$B$11,100),V57+W57+X57+Y57)+IF(R57="yes",Weights!$B$10,0)) -> 45 | AA57: Aug 2026 (Notion)
A58: =RANK(Z58,$Z$2:$Z$78) -> 52 | B58: Kenmore Residence Hotel | C58: 1570 Sutter St, Lower Nob Hill | D58: Lower Nob Hill | E58: SF-priority | F58: 26 | G58: Notion tracker | H58: sro-hotel | I58: Residence hotel (meals) | J58: Many | L58: ~$75/night w/ meals | M58: 1800 | N58: =M58*Weights!$B$12 -> 81000 | O58: communal | P58: Meals incl. | Q58: active | R58: unknown | S58: 2 | T58: not-contacted | V58: =IF(LEFT(E58,2)="SF",IF(F58="",0,Weights!$B$2*MAX(0,MIN(1,(Weights!$B$9-F58)/(Weights!$B$9-Weights!$B$8)))),0) -> 19 | W58: =IF(M58="",5,Weights!$B$3*MAX(0,MIN(1,(Weights!$B$7-M58)/(Weights!$B$7-Weights!$B$6)))) -> 10 | X58: =IF(O58="none",0,IF(O58="unknown",5,Weights!$B$4)) -> 15 | Y58: =IF(K58="",4,IF(AND(K58>=Weights!$B$13,K58<=Weights!$B$14),Weights!$B$5,IF(K58>100,15,IF(K58>=20,12,4)))) -> 4 | Z58: =IF(OR(Q58="taken",Q58="sold",Q58="ruled-out"),0,MIN(IF(AND(H58="tourist-hotel",O58="none"),Weights!$B$11,100),V58+W58+X58+Y58)+IF(R58="yes",Weights!$B$10,0)) -> 48 | AA58: Aug 2026 (Notion)
A59: =RANK(Z59,$Z$2:$Z$78) -> 44 | B59: The Mosser Hotel | C59: 54 4th St, SoMa | D59: SoMa | E59: SF-priority | F59: 7 | G59: Notion tracker | H59: tourist-hotel | I59: Budget hotel | J59: Large; shared+private | L59: Nightly; ask monthly | M59: 2000 | N59: =M59*Weights!$B$12 -> 90000 | O59: unknown | P59: Shared (limited) | Q59: active | R59: yes | S59: 2 | T59: not-contacted | V59: =IF(LEFT(E59,2)="SF",IF(F59="",0,Weights!$B$2*MAX(0,MIN(1,(Weights!$B$9-F59)/(Weights!$B$9-Weights!$B$8)))),0) -> 35 | W59: =IF(M59="",5,Weights!$B$3*MAX(0,MIN(1,(Weights!$B$7-M59)/(Weights!$B$7-Weights!$B$6)))) -> 5 | X59: =IF(O59="none",0,IF(O59="unknown",5,Weights!$B$4)) -> 5 | Y59: =IF(K59="",4,IF(AND(K59>=Weights!$B$13,K59<=Weights!$B$14),Weights!$B$5,IF(K59>100,15,IF(K59>=20,12,4)))) -> 4 | Z59: =IF(OR(Q59="taken",Q59="sold",Q59="ruled-out"),0,MIN(IF(AND(H59="tourist-hotel",O59="none"),Weights!$B$11,100),V59+W59+X59+Y59)+IF(R59="yes",Weights!$B$10,0)) -> 54 | AA59: Aug 2026 (Notion)
A60: =RANK(Z60,$Z$2:$Z$78) -> 71 | B60: Larkspur Landing Extended Stay | C60: 690 Gateway Blvd, South SF | D60: South SF | E60: Peninsula | F60: 225 | G60: Notion tracker | H60: tourist-hotel | I60: Extended-stay suites | J60: Many suites | L60: Nightly; weekly disc. | M60: 2000 | N60: =M60*Weights!$B$12 -> 90000 | O60: private | P60: Yes (full kitchen) | Q60: active | R60: yes | S60: 2 | T60: not-contacted | V60: =IF(LEFT(E60,2)="SF",IF(F60="",0,Weights!$B$2*MAX(0,MIN(1,(Weights!$B$9-F60)/(Weights!$B$9-Weights!$B$8)))),0) -> 0 | W60: =IF(M60="",5,Weights!$B$3*MAX(0,MIN(1,(Weights!$B$7-M60)/(Weights!$B$7-Weights!$B$6)))) -> 5 | X60: =IF(O60="none",0,IF(O60="unknown",5,Weights!$B$4)) -> 15 | Y60: =IF(K60="",4,IF(AND(K60>=Weights!$B$13,K60<=Weights!$B$14),Weights!$B$5,IF(K60>100,15,IF(K60>=20,12,4)))) -> 4 | Z60: =IF(OR(Q60="taken",Q60="sold",Q60="ruled-out"),0,MIN(IF(AND(H60="tourist-hotel",O60="none"),Weights!$B$11,100),V60+W60+X60+Y60)+IF(R60="yes",Weights!$B$10,0)) -> 29 | AA60: Aug 2026 (Notion)
A61: =RANK(Z61,$Z$2:$Z$78) -> 34 | B61: SOMA Residences | C61: 1045 Mission St, SoMa | D61: SoMa | E61: SF-other | F61: 5 | G61: Notion tracker | H61: apartment-block | I61: Apartments (market) | J61: 93 units | K61: 93 | L61: Verify ($2k+ studio) | M61: 2100 | N61: =M61*Weights!$B$12 -> 94500 | O61: private | P61: Yes (in-unit) | Q61: active | R61: unknown | S61: 2 | T61: not-contacted | V61: =IF(LEFT(E61,2)="SF",IF(F61="",0,Weights!$B$2*MAX(0,MIN(1,(Weights!$B$9-F61)/(Weights!$B$9-Weights!$B$8)))),0) -> 35 | W61: =IF(M61="",5,Weights!$B$3*MAX(0,MIN(1,(Weights!$B$7-M61)/(Weights!$B$7-Weights!$B$6)))) -> 2.5 | X61: =IF(O61="none",0,IF(O61="unknown",5,Weights!$B$4)) -> 15 | Y61: =IF(K61="",4,IF(AND(K61>=Weights!$B$13,K61<=Weights!$B$14),Weights!$B$5,IF(K61>100,15,IF(K61>=20,12,4)))) -> 12 | Z61: =IF(OR(Q61="taken",Q61="sold",Q61="ruled-out"),0,MIN(IF(AND(H61="tourist-hotel",O61="none"),Weights!$B$11,100),V61+W61+X61+Y61)+IF(R61="yes",Weights!$B$10,0)) -> 64.5 | AA61: Aug 2026 (Notion)
A62: =RANK(Z62,$Z$2:$Z$78) -> 55 | B62: Hotel Fiona | C62: 140 7th St, SoMa | D62: SoMa | E62: SF-priority | F62: 7 | G62: Notion tracker | H62: tourist-hotel | I62: Boutique hotel | J62: ~50 rooms | K62: 50 | L62: Nightly; ask monthly | M62: 2200 | N62: =M62*Weights!$B$12 -> 99000 | O62: none | P62: No (breakfast incl.) | Q62: active | R62: yes | S62: 2 | T62: not-contacted | V62: =IF(LEFT(E62,2)="SF",IF(F62="",0,Weights!$B$2*MAX(0,MIN(1,(Weights!$B$9-F62)/(Weights!$B$9-Weights!$B$8)))),0) -> 35 | W62: =IF(M62="",5,Weights!$B$3*MAX(0,MIN(1,(Weights!$B$7-M62)/(Weights!$B$7-Weights!$B$6)))) -> 0 | X62: =IF(O62="none",0,IF(O62="unknown",5,Weights!$B$4)) -> 0 | Y62: =IF(K62="",4,IF(AND(K62>=Weights!$B$13,K62<=Weights!$B$14),Weights!$B$5,IF(K62>100,15,IF(K62>=20,12,4)))) -> 20 | Z62: =IF(OR(Q62="taken",Q62="sold",Q62="ruled-out"),0,MIN(IF(AND(H62="tourist-hotel",O62="none"),Weights!$B$11,100),V62+W62+X62+Y62)+IF(R62="yes",Weights!$B$10,0)) -> 45 | AA62: Aug 2026 (Notion)
A63: =RANK(Z63,$Z$2:$Z$78) -> 46 | B63: Furnished Quarters SF | C63: 1162 Folsom St, SoMa | D63: SoMa | E63: SF-priority | F63: 12 | G63: Notion tracker | H63: co-living | I63: Furnished corp apts | J63: Verify | L63: Verify (corporate) | M63: 2500 | N63: =M63*Weights!$B$12 -> 112500 | O63: private | P63: Yes (in-unit) | Q63: active | R63: unknown | S63: 2 | T63: not-contacted | V63: =IF(LEFT(E63,2)="SF",IF(F63="",0,Weights!$B$2*MAX(0,MIN(1,(Weights!$B$9-F63)/(Weights!$B$9-Weights!$B$8)))),0) -> 33 | W63: =IF(M63="",5,Weights!$B$3*MAX(0,MIN(1,(Weights!$B$7-M63)/(Weights!$B$7-Weights!$B$6)))) -> 0 | X63: =IF(O63="none",0,IF(O63="unknown",5,Weights!$B$4)) -> 15 | Y63: =IF(K63="",4,IF(AND(K63>=Weights!$B$13,K63<=Weights!$B$14),Weights!$B$5,IF(K63>100,15,IF(K63>=20,12,4)))) -> 4 | Z63: =IF(OR(Q63="taken",Q63="sold",Q63="ruled-out"),0,MIN(IF(AND(H63="tourist-hotel",O63="none"),Weights!$B$11,100),V63+W63+X63+Y63)+IF(R63="yes",Weights!$B$10,0)) -> 52 | AA63: Aug 2026 (Notion)
A64: =RANK(Z64,$Z$2:$Z$78) -> 55 | B64: Villa Nob Hill Furnished Apts | C64: 1124 Leavenworth St, Nob Hill | D64: Nob Hill | E64: SF-priority | F64: 19 | G64: Notion tracker | H64: apartment-block | I64: Furnished apartments | J64: Several 2BR | L64: Verify (per apt) | M64: 2500 | N64: =M64*Weights!$B$12 -> 112500 | O64: private | P64: Yes (in-unit) | Q64: active | R64: unknown | S64: 2 | T64: not-contacted | V64: =IF(LEFT(E64,2)="SF",IF(F64="",0,Weights!$B$2*MAX(0,MIN(1,(Weights!$B$9-F64)/(Weights!$B$9-Weights!$B$8)))),0) -> 26 | W64: =IF(M64="",5,Weights!$B$3*MAX(0,MIN(1,(Weights!$B$7-M64)/(Weights!$B$7-Weights!$B$6)))) -> 0 | X64: =IF(O64="none",0,IF(O64="unknown",5,Weights!$B$4)) -> 15 | Y64: =IF(K64="",4,IF(AND(K64>=Weights!$B$13,K64<=Weights!$B$14),Weights!$B$5,IF(K64>100,15,IF(K64>=20,12,4)))) -> 4 | Z64: =IF(OR(Q64="taken",Q64="sold",Q64="ruled-out"),0,MIN(IF(AND(H64="tourist-hotel",O64="none"),Weights!$B$11,100),V64+W64+X64+Y64)+IF(R64="yes",Weights!$B$10,0)) -> 45 | AA64: Aug 2026 (Notion)
A65: =RANK(Z65,$Z$2:$Z$78) -> 44 | B65: Prism | C65: 1028 Market St, Mid-Market | D65: Mid-Market | E65: SF-priority | F65: 3 | G65: Notion tracker | H65: apartment-block | I65: Apartments (market) | J65: 90+ units | L65: Verify | M65: 2600 | N65: =M65*Weights!$B$12 -> 117000 | O65: private | P65: Yes (in-unit) | Q65: active | R65: unknown | S65: 2 | T65: not-contacted | V65: =IF(LEFT(E65,2)="SF",IF(F65="",0,Weights!$B$2*MAX(0,MIN(1,(Weights!$B$9-F65)/(Weights!$B$9-Weights!$B$8)))),0) -> 35 | W65: =IF(M65="",5,Weights!$B$3*MAX(0,MIN(1,(Weights!$B$7-M65)/(Weights!$B$7-Weights!$B$6)))) -> 0 | X65: =IF(O65="none",0,IF(O65="unknown",5,Weights!$B$4)) -> 15 | Y65: =IF(K65="",4,IF(AND(K65>=Weights!$B$13,K65<=Weights!$B$14),Weights!$B$5,IF(K65>100,15,IF(K65>=20,12,4)))) -> 4 | Z65: =IF(OR(Q65="taken",Q65="sold",Q65="ruled-out"),0,MIN(IF(AND(H65="tourist-hotel",O65="none"),Weights!$B$11,100),V65+W65+X65+Y65)+IF(R65="yes",Weights!$B$10,0)) -> 54 | AA65: Aug 2026 (Notion)
A66: =RANK(Z66,$Z$2:$Z$78) -> 55 | B66: Nob Hill Place | C66: 1155 Jones St, Nob Hill | D66: Nob Hill | E66: SF-priority | F66: 19 | G66: Notion tracker | H66: apartment-block | I66: Apartments | J66: Verify | L66: Verify (market) | M66: 2600 | N66: =M66*Weights!$B$12 -> 117000 | O66: private | P66: Yes (in-unit) | Q66: active | R66: unknown | S66: 2 | T66: not-contacted | V66: =IF(LEFT(E66,2)="SF",IF(F66="",0,Weights!$B$2*MAX(0,MIN(1,(Weights!$B$9-F66)/(Weights!$B$9-Weights!$B$8)))),0) -> 26 | W66: =IF(M66="",5,Weights!$B$3*MAX(0,MIN(1,(Weights!$B$7-M66)/(Weights!$B$7-Weights!$B$6)))) -> 0 | X66: =IF(O66="none",0,IF(O66="unknown",5,Weights!$B$4)) -> 15 | Y66: =IF(K66="",4,IF(AND(K66>=Weights!$B$13,K66<=Weights!$B$14),Weights!$B$5,IF(K66>100,15,IF(K66>=20,12,4)))) -> 4 | Z66: =IF(OR(Q66="taken",Q66="sold",Q66="ruled-out"),0,MIN(IF(AND(H66="tourist-hotel",O66="none"),Weights!$B$11,100),V66+W66+X66+Y66)+IF(R66="yes",Weights!$B$10,0)) -> 45 | AA66: Aug 2026 (Notion)
A67: =RANK(Z67,$Z$2:$Z$78) -> 60 | B67: Nob Hill Tower | C67: 1221 Jones St, Nob Hill | D67: Nob Hill | E67: SF-priority | F67: 20 | G67: Notion tracker | H67: apartment-block | I67: Apartments | J67: 41+ units | L67: Verify (market) | M67: 2700 | N67: =M67*Weights!$B$12 -> 121500 | O67: private | P67: Yes (in-unit) | Q67: active | R67: unknown | S67: 2 | T67: not-contacted | V67: =IF(LEFT(E67,2)="SF",IF(F67="",0,Weights!$B$2*MAX(0,MIN(1,(Weights!$B$9-F67)/(Weights!$B$9-Weights!$B$8)))),0) -> 25 | W67: =IF(M67="",5,Weights!$B$3*MAX(0,MIN(1,(Weights!$B$7-M67)/(Weights!$B$7-Weights!$B$6)))) -> 0 | X67: =IF(O67="none",0,IF(O67="unknown",5,Weights!$B$4)) -> 15 | Y67: =IF(K67="",4,IF(AND(K67>=Weights!$B$13,K67<=Weights!$B$14),Weights!$B$5,IF(K67>100,15,IF(K67>=20,12,4)))) -> 4 | Z67: =IF(OR(Q67="taken",Q67="sold",Q67="ruled-out"),0,MIN(IF(AND(H67="tourist-hotel",O67="none"),Weights!$B$11,100),V67+W67+X67+Y67)+IF(R67="yes",Weights!$B$10,0)) -> 44 | AA67: Aug 2026 (Notion)
A68: =RANK(Z68,$Z$2:$Z$78) -> 74 | B68: VELA Marina | C68: 2353 Lombard St, Marina | D68: Marina | E68: SF-other | F68: 54 | G68: Notion tracker | H68: apartment-block | I68: Apartments | J68: Verify | L68: Verify (market) | M68: 3000 | N68: =M68*Weights!$B$12 -> 135000 | O68: private | P68: Yes (in-unit) | Q68: active | R68: unknown | S68: 2 | T68: not-contacted | V68: =IF(LEFT(E68,2)="SF",IF(F68="",0,Weights!$B$2*MAX(0,MIN(1,(Weights!$B$9-F68)/(Weights!$B$9-Weights!$B$8)))),0) -> 0 | W68: =IF(M68="",5,Weights!$B$3*MAX(0,MIN(1,(Weights!$B$7-M68)/(Weights!$B$7-Weights!$B$6)))) -> 0 | X68: =IF(O68="none",0,IF(O68="unknown",5,Weights!$B$4)) -> 15 | Y68: =IF(K68="",4,IF(AND(K68>=Weights!$B$13,K68<=Weights!$B$14),Weights!$B$5,IF(K68>100,15,IF(K68>=20,12,4)))) -> 4 | Z68: =IF(OR(Q68="taken",Q68="sold",Q68="ruled-out"),0,MIN(IF(AND(H68="tourist-hotel",O68="none"),Weights!$B$11,100),V68+W68+X68+Y68)+IF(R68="yes",Weights!$B$10,0)) -> 19 | AA68: Aug 2026 (Notion)
A69: =RANK(Z69,$Z$2:$Z$78) -> 73 | B69: O&M Apartments | C69: 680 Indiana St, Dogpatch | D69: Dogpatch | E69: SF-other | F69: 44 | G69: Notion tracker | H69: apartment-block | I69: Apartments | J69: 38+ units | L69: Verify (market) | M69: 3000 | N69: =M69*Weights!$B$12 -> 135000 | O69: private | P69: Yes (in-unit) | Q69: active | R69: unknown | S69: 2 | T69: not-contacted | V69: =IF(LEFT(E69,2)="SF",IF(F69="",0,Weights!$B$2*MAX(0,MIN(1,(Weights!$B$9-F69)/(Weights!$B$9-Weights!$B$8)))),0) -> 1 | W69: =IF(M69="",5,Weights!$B$3*MAX(0,MIN(1,(Weights!$B$7-M69)/(Weights!$B$7-Weights!$B$6)))) -> 0 | X69: =IF(O69="none",0,IF(O69="unknown",5,Weights!$B$4)) -> 15 | Y69: =IF(K69="",4,IF(AND(K69>=Weights!$B$13,K69<=Weights!$B$14),Weights!$B$5,IF(K69>100,15,IF(K69>=20,12,4)))) -> 4 | Z69: =IF(OR(Q69="taken",Q69="sold",Q69="ruled-out"),0,MIN(IF(AND(H69="tourist-hotel",O69="none"),Weights!$B$11,100),V69+W69+X69+Y69)+IF(R69="yes",Weights!$B$10,0)) -> 20 | AA69: Aug 2026 (Notion)
A70: =RANK(Z70,$Z$2:$Z$78) -> 72 | B70: Suites at Fisherman's Wharf | C70: 2655 Hyde St, Fisherman's Wharf | D70: Fisherman's Wharf | E70: SF-other | F70: 45 | G70: Notion tracker | H70: tourist-hotel | I70: Suite hotel (full kitchen) | J70: Suites | L70: Nightly; ask monthly | M70: 3000 | N70: =M70*Weights!$B$12 -> 135000 | O70: private | P70: Yes (full kitchen) | Q70: active | R70: yes | S70: 2 | T70: not-contacted | V70: =IF(LEFT(E70,2)="SF",IF(F70="",0,Weights!$B$2*MAX(0,MIN(1,(Weights!$B$9-F70)/(Weights!$B$9-Weights!$B$8)))),0) -> 0 | W70: =IF(M70="",5,Weights!$B$3*MAX(0,MIN(1,(Weights!$B$7-M70)/(Weights!$B$7-Weights!$B$6)))) -> 0 | X70: =IF(O70="none",0,IF(O70="unknown",5,Weights!$B$4)) -> 15 | Y70: =IF(K70="",4,IF(AND(K70>=Weights!$B$13,K70<=Weights!$B$14),Weights!$B$5,IF(K70>100,15,IF(K70>=20,12,4)))) -> 4 | Z70: =IF(OR(Q70="taken",Q70="sold",Q70="ruled-out"),0,MIN(IF(AND(H70="tourist-hotel",O70="none"),Weights!$B$11,100),V70+W70+X70+Y70)+IF(R70="yes",Weights!$B$10,0)) -> 24 | AA70: Aug 2026 (Notion)
A71: =RANK(Z71,$Z$2:$Z$78) -> 74 | B71: Windsor at Dogpatch | C71: 2660 3rd St, Dogpatch | D71: Dogpatch | E71: SF-other | F71: 56 | G71: Notion tracker | H71: apartment-block | I71: Apartments | J71: 125+ units | L71: Verify (market) | M71: 3100 | N71: =M71*Weights!$B$12 -> 139500 | O71: private | P71: Yes (in-unit) | Q71: active | R71: unknown | S71: 2 | T71: not-contacted | V71: =IF(LEFT(E71,2)="SF",IF(F71="",0,Weights!$B$2*MAX(0,MIN(1,(Weights!$B$9-F71)/(Weights!$B$9-Weights!$B$8)))),0) -> 0 | W71: =IF(M71="",5,Weights!$B$3*MAX(0,MIN(1,(Weights!$B$7-M71)/(Weights!$B$7-Weights!$B$6)))) -> 0 | X71: =IF(O71="none",0,IF(O71="unknown",5,Weights!$B$4)) -> 15 | Y71: =IF(K71="",4,IF(AND(K71>=Weights!$B$13,K71<=Weights!$B$14),Weights!$B$5,IF(K71>100,15,IF(K71>=20,12,4)))) -> 4 | Z71: =IF(OR(Q71="taken",Q71="sold",Q71="ruled-out"),0,MIN(IF(AND(H71="tourist-hotel",O71="none"),Weights!$B$11,100),V71+W71+X71+Y71)+IF(R71="yes",Weights!$B$10,0)) -> 19 | AA71: Aug 2026 (Notion)
A72: =RANK(Z72,$Z$2:$Z$78) -> 49 | B72: The Pinnacle at Nob Hill | C72: 899 Pine St, Nob Hill | D72: Nob Hill | E72: SF-priority | F72: 15 | G72: Notion tracker | H72: apartment-block | I72: Apartments (upscale) | J72: 61+ units | L72: Verify (market, high) | M72: 3200 | N72: =M72*Weights!$B$12 -> 144000 | O72: private | P72: Yes (in-unit) | Q72: active | R72: unknown | S72: 2 | T72: not-contacted | V72: =IF(LEFT(E72,2)="SF",IF(F72="",0,Weights!$B$2*MAX(0,MIN(1,(Weights!$B$9-F72)/(Weights!$B$9-Weights!$B$8)))),0) -> 30 | W72: =IF(M72="",5,Weights!$B$3*MAX(0,MIN(1,(Weights!$B$7-M72)/(Weights!$B$7-Weights!$B$6)))) -> 0 | X72: =IF(O72="none",0,IF(O72="unknown",5,Weights!$B$4)) -> 15 | Y72: =IF(K72="",4,IF(AND(K72>=Weights!$B$13,K72<=Weights!$B$14),Weights!$B$5,IF(K72>100,15,IF(K72>=20,12,4)))) -> 4 | Z72: =IF(OR(Q72="taken",Q72="sold",Q72="ruled-out"),0,MIN(IF(AND(H72="tourist-hotel",O72="none"),Weights!$B$11,100),V72+W72+X72+Y72)+IF(R72="yes",Weights!$B$10,0)) -> 49 | AA72: Aug 2026 (Notion)
A73: =RANK(Z73,$Z$2:$Z$78) -> 54 | B73: Landing Furnished Apts | C73: 215 2nd St, SoMa | D73: SoMa | E73: SF-priority | F73: 18 | G73: Notion tracker | H73: apartment-block | I73: Furnished apartments | J73: Many units | L73: Verify (membership) | M73: 3200 | N73: =M73*Weights!$B$12 -> 144000 | O73: private | P73: Yes (in-unit) | Q73: active | R73: unknown | S73: 2 | T73: not-contacted | V73: =IF(LEFT(E73,2)="SF",IF(F73="",0,Weights!$B$2*MAX(0,MIN(1,(Weights!$B$9-F73)/(Weights!$B$9-Weights!$B$8)))),0) -> 27 | W73: =IF(M73="",5,Weights!$B$3*MAX(0,MIN(1,(Weights!$B$7-M73)/(Weights!$B$7-Weights!$B$6)))) -> 0 | X73: =IF(O73="none",0,IF(O73="unknown",5,Weights!$B$4)) -> 15 | Y73: =IF(K73="",4,IF(AND(K73>=Weights!$B$13,K73<=Weights!$B$14),Weights!$B$5,IF(K73>100,15,IF(K73>=20,12,4)))) -> 4 | Z73: =IF(OR(Q73="taken",Q73="sold",Q73="ruled-out"),0,MIN(IF(AND(H73="tourist-hotel",O73="none"),Weights!$B$11,100),V73+W73+X73+Y73)+IF(R73="yes",Weights!$B$10,0)) -> 46 | AA73: Aug 2026 (Notion)
